{
  "batch_num": 2,
  "batch_size": 30,
  "created_at": "2026-01-17T19:43:01.186169",
  "cases": [
    {
      "case_id": 291979,
      "score": 5,
      "score_decimal": "9.6",
      "favourite": 78,
      "company_name": "W+K 波特兰 美国",
      "company_logo": "https://oss.adquan.com/logos/1524822390436168.jpg",
      "thumb": "https://oss.adquan.com/upload/20200225/15826036324214e821c0124edc.jpg",
      "source_url": "https://m.adquan.com/creative/detail/291979",
      "title": "耐克致敬科比：永远的黑曼巴",
      "description": "2月24日上午10点，科比·布莱恩特及女儿gigi的追悼会在洛杉矶的斯台普斯中心举行，科比的父母、妻子瓦妮莎、迈克尔·乔丹等亲人挚友共同为科比送上最后一程。 在迈克尔·乔丹上台讲话之前，屏幕上播出了一段耐克致敬科比的短片： 全片没有出现任何画面，只有声音和“Forever”串联起科比的人生经历，回顾了科比传奇的一生，从高中崭露头角到湖人队历史性的胜利，从经历事业低谷到人生每一个高光时刻，不管是球场上还是生活中，他身上的黑曼巴精神将永远鼓舞着人们。 仅有声音就足够勾起人们的情感共鸣，因为这些画面和场景早就印在人们的心里。耐克用一支简单却有力量的短片表达出品牌对科比的敬意，历史定格，科比的传奇以及黑曼巴精神永存。",
      "main_image": "https://oss.adquan.com/upload/20200225/15826036324214e821c0124edc.jpg",
      "images": [
        "https://file.adquan.com/uploads_img/4pcrg1582604467.jpg"
      ],
      "video_url": "https://v.qq.com/txp/iframe/player.html?vid=h3071ej8nuk&tiny=0&auto=0",
      "author": "heying",
      "publish_time": "2020-02-26",
      "brand_industry": "时尚、美妆",
      "activity_type": "影视",
      "location": "美国",
      "tags": [
        "耐克",
        "科比"
      ]
    },
    {
      "case_id": 47577,
      "score": 5,
      "score_decimal": "9.7",
      "favourite": 127,
      "thumb": "https://oss.adquan.com/upload/20181211/1544521663014d36631af8a81d.jpg",
      "source_url": "https://m.adquan.com/creative/detail/47577",
      "title": "今年最萌的圣诞广告，1分钟让你暖到心底",
      "description": "每年的圣诞季广告中，总会冒出几枚威力强劲的催泪弹，除了John Lewis以外，今年这部动画广告也让人暖心中带着满满的感动。这部短片，是奥地利Erste Group Bank和德国Sparkasse银行联合出品的一支圣诞公益广告。 就算你满身是刺，也一定有人融化你的盔甲来爱你。这支广告上线５天就在Youtube上突破千万点击。短片描述一只转到新学校的小刺猬，想跟别的同学做朋友，身上的刺却让他屡屡受挫。故事的结局有着令人意想不到的温暖：小伙伴们在圣诞节那天送给了小刺猬一份很特别的礼物，有了这份礼物，小刺猬终于可以无所顾忌地和别人拥抱玩耍。 虽然故事很简单，却恰巧击中了人们最柔软的地方，吸引了无数网友的转发评论。",
      "main_image": "https://oss.adquan.com/upload/20181211/1544521663014d36631af8a81d.jpg",
      "images": [
        "http://file.adquan.com/uploads_img/aztok1544521413.gif"
      ],
      "video_url": "https://v.qq.com/txp/iframe/player.html?vid=p0811g0qi5r&tiny=0&auto=0",
      "author": "王晶",
      "publish_time": "2018-12-12",
      "brand_industry": "金融、保险",
      "activity_type": "影视",
      "location": "欧洲",
      "tags": [
        "圣诞广告"
      ]
    },
    {
      "case_id": 45477,
      "score": 5,
      "score_decimal": "9.1",
      "favourite": 207,
      "thumb": "https://oss.adquan.com/upload/20180730/1532940403c9205e5efe741fae.jpg",
      "source_url": "https://m.adquan.com/creative/detail/45477",
      "title": "要是看懂了富士相机的荒诞美学，该有多绝望",
      "description": "记录现实，现实却被拒绝接受，当人们把虚构当真实的时候，真实又该何去何从，一些人想要颠倒黑白，一些人想要黑白分明，在扭曲纷杂中，敢于直面“世界命题”的人，能够深入这些问题的人，有多少？ “世界好像疯了。”人说 “因为四处都是疯子？”医者问 “因为现在的人只相信疯子。”人说 从2016年开始，富士相机开启了“世界命题”系列，欺凌、贫穷、遗弃、政治失格、美丑、核武器、神经病态......在似问非问，似答非答的对话中，一个光怪陆离的世界向我们展示它的千疮百孔，也向我们炫耀它仍在仍野蛮生长，荒诞却合理，似是而非，不明所以，大众的清醒与迷茫在虚构中愈发明显。 富士相机在美学中向来偏爱致敬“离经叛道”的艺术大师，或许，在富士为X100打造了一系列向日本重量级的摄影师森山大道和荒木经惟致敬的“浪摄流”广告后，这个品牌就注定走向一条极致的文艺之路。短片里的白面妆与天狐面具等元素，既是致敬寺山修司，也是致敬歌舞伎等日本传统文化，深邃内敛的东方之美让人迷惑，让人神往。 在今年以“神经”为主题推出富士X-H1之前，富士曾以同样的风格宣传X-Pro2（2017.8核先生）、X100F&X-T20（2017.2美丑）、X-T2（2016.9失格 ）和X70（2016.1欺凌、贫穷、遗弃）。 【核先生】篇 “对不起！”核先生说 “核先生…”人答 “我是善意的。只是失控了。”核先生说 “你根本不需要和我道歉。我才是要向地球道歉。”人答 【美丑 】篇 整容是想变得美丽？ 我只想变得不丑陋，不再被批判。 是世界生病了？ 美丽本来就是病态 【失格】篇： “你有资格资格当议员吗？”人问 “绝对有”议员答 “你有资格当人吗”人问 “应该……没有”议员答 【欺凌】篇 怎么样算欺凌？ 十个人欺负一个人是欺凌。 一百个人欺负一个人也是。 那么一万人呢？ 是正义啊。 真奇怪 。 【贫穷】篇 你认识贫穷吗？ 在电视上看过，是遥不可及的东西。 讨厌。 你想过有一天会贫穷吗？ 很遗憾。根据世界的逻辑…只会 富者愈富。 也有一句话，叫富不过三代。 【遗弃】篇 “真可怜，你被主人遗弃了么？”人问 “人不是吗？”猫答 “生命的本质就是孤独，如同被遗弃一样。”猫说 “我们都是可怜的人类”人答 相关阅读： 为了劝你买相机，富士开始不说人话了 … 相关阅读： 富士“不说人话”系列新篇，这次聊“欺凌 相关阅读： 浪摄流，富士相机的极致文艺",
      "main_image": "https://oss.adquan.com/upload/20180730/1532940403c9205e5efe741fae.jpg",
      "images": [
        "http://file.adquan.com/upload/20180730/15329403137dbcdd6ad89b24ec.png",
        "http://file.adquan.com/upload/20180730/1532940331ad00dbb2fc1378bb.png"
      ],
      "video_url": "http://v.qq.com/iframe/player.html?vid=t0601m94kc9&tiny=0&auto=0",
      "author": "Garbo",
      "publish_time": "2018-07-31",
      "brand_industry": "数码、通讯",
      "activity_type": "影视",
      "location": "日本",
      "tags": [
        "富士X-H1",
        "富士"
      ]
    },
    {
      "case_id": 303255,
      "score": 4,
      "score_decimal": "8.3",
      "favourite": 108,
      "thumb": "https://oss.adquan.com/upload/20210407/1617784952caa58b69094accd8.png",
      "source_url": "https://m.adquan.com/creative/detail/303255",
      "title": "易立竞的“审问式”广告，冒犯了谁？",
      "description": "凭借独特的“审问式”吐槽，易立竞成为本季《吐槽大会》黑马之一。 她面色泰然，言辞犀利，看似温柔，实则已紧捏他人七寸，带着鲜明的个人风格，让看客拍手叫好，为吐槽大会和自己带来一波又一波的热度。 爆火之后，易立竞自然而然成为了品牌眼中的“流量红人”。 在品牌五周年之际，网易严选请来易立竞再现致命“追问”。 你常熬夜吗？ 是为了明天，还是为了逃避明天？ 你焦虑吗？ 是因为过得不够好，还是因为别人过得比你好？ 你想过逃离吗？ 那你为什么还没有出发？ 是不甘心，还是无处可逃？ 你的生活里，有爱情吗？ 你确定，那就是爱情吗？ 你买房了吗？ 房子在你眼中，是家，还是身家？ 你有婚育压力吗？ 确实想要，还是必须得要？ 你有想做却没做的事吗？ 因为懒，还是因为不敢？ 你羡慕别人的生活吗？ 有人羡慕你的生活吗？ 你会为了被羡慕，勉强自己吗？ 勉强自己的人，还会喜欢自己吗？ 讨自己欢心和被别人羡慕，你想要哪种？ 你，喜欢自己的生活吗？ 在此之前，聚划算、抖音也都向易立竞伸出橄榄枝。 易立竞X聚划算",
      "main_image": "https://oss.adquan.com/upload/20210407/1617784952caa58b69094accd8.png",
      "images": [
        "https://file.adquan.com/uploads_img/fcjnx1617783456.png",
        "https://file.adquan.com/uploads_img/se2o31617784655.jpg"
      ],
      "author": "Garbo",
      "publish_time": "2021-04-07",
      "brand_industry": "电商、零售",
      "activity_type": "影视",
      "location": "中国大陆",
      "tags": [
        "易立竞",
        "网易严选"
      ]
    },
    {
      "case_id": 292788,
      "score": 4,
      "score_decimal": "7.9",
      "favourite": 161,
      "company_name": "4A广告文案",
      "company_logo": "https://oss.adquan.com/avator/235083_1555932734_full.jpg",
      "thumb": "https://oss.adquan.com/upload/20200317/1584442555814545.png",
      "source_url": "https://m.adquan.com/creative/detail/292788",
      "title": "每日优鲜的文案，让人爱上做饭！",
      "description": "最近被每日优鲜的一组包装袋文案吸引。 在38节之际，每日优鲜打造「听女人的话」campaign，联合张静初、秦岚、谭卓等 10 位女星发声「在家吃饭」。 “不要熬夜，熬汤可以”、“不要挤电梯，挤橙子可以”、“不要淘气，淘米可以“……将“在家吃饭”的生活观通过日常小事呈现出来。 此外，它们还在每日包装袋上写下浪漫情诗，呼吁对女性群体要有更多理解和关爱，并传达「在家吃饭 每日优鲜」的品牌主张。 三行情诗 红透的西红柿 跳进鲜黄的鸡蛋汤 大火里起舞 余温后收汁 人生学会的第一道菜 在人生里炒了无数次 最熟悉的日常 也是最眷恋的家常 一块上好五花肉的绝佳去处 是让它缠绵在酱油与料酒的怀抱里 高温中翻滚 冰糖里焖煮 瘦却不柴 肥又不腻 而让一个人心安的独门秘诀 是就这么跟着味觉 找到最熟悉的归途 认识的第一年 土豆丝被她切成土豆条 在一起的第三年 盘里的醋多醋少 取决于咱俩的矛盾大小 还好没有人比我更知晓 碗里的醋有多少 心底的爱就有多少 用细腻生动的文字描写出炒菜的过程，同时又蕴含着人生哲理。 其实你可能不知道，每日优鲜还是隐藏的文案高手，我们来看下每日优鲜的优秀文案吧。 517吃货节文案 好吃点只要琢磨一下就好 吃好点却是一辈子在琢磨的事 人生如果有不如意 很多时候都是我们吃饱了撑的 其实，生活中让人愉快的 通常就是那些所谓的芝麻小事 想成独立兽 常常特立独行 做吃货只需要成群结队 这个世界上 最好吃的食物 总是性感的 如果做强者 有什么秘诀的话 就是：eat 这组吃货节文案，以“吃点好的怎么了”为传播主题，将吃好和人生道理相结合，赋予食物更深层次的一面。 官网文案 寥寥数笔写出了消费者最关心的原产地、质检和产品口感。 麻辣小龙虾 每日优鲜基地“包养” 当季新鲜活虾秘制，肉质弹牙 18余味先煮后炸再秘制， 锁住虾黄 着重描写肉质的鲜嫩和制虾工艺的复杂。 南非水橙 源自“彩虹之国”的鲜甜 轻轻一咬就出水 细嫩化渣甜到你心里 生动细腻的描述让人忍不住流下了口水。 每日优鲜最擅长的就是用拟人化的手法，将食物类比成人，赋予食材生命和人的情感特征。 #冬季C位水果#文案 猕猴桃 今天我是甜蜜屁池 不仅想你，还要抱住你 苹果 今天我是开心阿婆 没有理由，就是傻乐 西瓜 今天我是暴躁瓦特妹棱 我要骂人，还要吃小孩 这组文案将水果以拟人的口吻自述，让你感受到水果的人格化特征，同时水果的名字也采用英文直译的方式，显得趣味十足。 在微博，每日优鲜发起#小鲜甜话#话题。利用水果蔬菜发情话日常。 每日情话文案 众生皆苦，只有你是草莓味儿 ——草莓 有很多人讨厌我，没关系你们继续 反正我知道有很多人爱我 ——香菜 谈过恋爱的每个人心里都很清楚 甜蜜只是暂时的 而红颜草莓是一直一直都甜蜜的 柠檬的果语是忌妒， 因为柠檬“心是酸的，脸是绿的” 你们都好甜哦，又是柠檬精的一天 ——柠檬 芝麻是草莓上剔出来的吗？ 生蚝煮熟了还是生蚝吗？ 想你可以发消息吗？ 你可以喜欢我吗？ 亲爱的 内心别像我一样藏太多芝麻事， 好好吃饭，每天过得简单快乐！爱你 ——火龙果 女孩子不讲道理的时候， 你让几分，她就多爱你几分， 一如这颗酥梨， 你吃几口，它就甜几口。 ——GN 还有围绕#每日一签#写的文案，或是满满的正能量，或是动人的情话。 #每日日签#文案 生命太过短暂，活出当下的精彩 青春如此华美 却在烟火在散场 听从你心 无问东西 你一定要记得 你值得最好的 愿你在被打击时，记起你的珍贵 生命最重要的不是你遭遇了什么 而是你记住了什么 是如何铭记的 与其说迷恋你 倒不如说遇见你 我有多幸运 你的顺其自然是努力过后 还是随波逐流呢 只要思想不滑坡，办法总比困难多 借势营销节点 海 报 #今日立春# 春方立，宜咬春。 宜等春风来，宜等江城樱花开 #今日雨水# 东风解冻，散为雨水。 宜随草木生，宜食山药除湿寒。 #今日惊蛰# 春雷动，万物醒。 乍暖还寒，天干物燥，宜食梨 不得不提的是，我发现每日优鲜的APP产品文案很有意思，于是拿出一些作为例子，一起来学习下吧！ APP产品文案 1、加入场景描述 一不小心栽倒在你的浪漫香味——沐浴露 -（带入场景描述，营造氛围） 2、善用拟人 我可以hold住所有睡姿——晚安裤 -（用拟人化口吻讲述消费者最关注的产品用途） 细韧无比，用我湿水不怕破——纸巾 —（同样是拟人化口吻，表达纸巾细韧特点） 3、恰到好处的比喻 就像把花瓣撒进洗衣机——洗衣液 -（让人透过文字就能想象洗衣液的清香。） 像穿梭樱花树下 美肤滋养——沐浴露 -（谁不想穿梭在樱花树下，不仅比喻贴切，还极具画面感。） 酵素配方 像剪刀把油污剪碎——洗衣液 -（将去污的过程比喻为把污渍剪碎，实在巧妙。） 4、从消费者的角度描写 徒手就能爽快撕的保鲜膜——保鲜膜 -（不直接讲保鲜膜的卖点，而是突出使用者的感受） 5、学会夸张，让文案分分钟上天 看见威猛先生 油污妖精都害怕——清洁剂 -（这句用了夸张的手法展现威猛先生去油的强劲功效） 6、洞察消费者痛点 不开火 不在厨房蒸桑拿——电炖锅 -（写出了消费者用电炖锅就像在厨房蒸桑拿的痛点） 7、多一点对用户的关心 保护自己 卸妆要比化妆更认真——卸妆水 —（传达正确的护肤方式，强调女生好保护自己，体现出品牌的关心） 每日优鲜不管是海报文案、日常互动文案还是APP产品文案，都以趣味用生动、表达细腻的方式传达产品卖点，以及「在家吃饭 每日优鲜」的品牌主张，这样的文案你喜欢吗？ 4A广告文案原创，转载请联系原作者 4A广告文案（AAAAIdea）",
      "main_image": "https://oss.adquan.com/upload/20200317/1584442555814545.png",
      "images": [
        "https://file.adquan.com/pic/158444155013519fd15af9bea1.jpg",
        "https://file.adquan.com/pic/158444155089caa0772fb21f2f.jpg",
        "https://file.adquan.com/pic/1584441550f689f8a6c5166a12.jpg",
        "https://file.adquan.com/pic/1584441550b9c46cf42c734464.jpg",
        "https://file.adquan.com/pic/15844415513b49acd4963cb1f2.jpg",
        "https://file.adquan.com/pic/15844415515d8e49ebb9677e98.jpg",
        "https://file.adquan.com/pic/15844415511e061c2cba806f4f.jpg",
        "https://file.adquan.com/pic/1584441551b93eed189d6e7d92.jpg",
        "https://file.adquan.com/pic/15844415524826236784fafe83.jpg",
        "https://file.adquan.com/pic/15844415520fc513fc51610164.jpg",
        "https://file.adquan.com/pic/158444155246d7a697893606dd.jpg",
        "https://file.adquan.com/pic/158444155213ae8d857e525643.jpg",
        "https://file.adquan.com/pic/15844415532e180677805aad2d.jpg",
        "https://file.adquan.com/pic/15844415531c7ee2fa7f07afdc.jpg",
        "https://file.adquan.com/pic/15844415537cf6287a3c735665.jpg",
        "https://file.adquan.com/pic/1584441553a2ae78f99262374b.jpg",
        "https://file.adquan.com/pic/15844415538f297abbdc4787aa.jpg",
        "https://file.adquan.com/pic/1584441553806ae427f9f5f6cb.jpg",
        "https://file.adquan.com/pic/1584441554c8749bed1ac906a8.jpg",
        "https://file.adquan.com/pic/158444155426ea08f773039951.jpg",
        "https://file.adquan.com/pic/15844415545a5594ffff8db6d2.jpg",
        "https://file.adquan.com/pic/15844415547bf04360f5e8b3b2.jpg",
        "https://file.adquan.com/pic/1584441554d8b658ba28f01ccd.jpg",
        "https://file.adquan.com/pic/1584441554c8cf23a6b9499236.jpg",
        "https://file.adquan.com/pic/15844415554c42f344eb5bd49c.jpg",
        "https://file.adquan.com/pic/1584441555aacacc6125eb2009.jpg",
        "https://file.adquan.com/pic/15844415559b27d8098b3b3d14.jpg",
        "https://file.adquan.com/pic/1584441555e6a4642afca91648.jpg",
        "https://file.adquan.com/pic/1584441555062439f87aa63ddd.jpg",
        "https://file.adquan.com/pic/1584441555637c5ff90c3af5aa.jpg",
        "https://file.adquan.com/pic/15844415568698bb1abb5252e5.jpg",
        "https://file.adquan.com/pic/1584441556f7462d60fe58a352.jpg",
        "https://file.adquan.com/pic/1584441556d8f85a22d1da744c.jpg",
        "https://file.adquan.com/pic/158444155624ce3c273bb8bb02.jpg",
        "https://file.adquan.com/pic/1584441556ee7c81e91e907320.jpg",
        "https://file.adquan.com/pic/1584441556d245a59e4ba55592.jpg",
        "https://file.adquan.com/pic/1584441557c284de52f100d3f8.jpg",
        "https://file.adquan.com/pic/15844415576692576bc67468f6.jpg",
        "https://file.adquan.com/pic/15844415574dcb5e493e3c9fe2.jpg",
        "https://file.adquan.com/pic/15844415571b2860f7cc49ee33.jpg",
        "https://file.adquan.com/uploads_img/6593d1584441877.png"
      ],
      "author": "4A广告文案",
      "publish_time": "2020-03-18",
      "brand_industry": "互联网",
      "activity_type": "平面",
      "location": "中国大陆",
      "tags": [
        "文案",
        "案例"
      ]
    },
    {
      "case_id": 308985,
      "score": 4,
      "score_decimal": "8.7",
      "favourite": 205,
      "company_name": "江小白",
      "company_logo": "https://oss.adquan.com/logo/20161227193526_72487_320.png",
      "thumb": "https://oss.adquan.com/upload/20211122/1637550936a808b58ee9d6ad32.jpg",
      "source_url": "https://m.adquan.com/creative/detail/308985",
      "title": "江小白的100句声明文案 , 有点狠",
      "description": "今天一大早，朋友圈就被江小白连发100条声明刷爆了。 江小白趁着10周年生日发布了“郑重声明”，文案不仅暗戳戳地回应了之前对他们的所有质疑，还展现出其和谐温暖的工作氛围和企业文化。100张声明用不同风格的海报展现，以自嘲的方式以及非寻常的发文时间和数量吸引了大家的关注，迅速登上了微博热搜榜第一名。 搞笑且用心的文案帮江小白刷了一波同情和好感，先不看内容，光是100条的数量就赢了。网友不禁调侃：“又逼疯一个运营”、“论广告创意的海报，都如此卷了嘛？” 以下为「江小白的100条郑重声明」！（本文图片有点多，但看到最后或许有惊喜） 海报发出后，便引来诸多品牌的互动，不仅自制“同款”「郑重声明」海报还在微博下方评论，文案花样百出，可以说是联动全网了。 平安银行：我真的很想知道这个答案 图源：平安银行官博 图源：58同城官博 图源：喜多多官博 图源：饿了么官博 图源：天猫发言人官博",
      "main_image": "https://oss.adquan.com/upload/20211122/1637550936a808b58ee9d6ad32.jpg",
      "images": [
        "https://file.adquan.com/pic/1637550511dc250c7a35d63179.jpg",
        "https://file.adquan.com/pic/163755051298d6dcf7568a9d67.jpg",
        "https://file.adquan.com/pic/16375505123353bd965dcecb2d.jpg",
        "https://file.adquan.com/pic/163755051352119cecb5bc115b.jpg",
        "https://file.adquan.com/pic/1637550514a9689d38ab8f3660.jpg",
        "https://file.adquan.com/pic/1637550515f9d7be4586fa8095.jpg",
        "https://file.adquan.com/pic/163755051512ffa825df6ad144.jpg",
        "https://file.adquan.com/pic/16375505164ee4a155697de496.jpg",
        "https://file.adquan.com/pic/163755051791e64ab8a4616e4b.jpg",
        "https://file.adquan.com/pic/16375505175203d4146d4d2487.jpg",
        "https://file.adquan.com/pic/16375505182255fd54b1410d5d.jpg",
        "https://file.adquan.com/pic/1637550520bacc1d3461018179.jpg",
        "https://file.adquan.com/pic/163755052163a19efd6c3f0bd7.jpg",
        "https://file.adquan.com/pic/16375505228e07688e36003c0a.jpg",
        "https://file.adquan.com/pic/1637550524d90fb6307b476793.jpg",
        "https://file.adquan.com/pic/16375505258995a4a284f66a70.jpg",
        "https://file.adquan.com/pic/163755052628004f8d98e8dadf.jpg",
        "https://file.adquan.com/pic/163755052691e0b7d12d18a7e9.jpg",
        "https://file.adquan.com/pic/16375505278d3ab68b2582ff2e.jpg",
        "https://file.adquan.com/pic/16375505285e1418654661a721.jpg",
        "https://file.adquan.com/pic/1637550528518933a9adcb8f40.jpg",
        "https://file.adquan.com/pic/163755052961bf31e1ccb7df40.jpg",
        "https://file.adquan.com/pic/163755053022efd80cc69163dc.jpg",
        "https://file.adquan.com/pic/16375505313d379c685e807415.jpg",
        "https://file.adquan.com/pic/163755053289351bc156d09e37.jpg",
        "https://file.adquan.com/pic/163755053397eb12428b36e6c0.jpg",
        "https://file.adquan.com/pic/163755053324b1c170c0d3025e.jpg",
        "https://file.adquan.com/pic/1637550535d02934c3cbda164c.jpg",
        "https://file.adquan.com/pic/1637550535661519aaf8bb9213.jpg",
        "https://file.adquan.com/pic/1637550536587654fbd1d8a92e.jpg",
        "https://file.adquan.com/pic/16375505374a3438ed6a9686b6.jpg",
        "https://file.adquan.com/pic/1637550538d8a86467b25ecc73.jpg",
        "https://file.adquan.com/pic/163755053901521e0c5b16c113.jpg",
        "https://file.adquan.com/pic/1637550540c492e75877074cb5.jpg",
        "https://file.adquan.com/pic/16375505404c8a84ee51efae87.jpg",
        "https://file.adquan.com/pic/1637550541b39fc36316ea99c4.jpg",
        "https://file.adquan.com/pic/1637550542fd3ea4a735bf57a2.jpg",
        "https://file.adquan.com/pic/163755054215208578c8b7aa96.jpg",
        "https://file.adquan.com/pic/1637550543f138599ea14af6a0.jpg",
        "https://file.adquan.com/pic/16375505449c51c9df148968fb.jpg",
        "https://file.adquan.com/pic/163755054571d473c4d4e046dc.jpg",
        "https://file.adquan.com/pic/1637550546b43254d89f89c07d.jpg",
        "https://file.adquan.com/pic/1637550546eab7649b989628ed.jpg",
        "https://file.adquan.com/pic/1637550547a2596e4ae328f022.jpg",
        "https://file.adquan.com/pic/16375505479abf43ebe6371e40.jpg",
        "https://file.adquan.com/pic/16375505486e8bcd38e9dcd740.jpg",
        "https://file.adquan.com/pic/1637550548af3b5aab6aa6d32f.jpg",
        "https://file.adquan.com/pic/1637550549486af76471b5fa9d.jpg",
        "https://file.adquan.com/pic/1637550550361a11f213b430ba.jpg",
        "https://file.adquan.com/pic/16375505519148e85b2b67c74c.jpg",
        "https://file.adquan.com/pic/163755055299c48674af911709.jpg",
        "https://file.adquan.com/pic/1637550552f76a08c775878cf2.jpg",
        "https://file.adquan.com/pic/1637550554680a62bb16fb72b4.jpg",
        "https://file.adquan.com/pic/163755055524aca331379fe1bc.jpg",
        "https://file.adquan.com/pic/1637550556087f56e318dd9093.jpg",
        "https://file.adquan.com/pic/163755055755aaa44b9e9253c2.jpg",
        "https://file.adquan.com/pic/1637550559e285706c4fbee7d1.jpg",
        "https://file.adquan.com/pic/1637550560bb28a7317362c690.jpg",
        "https://file.adquan.com/pic/1637550561b23cd18e0fe3f4ab.jpg",
        "https://file.adquan.com/pic/1637550562e17c45e00d051f52.jpg",
        "https://file.adquan.com/pic/1637550562ed1bd31ec1abc25b.jpg",
        "https://file.adquan.com/pic/16375505634fd4d40849f7ebce.jpg",
        "https://file.adquan.com/pic/1637550564d89a6989c552c828.jpg",
        "https://file.adquan.com/pic/1637550565c271e39822d20b57.jpg",
        "https://file.adquan.com/pic/1637550566632dd85f50e54e3b.jpg",
        "https://file.adquan.com/pic/1637550567e24b495d92058f72.jpg",
        "https://file.adquan.com/pic/163755056720c0babfb226f9e8.jpg",
        "https://file.adquan.com/pic/163755056880207ccb1a3e901d.jpg",
        "https://file.adquan.com/pic/163755056932ee2b12138e9561.jpg",
        "https://file.adquan.com/pic/1637550570e801e198b0b733a4.jpg",
        "https://file.adquan.com/pic/163755057057082925420d508e.jpg",
        "https://file.adquan.com/pic/16375505718ac27f0704627b02.jpg",
        "https://file.adquan.com/pic/1637550573ec8b234ad612da6c.jpg",
        "https://file.adquan.com/pic/1637550574e3bad0cd57f34baa.jpg",
        "https://file.adquan.com/pic/163755057495180295bceef8a6.jpg",
        "https://file.adquan.com/pic/16375505750e303081d6d298a3.jpg",
        "https://file.adquan.com/pic/1637550576966fab3bdcbdb2a7.jpg",
        "https://file.adquan.com/pic/1637550577d393a4eda24b82a7.jpg",
        "https://file.adquan.com/pic/16375505788d76ec49675d1824.jpg",
        "https://file.adquan.com/pic/1637550578151a1cb9e02da768.jpg",
        "https://file.adquan.com/pic/1637550579f8e64b9774c181b0.jpg",
        "https://file.adquan.com/pic/16375505814be7426524612ec1.jpg",
        "https://file.adquan.com/pic/1637550581070ee67632ababe2.jpg",
        "https://file.adquan.com/pic/16375505820e7b33a999f76a95.jpg",
        "https://file.adquan.com/pic/16375505839b1a53caaebef2ff.jpg",
        "https://file.adquan.com/pic/1637550584e315ad240fa52e08.jpg",
        "https://file.adquan.com/pic/163755058544c8d225c16eeaef.jpg",
        "https://file.adquan.com/pic/163755058634d4e88cb75fd063.jpg",
        "https://file.adquan.com/pic/163755058629149f42f5c36fbb.jpg",
        "https://file.adquan.com/pic/1637550587254fd3f1f45571d1.jpg",
        "https://file.adquan.com/pic/1637550588f86f8a07021acf85.jpg",
        "https://file.adquan.com/pic/16375505894f6eab2e146c082b.jpg",
        "https://file.adquan.com/pic/163755059036665dde619af1c2.jpg",
        "https://file.adquan.com/pic/1637550591300b9ce2044ad976.jpg",
        "https://file.adquan.com/pic/1637550592e33b1fb841a9d1ca.jpg",
        "https://file.adquan.com/pic/163755059331248a621c17cc9c.jpg",
        "https://file.adquan.com/pic/16375505941c8abb89148686e5.jpg",
        "https://file.adquan.com/pic/16375505956218913004d2f811.jpg",
        "https://file.adquan.com/pic/16375505967da25a3ec2123ddf.jpg",
        "https://file.adquan.com/pic/1637550597635a5c7177bace07.jpg",
        "https://file.adquan.com/pic/1637550598b4e7bc8ca06f27f9.jpg",
        "https://file.adquan.com/pic/16375505997b2fc6a2c7a4b283.jpg",
        "https://file.adquan.com/pic/1637550599b8c85833b8492707.jpg",
        "https://file.adquan.com/pic/163755060016de5056af7a6898.jpg",
        "https://file.adquan.com/pic/1637550601ea4975793e444f0e.jpg",
        "https://file.adquan.com/pic/16375506016777627a0c154054.jpg",
        "https://file.adquan.com/pic/16375506028cb7808f8d9d4a09.jpg",
        "https://file.adquan.com/pic/163755060306b4914a388e93d6.jpg",
        "https://file.adquan.com/pic/1637550604c8174f4ee950da71.jpg",
        "https://file.adquan.com/pic/163755060444384281f768f610.jpg",
        "https://file.adquan.com/pic/1637550605561e817cf34d875d.jpg",
        "https://file.adquan.com/pic/163755060549dfd41f7d91058d.jpg",
        "https://file.adquan.com/pic/1637550606a42e73631eb44a6b.jpg",
        "https://file.adquan.com/pic/163755060607183bd070e8eca4.jpg",
        "https://file.adquan.com/pic/1637550607598938a5aff12799.jpg",
        "https://file.adquan.com/pic/1637550608a854d1a48976832e.jpg",
        "https://file.adquan.com/pic/16375506095052e2b34b1fe887.jpg",
        "https://file.adquan.com/pic/163755060997f8895a00c76320.jpg",
        "https://file.adquan.com/pic/1637550610023aa715e31a6659.jpg",
        "https://file.adquan.com/pic/16375506117749d542b2cbe920.jpg",
        "https://file.adquan.com/pic/163755061391fc5043ca4a4c51.jpg",
        "https://file.adquan.com/pic/16375506147b49fa0eb8293884.jpg",
        "https://file.adquan.com/pic/1637550615526424d12e0f97ca.jpg",
        "https://file.adquan.com/pic/163755061615bde19fc78cec1a.jpg",
        "https://file.adquan.com/pic/1637550617c1cff19d922c0348.jpg",
        "https://file.adquan.com/pic/163755061753282bc6287bcd6a.jpg",
        "https://file.adquan.com/pic/16375506182a21077e8f52acbc.jpg",
        "https://file.adquan.com/pic/16375506190b3f37753bc2f0c3.jpg",
        "https://file.adquan.com/pic/1637550620b789301c71393991.jpg",
        "https://file.adquan.com/pic/1637550620e953f32490c58f7b.jpg",
        "https://file.adquan.com/pic/1637550621bd6dcb5830e24ad1.jpg"
      ],
      "author": "Annabelle",
      "publish_time": "2021-11-22",
      "brand_industry": "快消品",
      "activity_type": "平面",
      "location": "中国大陆",
      "tags": [
        "江小白",
        "广告文案"
      ]
    },
    {
      "case_id": 287703,
      "score": 4,
      "score_decimal": "7.1",
      "favourite": 34,
      "thumb": "https://oss.adquan.com/upload/20190923/1569235725306025b5c28f1a38.png",
      "source_url": "https://m.adquan.com/creative/detail/287703",
      "title": "微众银行五周年广告片，细数生活的小确幸",
      "description": "在五周年之际，微众银行由这一巴掌的岁月，引申出主题“为美好生活击掌”，串联起一个个无意的“give me five”，展现人与人之间的奇妙联系，致敬我们的美好日常。 《一起为美好生活击掌》 在首发短片《一起为美好生活击掌》之后，微众银行也陆续上线短片的延伸视频，重现击掌的前因后果。 part 1：为田间的超级英雄击个掌吧 part 2：为出乎意料的打call击个掌吧 part 3：为热血青年的霸气侧漏击个掌吧 part 4：破次元的Freestyle击个掌吧 part 5：微众银行，为深藏不露的少女心击个掌吧 part 6：为跨界的缘分击个掌吧 生活中的意外数不胜数，虽然很多时候并不受欢迎，但偶然一次的美好就足以让人感叹。品牌正是通过展现一系列出人意料的“小确幸”，传递美好的期待，从而拉进与受众的距离。",
      "main_image": "https://oss.adquan.com/upload/20190923/1569235725306025b5c28f1a38.png",
      "images": [
        "https://file.adquan.com/uploads_img/pear01569235706.jpg",
        "https://file.adquan.com/uploads_img/epwh41569235707.jpg"
      ],
      "video_url": "https://v.qq.com/txp/iframe/player.html?vid=v0921phvjch&tiny=0&auto=0",
      "author": "Garbo",
      "publish_time": "2019-09-24",
      "brand_industry": "金融、保险",
      "activity_type": "影视",
      "location": "中国大陆",
      "tags": [
        "微众银行"
      ]
    },
    {
      "case_id": 284653,
      "score": 4,
      "score_decimal": "7.8",
      "favourite": 80,
      "thumb": "https://oss.adquan.com/upload/20190518/15581631170a8b967c8634450f.jpg",
      "source_url": "https://m.adquan.com/creative/detail/284653",
      "title": "天猫国潮行动，推出过哪些刷屏爆款？",
      "description": "为响应5月10日的国家品牌日，天猫通过“国潮来了”，与无数国货展开破次元的合作。 李宁亮相纽约时装周、旺仔56个民族系列，六神RIO鸡尾酒、周黑鸭御泥坊小辣吻咬唇膏……这些刷屏的国货，其实都是在天猫“国潮行动”的背景下展开的，那么天猫的“国潮来了”，究竟推出了多少刷屏的国货合作案例呢，让我门来盘点一下吧。 密扇MUKZIN巴黎大秀 中国李宁亮相巴黎时装周 周黑鸭“混音诗人”国风亮相 周黑鸭X御泥坊：小辣吻咬唇膏 福临门X阿芙精油：万福金油 泸州老窖香水 卫龙辣条粽子 旺旺56个名族牛奶 旺旺塔卡沙联名 以上，只是天猫国潮行动的部分脑洞大开的案例。近两年，李宁、飞跃、荣耀、知味观、恒源祥、百雀羚、马应龙等国货不断刷屏我们的朋友圈，而带领这些中国品牌C位出道的正是天猫，天猫向我们全方位展示了“万物皆可联名”的国货推广新思路。",
      "main_image": "https://oss.adquan.com/upload/20190518/15581631170a8b967c8634450f.jpg",
      "images": [
        "https://file.adquan.com/uploads_img/tkhvu1558161596.jpg",
        "https://file.adquan.com/uploads_img/ohx8q1558161597.jpg",
        "https://file.adquan.com/uploads_img/nx1b61558161597.gif",
        "https://file.adquan.com/uploads_img/k7r541558161597.jpg",
        "https://file.adquan.com/uploads_img/0cfz21558161665.jpg",
        "https://file.adquan.com/uploads_img/0tbij1558161665.jpg",
        "https://file.adquan.com/uploads_img/14rgi1558161665.jpg",
        "https://file.adquan.com/uploads_img/5zsb41558161827.jpg",
        "https://file.adquan.com/uploads_img/xj74f1558161828.jpg",
        "https://file.adquan.com/uploads_img/kwqb21558161828.jpg",
        "https://file.adquan.com/uploads_img/t3a901558161966.jpg",
        "https://file.adquan.com/uploads_img/478k11558162157.jpg",
        "https://file.adquan.com/uploads_img/xijyk1558161967.jpg",
        "https://file.adquan.com/uploads_img/xjhk11558162221.jpg",
        "https://file.adquan.com/uploads_img/pi9y81558162240.jpg",
        "https://file.adquan.com/uploads_img/9p0cz1558162311.jpg",
        "https://file.adquan.com/uploads_img/10wks1558162595.jpg",
        "https://file.adquan.com/uploads_img/57j8p1558162595.jpg",
        "https://file.adquan.com/uploads_img/mv8oh1558162750.jpg",
        "https://file.adquan.com/uploads_img/76wcq1558162750.gif"
      ],
      "author": "小破吃的",
      "publish_time": "2019-05-18",
      "brand_industry": "电商、零售",
      "activity_type": "平面",
      "location": "中国大陆",
      "tags": [
        "天猫臻值日",
        "国潮来了"
      ]
    },
    {
      "case_id": 285030,
      "score": 5,
      "score_decimal": "9.1",
      "favourite": 120,
      "company_name": "大嘴收纳屋",
      "company_logo": "https://oss.adquan.com/avator/1563598535106e9d0249295230.jpg",
      "thumb": "https://oss.adquan.com/upload/20190606/1559798965833229.jpg",
      "source_url": "https://m.adquan.com/creative/detail/285030",
      "title": "5月国内创意海报，被电商包场了？ | 收藏",
      "description": "5月刚刚结束了，我門收集了本月份的127张国内创意海报，供大家欣赏收藏。 01 品牌方： 天猫618 02 品牌方： 滴滴出行 03 品牌方： 阿里IP 04 品牌方： 京东 05 品牌方： 361° 06 品牌方： 路虎×国家地理 07 品牌方： 虎牙直播 08 品牌方： 永辉 x luckin 09 品牌方： 破冰行动 10 品牌方： 大众点评 11 品牌方： 天猫国潮 12 品牌方： 天猫定制礼盒 13 品牌方： 天猫 14 品牌方： flow 15 品牌方： 快手 16 品牌方： 王者荣耀 17 品牌方： 奥利奥 18 品牌方：天猫 19 20 品牌方：华为荣耀 21 品牌方：asics 22 品牌方：宝洁 23 品牌方：言几又 x 知乎 24 品牌方： 弹个车 25 品牌方： 优酷 26 27 品牌方： 淘鲜达 28 品牌方： 雪花品牌联合 点击此处 百度云链接打包下载，（提取码： x8ju） 作者公众号：大嘴收纳屋（ID: ad_collection）",
      "main_image": "https://oss.adquan.com/upload/20190606/1559798965833229.jpg",
      "images": [
        "https://file.adquan.com/pic/15597972984b1be3857e4b65ed.jpg",
        "https://file.adquan.com/pic/1559797299836d760b04935ae5.jpg",
        "https://file.adquan.com/pic/1559797302c050fb3f6633688e.jpg",
        "https://file.adquan.com/pic/15597973068932445896b72bfa.jpg",
        "https://file.adquan.com/pic/15597973098dee99d4c0197019.jpg",
        "https://file.adquan.com/pic/155979731211fa8a4ee5fb147c.jpg",
        "https://file.adquan.com/pic/1559797316fff061d8b87bf73d.jpg",
        "https://file.adquan.com/pic/155979731869be1387f39c4455.jpg",
        "https://file.adquan.com/pic/15597973217104076bc9041217.jpg",
        "https://file.adquan.com/pic/1559797324160cecf8203c59f4.jpg",
        "https://file.adquan.com/pic/1559797328fb019f6dd7a39351.jpg",
        "https://file.adquan.com/pic/15597973315024ad01e64f428f.jpg",
        "https://file.adquan.com/pic/1559797334b4a007bc7fe8cdaa.jpg",
        "https://file.adquan.com/pic/1559797337c68807cbded1cbbe.jpg",
        "https://file.adquan.com/pic/155979733985214f55aa7b5828.jpg",
        "https://file.adquan.com/pic/155979734177a04c5c0854535f.jpg",
        "https://file.adquan.com/pic/155979734239e280b35ae956ed.jpg",
        "https://file.adquan.com/pic/155979734229dd7843b5937fa9.jpg",
        "https://file.adquan.com/pic/15597973436cb9bf15d03d3007.jpg",
        "https://file.adquan.com/pic/15597973433bec36edd134063f.jpg",
        "https://file.adquan.com/pic/15597973435db328a0bce40ba2.jpg",
        "https://file.adquan.com/pic/15597973442a848bd1b6273b57.jpg",
        "https://file.adquan.com/pic/15597973442d23c1b752afa52f.jpg",
        "https://file.adquan.com/pic/1559797344312b2e1a85276eda.jpg",
        "https://file.adquan.com/pic/15597973454fe01059b667fee6.jpg",
        "https://file.adquan.com/pic/15597973457a48af5b2ca22600.jpg",
        "https://file.adquan.com/pic/15597973452412ab6feb9064f1.jpg",
        "https://file.adquan.com/pic/155979734546bacb1e77386945.jpg",
        "https://file.adquan.com/pic/1559797346a4978bbbbc051e5a.jpg",
        "https://file.adquan.com/pic/15597973469f1228faa2df0c8e.jpg",
        "https://file.adquan.com/pic/15597973468285706f40250f55.jpg",
        "https://file.adquan.com/pic/155979734689ea3ef005d762b9.jpg",
        "https://file.adquan.com/pic/1559797346099b1d73ebfc4dcc.jpg",
        "https://file.adquan.com/pic/155979734748e80b51aba5e0be.jpg",
        "https://file.adquan.com/pic/15597973475b55810c34e9c609.jpg",
        "https://file.adquan.com/pic/155979734729804208f568e9c0.jpg",
        "https://file.adquan.com/pic/155979734719bbf56f3b717d3d.jpg",
        "https://file.adquan.com/pic/1559797348d5b4dbf9e002c075.jpg",
        "https://file.adquan.com/pic/1559797348ae674e26b02bec22.jpg",
        "https://file.adquan.com/pic/15597973486a9e034f44f9aa27.jpg",
        "https://file.adquan.com/pic/15597973482b5fc9fc18f70b27.jpg",
        "https://file.adquan.com/pic/1559797349b5133243d64271be.jpg",
        "https://file.adquan.com/pic/15597973493fbaf38501fdffde.jpg",
        "https://file.adquan.com/pic/15597973493ac4de26ba8b7047.jpg",
        "https://file.adquan.com/pic/155979735016f2d95385e9c8dc.jpg",
        "https://file.adquan.com/pic/1559797350d110cdd00965ab55.jpg",
        "https://file.adquan.com/pic/155979735004251952f5995c71.jpg",
        "https://file.adquan.com/pic/1559797350afe423d818bcecfb.jpg",
        "https://file.adquan.com/pic/1559797351c42494d26b997dc6.jpg",
        "https://file.adquan.com/pic/1559797351459ed5216bd87c74.jpg",
        "https://file.adquan.com/pic/1559797351a65738c5dcec8748.jpg",
        "https://file.adquan.com/pic/155979735270884a48d19a9ea4.jpg",
        "https://file.adquan.com/pic/1559797352762790949578abfc.jpg",
        "https://file.adquan.com/pic/1559797352591974090c2eb7a7.jpg",
        "https://file.adquan.com/pic/1559797353e3453e9400a5c6f8.jpg",
        "https://file.adquan.com/pic/1559797353f9d2cb3c6e279952.jpg",
        "https://file.adquan.com/pic/15597973538f25f38225b876a1.jpg",
        "https://file.adquan.com/pic/15597973548e427d66ecee559a.jpg",
        "https://file.adquan.com/pic/1559797354a0048ee840582602.jpg",
        "https://file.adquan.com/pic/1559797354343b6b303c92e3b1.jpg",
        "https://file.adquan.com/pic/15597973541027e0adc9793b1a.jpg",
        "https://file.adquan.com/pic/15597973548f7abe5ec3af5cd5.jpg",
        "https://file.adquan.com/pic/155979735518c935bac469ade1.jpg",
        "https://file.adquan.com/pic/1559797355eb600b62eff34e0c.jpg",
        "https://file.adquan.com/pic/1559797355e04b9e611d8c941a.jpg",
        "https://file.adquan.com/pic/1559797356d7fdbe8e2e19aae5.jpg",
        "https://file.adquan.com/pic/1559797356dba00636870109a5.jpg",
        "https://file.adquan.com/pic/1559797356b1ec82eaf7972111.jpg",
        "https://file.adquan.com/pic/1559797357ac8d822909ff8d77.jpg",
        "https://file.adquan.com/pic/1559797357d8bb01ea7a139dcd.jpg",
        "https://file.adquan.com/pic/1559797357c5a8a7bb64ec4cab.jpg",
        "https://file.adquan.com/pic/1559797358700580d9d1a93cdf.jpg",
        "https://file.adquan.com/pic/155979735879977179f7f4fe0d.jpg",
        "https://file.adquan.com/pic/1559797358b89dcbc31b99541c.jpg",
        "https://file.adquan.com/pic/1559797358f7c3de44f8a479a6.jpg",
        "https://file.adquan.com/pic/15597973593c4764cd7604fdb6.jpg",
        "https://file.adquan.com/pic/155979735988c01c094eb5c9d8.jpg",
        "https://file.adquan.com/pic/1559797360e6a26b306ec99205.jpg",
        "https://file.adquan.com/pic/1559797360bbbd4cf47751dc4a.jpg",
        "https://file.adquan.com/pic/1559797360abda3af63e75d82d.jpg",
        "https://file.adquan.com/pic/1559797361cf072a7f90e4f14d.jpg",
        "https://file.adquan.com/pic/1559797361857f69604f29b63f.jpg",
        "https://file.adquan.com/pic/155979736118eeb9530cc1f766.jpg",
        "https://file.adquan.com/pic/1559797362635fc1ba678a360e.jpg",
        "https://file.adquan.com/pic/1559797362053f4b8f3818279b.jpg",
        "https://file.adquan.com/pic/1559797362da25794af3bb5037.jpg",
        "https://file.adquan.com/pic/1559797362d5cbbca331d27f0f.jpg",
        "https://file.adquan.com/pic/155979736385c94ca0feb1a5d3.jpg",
        "https://file.adquan.com/pic/1559797364adc4ba99b60a59b1.jpg",
        "https://file.adquan.com/pic/155979736411b33788e6de238e.jpg",
        "https://file.adquan.com/pic/15597973656b6d617869661462.jpg",
        "https://file.adquan.com/pic/15597973655793bf769404ff4b.jpg",
        "https://file.adquan.com/pic/1559797366ed7e74108be41498.jpg",
        "https://file.adquan.com/pic/15597973668fba67e30ab86497.jpg",
        "https://file.adquan.com/pic/15597973668db20ce91c44897c.jpg",
        "https://file.adquan.com/pic/155979736679497fadfc554edd.jpg",
        "https://file.adquan.com/pic/155979736790acd59ea567359f.jpg",
        "https://file.adquan.com/pic/1559797369711aefd52221f522.jpg",
        "https://file.adquan.com/pic/1559797371b1e8fab578899a2d.jpg",
        "https://file.adquan.com/pic/1559797372ebb3d091fafd9155.jpg",
        "https://file.adquan.com/pic/15597973768db7bd7f3ea13182.jpg",
        "https://file.adquan.com/pic/155979737743ab9ce757dc2b5d.jpg",
        "https://file.adquan.com/pic/1559797378af27215778ab94d1.jpg",
        "https://file.adquan.com/pic/15597973786fad58d180c047e0.jpg",
        "https://file.adquan.com/pic/1559797378205346af5615c27e.jpg",
        "https://file.adquan.com/pic/155979737960450369520d3085.jpg",
        "https://file.adquan.com/pic/1559797379215e098b6ac27255.jpg",
        "https://file.adquan.com/uploads_img/wpicd1559797933.jpg"
      ],
      "author": "大嘴收纳屋",
      "publish_time": "2019-06-10",
      "brand_industry": "互联网",
      "activity_type": "影视",
      "location": "中国大陆",
      "tags": [
        "海报",
        "平面"
      ]
    },
    {
      "case_id": 289405,
      "score": 4,
      "score_decimal": "8.5",
      "favourite": 98,
      "company_name": "Publicis 阳狮 纽约 美国",
      "company_logo": "https://oss.adquan.com/logos/1525432099542605.jpg",
      "thumb": "https://oss.adquan.com/upload/20191205/1575534453e6a90c2a3c9ef65e.jpg",
      "source_url": "https://m.adquan.com/creative/detail/289405",
      "title": "这支咖啡广告，在违法的边缘疯狂试探......",
      "description": "根据研究表明，咖啡里含有的咖啡因会让人变得精神振奋，因此也会让人上瘾，那么大家就来脑洞大开想象一下，如果喝咖啡违法，世界将会变成什么样？会有人为了咖啡铤而走险，甚至会形成违法贩卖咖啡的地下产业，犯罪率激增，整个社会人心惶惶...... 最近，美国食品公司J.M. Smucker Company（JM斯马克公司）就以此为创意点，为旗下的高端咖啡品牌1850咖啡拍摄了一支荒诞却又充满黑色幽默的“缉毒片”。 短片想象出了各种各样可能出现的咖啡犯罪场景，全程气氛紧张却并不压抑，反而在一本正经的搞笑，尤其是警官用小拇指沾了杯子里的咖啡，品尝之后对嫌犯嘲讽的说道： 星爸爸：感觉有被内涵到...... 短片用戏剧化的夸张的幽默表现出了1850咖啡“好喝到犯罪”的浓郁丝滑高纯度口感，成功引起观众的好奇心，让人看完之后特别想知道到这咖啡底有什么致命的魅力，即使面对蹲局子的风险也欲罢不能，这迷人又危险的极致味道，有谁不想尝尝呢。",
      "main_image": "https://oss.adquan.com/upload/20191205/1575534453e6a90c2a3c9ef65e.jpg",
      "images": [
        "https://file.adquan.com/uploads_img/hubmk1575533318.png",
        "https://file.adquan.com/uploads_img/slv7y1575533341.png"
      ],
      "video_url": "https://v.qq.com/txp/iframe/player.html?vid=t3026esdcan&tiny=0&auto=0",
      "author": "heying",
      "publish_time": "2019-12-05",
      "brand_industry": "快消品",
      "activity_type": "影视",
      "location": "美国",
      "tags": [
        "1850咖啡",
        "JM Smucker"
      ]
    },
    {
      "case_id": 46607,
      "score": 4,
      "score_decimal": "8.6",
      "favourite": 147,
      "thumb": "https://oss.adquan.com/upload/20181109/154174243597d5db4ca6d1b580.png",
      "source_url": "https://m.adquan.com/creative/detail/46607",
      "title": "京东这波沙雕广告是我今天的快乐源泉！",
      "description": "来源：创意嘿店（ID：highlight1207） 作者：店长 作为人群中最快乐的小沙雕 我一直对沙雕文化爱得深沉 并且立志做沙雕文化传播者 所以当我发现京东这支沙雕广告时 我欣喜若狂惊喜万分如获至宝 骚话不多说 先乐呵起来 如果你以为这支广告只有沙雕 那真正的沙雕可能是看戏的你 Actually！ 京东这支广告向我们展示了 它是如何在6分钟之内 一口气卖30款电器的 港真 现在想要我花六分钟 完整地看完一支广告 几乎是不可能的事情 毕竟大猪蹄子都没什么耐心 所以为了让我这种货色看下去 京东这沙雕广告处处都在埋梗 【变正经分割段】 客户的嘴 骗人的鬼 发60秒语音的客户 是魔鬼 所以京东建议大家 端碗面 当面聊 毕竟语音说不清 咱们需要当面聊 Attention！ 接下来这一幕 是职场高频social现场 “ H5挺牛X啊！” “ 拍的好！拍的好！” “ 产品好！产品好！” “ 客户厉害！客户厉害！” 试问没有情感的闭眼吹 和一台只会吹风的电扇 有什么本质区别？ 没有区别。 情绪稳定的成年人 从不当面表达好恶 “ 你也喜欢全键盘？” “ 呃... 我喜欢全面屏。” 只会在背地里洗手 人这一生 能遇到几个心心相惜的人？ 所以话说回来 人活这一辈子 即便是开个灯 也得带着情感 毕竟我们只能从开灯的刹那 体会到电光火石般的激情了 如何正确形容品牌爸爸的屏幕真的大？ 京东：看屏幕的X某看着看着就 “ 看开 ” 了 所以说世界上最宽广的 不止有像门板一样宽的曲面显示器 还有你看开了的那双眼 当然 假如生活夹住了你 你不但要学会看开 还要懂得让它翻篇 人生在世 要尽可能地活成一台 能屈能伸的双屏手机 不知不觉30条广告看下来 居然差点被种了一片草原 你别说 变沙雕的京东 还真挺能带货的",
      "main_image": "https://oss.adquan.com/upload/20181109/154174243597d5db4ca6d1b580.png",
      "images": [
        "http://file.adquan.com/uploads_img/yoqmu1541741854.jpg",
        "http://file.adquan.com/uploads_img/2nc1y1541742508.jpg",
        "http://file.adquan.com/uploads_img/8vl201541742627.jpg",
        "http://file.adquan.com/image_upload/server/upload/6f4e9a0be02125289e7cb2be628806fd.gif",
        "http://file.adquan.com/uploads_img/ax9b51541742859.png",
        "http://file.adquan.com/uploads_img/qjv0w1541742906.png",
        "http://file.adquan.com/image_upload/server/upload/59d4047b41f5b127064d21d56cb48f90.gif",
        "http://file.adquan.com/uploads_img/whfb41541742947.png",
        "http://file.adquan.com/image_upload/server/upload/4f70b53385dfa29d24977cde62c723b4.gif",
        "http://file.adquan.com/uploads_img/h8p671541743007.png",
        "http://file.adquan.com/image_upload/server/upload/c75ed9d71ed3eb61b0265a48d94aec95.gif",
        "http://file.adquan.com/uploads_img/ru61n1541743054.png",
        "http://file.adquan.com/image_upload/server/upload/c1feb076fe49a93e273523da6c6cde8d.gif",
        "http://file.adquan.com/uploads_img/zluts1541743100.png",
        "http://file.adquan.com/uploads_img/0frhk1541743115.jpg",
        "http://file.adquan.com/uploads_img/l4wkx1541743151.jpg"
      ],
      "video_url": "https://v.qq.com/txp/iframe/player.html?vid=e0787cbi46e&tiny=0&auto=0%0A%0A%E4%BA%AC%E4%B8%9C%E8%BF%99%E6%B3%A2%E5%B9%BF%E5%91%8A%E6%98%AF%E7%9C%9F%E7%9A%84%E5%BE%88%E6%B2%99%E9%9B%95%E2%80%A6%E2%80%A6%E2%80%A6%E2%80%A6%E2%80%A6%E2%80%A6",
      "author": "杜玥",
      "publish_time": "2018-11-09",
      "brand_industry": "电商、零售",
      "activity_type": "影视",
      "location": "中国大陆",
      "tags": [
        "京东",
        "沙雕广告"
      ]
    },
    {
      "case_id": 48537,
      "score": 5,
      "score_decimal": "9.6",
      "favourite": 145,
      "thumb": "https://oss.adquan.com/upload/20190117/15477110654510a07ded25b064.png",
      "source_url": "https://m.adquan.com/creative/detail/48537",
      "title": "日本的户外广告真的能看一天！",
      "description": "近日日本电信公司DOCOMO面向外国游客，推出交互创意短片WOW! NINJA in SHIBUYA（哇！涩谷忍者）以推广其旅游网站WOW! JAPAN。 短片分为昼、夜两版，将古老神秘的日本忍者元素完美融合到新鲜时尚的涩谷，使人们一抬头，就可以看到屏幕上的“忍者”不停跳跃、分身、炫技，十分逼真。表演过后，官方还派出一位真正的“忍者”突然出现在路人之中，与外国游客们惊讶相遇。",
      "main_image": "https://oss.adquan.com/upload/20190117/15477110654510a07ded25b064.png",
      "images": [],
      "video_url": "https://v.qq.com/txp/iframe/player.html?vid=w0827pnjy83&tiny=0&auto=0",
      "author": "Garbo",
      "publish_time": "2019-01-18",
      "brand_industry": "互联网",
      "activity_type": "影视",
      "location": "日本",
      "tags": [
        "日本",
        "户外广告"
      ]
    },
    {
      "case_id": 288301,
      "score": 4,
      "score_decimal": "7.9",
      "favourite": 107,
      "thumb": "https://oss.adquan.com/upload/20191024/1571899934114273263947be15.jpg",
      "source_url": "https://m.adquan.com/creative/detail/288301",
      "title": "瑞幸咖啡的新广告有毒吧哈哈哈哈哈哈",
      "description": "为了纪念人类登月50周年，瑞幸咖啡最近在北京开了一家「致敬NASA」主题店，并发布了一支画风突变的沙雕TVC，一本正经的搞笑简直让人猝不及防，话不多说先看视频： 两名宇航员在太空执行航天任务，做事马虎自带灾星体质的尼克和沉着冷静淡定的装x高手刘强cp感满满，两人在执行任务的过程中状况百出： 第一天，通讯器故障，尼克反复调试之后二人失联，刘强不慌不忙地拿出小蓝杯放在天线上调节角度重新连接信号，歪果仁尼克成功学到一个新词汇“鹿由器”。 第二天，尼克发现舱体漏气，他尝试了各种方法甚至险些赌上性命，只见刘强不慌不忙拿出防洒漏的小蓝塞成功堵上船舱。 第三天，尼克执行舱外任务时不慎安全扣脱落，他紧张得大口呼吸，最终氧气供给不足30分钟，刘强再次不慌不忙拿出手机点了一杯瑞幸咖啡，30分钟必达的外卖小哥成功解救尼克。 三支短片虽然剧情沙雕无厘头，但是用轻松幽默的方式清晰准确地体现出了产品卖点，将咖啡和太空元素巧妙结合，让人看了之后记忆深刻。 线下的「致敬NASA」主题店融入大量具有科技感和设计感的太空元素，设计了太空舱、星空密室等主题场景，航空器模型、宇航服、纪念章等装饰品还原了宇航员在空间站的生活环境，看上去非常炫酷。",
      "main_image": "https://oss.adquan.com/upload/20191024/1571899934114273263947be15.jpg",
      "images": [
        "https://file.adquan.com/uploads_img/jiluo1571899627.gif",
        "https://file.adquan.com/uploads_img/m7uis1571899633.gif",
        "https://file.adquan.com/uploads_img/ae7dw1571899632.gif",
        "https://file.adquan.com/uploads_img/pzaj81571899636.gif",
        "https://file.adquan.com/uploads_img/y2nuf1571899632.gif",
        "https://file.adquan.com/uploads_img/736fl1571899636.gif",
        "https://file.adquan.com/uploads_img/mvpe11571899672.jpg",
        "https://file.adquan.com/uploads_img/n2ohs1571899673.jpg",
        "https://file.adquan.com/uploads_img/bm30h1571899673.jpg",
        "https://file.adquan.com/uploads_img/x3zdb1571899675.jpg"
      ],
      "video_url": "https://v.qq.com/txp/iframe/player.html?vid=l3011jkjw9s&tiny=0&auto=0",
      "author": "heying",
      "publish_time": "2019-10-25",
      "brand_industry": "快消品",
      "activity_type": "影视",
      "location": "中国大陆",
      "tags": [
        "瑞幸咖啡"
      ]
    },
    {
      "case_id": 286808,
      "score": 5,
      "score_decimal": "9.4",
      "favourite": 132,
      "company_name": "SG 胜加",
      "company_logo": "https://oss.adquan.com/logos/1560156822903650.jpg",
      "thumb": "https://oss.adquan.com/upload/20190813/15656764674d7527a03956a92e.png",
      "source_url": "https://m.adquan.com/creative/detail/286808",
      "title": "母鸡会打鸣 ? 方太上线新广告《王的鸡》",
      "description": "本文为会员专享，订阅会员查看完整内容 本文共计785字，包含2个视频、11张图片，订阅后阅读全文",
      "main_image": "https://oss.adquan.com/upload/20190813/15656764674d7527a03956a92e.png",
      "images": [
        "https://m.adquan.com/images/vip_zk.png"
      ],
      "author": "张瑜轩",
      "publish_time": "2020-10-17",
      "tags": []
    },
    {
      "case_id": 287812,
      "score": 5,
      "score_decimal": "9.0",
      "favourite": 66,
      "thumb": "https://oss.adquan.com/upload/20190926/15694914034402d0d62c683c69.jpg",
      "source_url": "https://m.adquan.com/creative/detail/287812",
      "title": "《我和我的祖国》预售破亿，全明星海报有点燃！",
      "description": "近日，一部电影人致敬新中国建国70周年的影片——《我和我的祖国》多次刷屏。这部影片取材于多个历史性经典瞬间，讲述普通人与国家之间息息相关的故事。和以往电影的叙述方式不同，此次电影分成了七个单元，由7位导演带领大家重温七个全民记忆的历史瞬间，再现七次见证国史瞬间的能量迸发，由小见大回顾新中国70年的波澜历程。 （影片原定10.1全国公映，而后提档一天于9月30上映） 虽然影片还未正式上映，但通过官方发布的系列海报，就足以勾起无数观众的记忆与热议。 “瞬间”版海报 开国大典不眠前夜，他们争分夺秒、排除万难， 确保#新中国第一次升起五星红旗#万无一失。 1949年，第一面五星红旗承载着4亿人的希望 2019年，五星红旗成了14亿人的骄傲 中国第一颗原子弹爆炸成功的背后 是无数“献了青春献终身”的国防科技战线科研人员 从此他们和亲人只有相遇，再无相聚 他们刻骨铭心的爱情和他们的名字一样，永不褪色 1984年8月8日，中国女排首次登上奥运会最高领奖台，实现世界大赛三连冠 总能给国人带来骄傲、荣耀、拼搏的泪水，有一种精神叫中国女排！ 据悉，在电影我和我的祖国拍摄《夺冠》期间，郎平亲自探班，在片场与导演徐峥 及小演员们分享了自己作为运动员第一次获得奥运冠军背后的故事，并表示希望将中国女排的拼搏精神和团队精神一代代传递下去。 1997年7月1日0时0分，香港回归一秒不差。 我和我的祖国，一刻也不能分割！ 用热血沸腾的呐喊点燃心中的自豪与骄傲！ 2008年8月8日，我们与世界共同见证北京奥运会开幕式 奥运梦圆，北京你好，中国加油！ 她们是纪念抗战胜利70周年阅兵式上一道靓丽的风景线， “中国空军花木兰”守护祖国蓝天！ 神舟十一号划过长空，戈壁上的人们见到了传说中的神迹——白昼流星。而他们脚下这片土地也在悄然改变着。 《白昼流星》不仅有陈飞宇和刘昊然，更有神舟十一号飞船航天员景海鹏、陈冬的参演，真实再现返回舱顺利着陆这一历史性瞬间。 借势海报 5·12 6·1 儿童节 7·1 建党98周年 中秋 · 团圆 主题曲系列海报 影片预售已全面开启，并在9月25日14点18分，传来预售破亿的消息。 你会去看吗？",
      "main_image": "https://oss.adquan.com/upload/20190926/15694914034402d0d62c683c69.jpg",
      "images": [
        "https://file.adquan.com/uploads_img/n92mw1569483879.jpg",
        "https://file.adquan.com/uploads_img/bqkl51569488326.png",
        "https://file.adquan.com/uploads_img/50p6l1569484052.jpg",
        "https://file.adquan.com/uploads_img/fqmay1569484052.jpg",
        "https://file.adquan.com/uploads_img/ycktd1569484053.jpg",
        "https://file.adquan.com/uploads_img/tq7g31569484053.jpg",
        "https://file.adquan.com/uploads_img/c07tb1569484053.jpg",
        "https://file.adquan.com/uploads_img/rvuly1569484054.jpg",
        "https://file.adquan.com/uploads_img/fx42a1569484055.jpg",
        "https://file.adquan.com/uploads_img/ube5o1569484055.jpg",
        "https://file.adquan.com/uploads_img/30rs11569483875.jpg",
        "https://file.adquan.com/uploads_img/26whs1569489524.jpg",
        "https://file.adquan.com/uploads_img/57dbo1569489503.jpg",
        "https://file.adquan.com/uploads_img/e315o1569483875.jpg",
        "https://file.adquan.com/uploads_img/d3gwp1569483876.jpg",
        "https://file.adquan.com/uploads_img/e8v3k1569483877.jpg",
        "https://file.adquan.com/uploads_img/xsrwi1569483876.jpg",
        "https://file.adquan.com/uploads_img/9n8p51569483878.jpg",
        "https://file.adquan.com/uploads_img/tloiu1569483878.jpg",
        "https://file.adquan.com/uploads_img/7mfra1569483879.jpg",
        "https://file.adquan.com/uploads_img/xh0up1569490610.jpg",
        "https://file.adquan.com/uploads_img/iz3941569490610.jpg",
        "https://file.adquan.com/uploads_img/efloh1569490610.jpg",
        "https://file.adquan.com/uploads_img/jvleq1569490611.jpg",
        "https://file.adquan.com/uploads_img/nszg01569490612.jpg",
        "https://file.adquan.com/uploads_img/6zc071569490612.jpg",
        "https://file.adquan.com/uploads_img/ak1591569490613.jpg",
        "https://file.adquan.com/uploads_img/fwnkb1569490613.jpg",
        "https://file.adquan.com/uploads_img/ioe071569490904.jpg"
      ],
      "author": "Garbo",
      "publish_time": "2019-09-26",
      "brand_industry": "政府、非盈利机构",
      "activity_type": "影视",
      "location": "中国大陆",
      "tags": [
        "《我和我的祖国》",
        "海报"
      ]
    },
    {
      "case_id": 49523,
      "score": 5,
      "score_decimal": "9.2",
      "favourite": 125,
      "thumb": "https://oss.adquan.com/upload/20190225/155106803299c2559b362c4bd7.jpg",
      "source_url": "https://m.adquan.com/creative/detail/49523",
      "title": "走向国际的乡村爱情，连海报都这么fashion!",
      "description": "印象里《乡村爱情》应该是这样的。 但实际上却是这样！ 在被翻译成美泰日韩印法西英的《乡村爱情11》海报中，东北大碴子味消失不见，反而完美地抓住各个国家电视海报的精髓，奇怪，《乡村爱情》什么时候这么fashion了？ 从2006年开播以来，《乡村爱情》常年霸占各大荧屏，虽然带火了谢飞机、刘能、尼古拉斯-赵四、谢大脚等一众角色...但还是摆脱不了“土”的标签，在年轻人的市场中，大多数作为表情包用于调侃。 偶尔也是发人深省的“人间鸡汤”。 但自从《乡村爱情》第11季开播，土了13年的乡村偶像剧变得潮起来......画风突变，你还适应吗？",
      "main_image": "https://oss.adquan.com/upload/20190225/155106803299c2559b362c4bd7.jpg",
      "images": [
        "https://file.adquan.com/uploads_img/15948038053932c14360249e75.jpg",
        "http://file.adquan.com/uploads_img/rzwmx1551068325.jpg",
        "http://file.adquan.com/uploads_img/wea4h1551068326.jpg",
        "http://file.adquan.com/uploads_img/42tfe1551068327.jpg",
        "http://file.adquan.com/uploads_img/kx4yj1551068327.jpg",
        "http://file.adquan.com/uploads_img/fri531551068326.jpg",
        "http://file.adquan.com/uploads_img/4pbqc1551068329.jpg",
        "http://file.adquan.com/uploads_img/51xat1551068329.jpg",
        "http://file.adquan.com/uploads_img/t51op1551068329.jpg",
        "http://file.adquan.com/uploads_img/dvazl1551068330.jpg",
        "https://file.adquan.com/uploads_img/15948038059e87c863c6e057a3.jpg",
        "https://file.adquan.com/uploads_img/1594803806eda30327f6f784aa.jpg",
        "https://file.adquan.com/uploads_img/159480380621a3143f3c6d2c20.jpg",
        "http://file.adquan.com/uploads_img/cfnqr1551069689.jpg"
      ],
      "author": "Garbo",
      "publish_time": "2020-08-15",
      "brand_industry": "互联网",
      "activity_type": "平面",
      "location": "中国大陆",
      "tags": [
        "乡村爱情",
        "海报"
      ]
    },
    {
      "case_id": 287348,
      "score": 4,
      "score_decimal": "8.6",
      "favourite": 135,
      "thumb": "https://oss.adquan.com/upload/20190909/156800113864c2d3333efc11f9.png",
      "source_url": "https://m.adquan.com/creative/detail/287348",
      "title": "这可能是腾讯拍过最搞笑的广告了！",
      "description": "马上又要开始一年一度的校招，各大公司纷纷开始为自己打广告，今年就连大名鼎鼎的鹅厂腾讯都发布了招聘广告片，携手全家老小组团出镜，一起来看看大厂子是怎么招人的吧： 短片风格是当下最流行的沙雕无厘头小剧场，用谐音和反转将完全不搭边的两个场景相结合，准确传达出不同的产品特性，一本正经的搞笑让人忍俊不禁。 从汽车之父、电话之父过渡到微信支付，而且还是全民致富，不仅谐音还双押，玩儿梗这么溜，鹅厂够酷。 腾讯视频真香，内容精彩够下饭，不负好时光，吃啥啥都香。 一路风雨陪你长大的企鹅，还会继续陪伴大家走下去，社交就要有温度。 腾讯广告，痛点痒点全知道，谐音不够双关来凑，硬广软广腾讯广告软硬兼施。 普天之下，莫非王土，朝堂之上，不如微视，微视专治各种不开心。 腾讯有云：汲取圣人智慧，创造腾讯未来。加入腾讯云，智慧更超群。 又是一个双关梗，腾讯的招聘原则：没有屈打成招，只有看准就招，不放过任何一个潜力股。 看了之后有没有对鹅厂充满期待呢？校招的小伙伴们冲鸭！！！",
      "main_image": "https://oss.adquan.com/upload/20190909/156800113864c2d3333efc11f9.png",
      "images": [
        "https://file.adquan.com/uploads_img/m9bga1568001089.png",
        "https://file.adquan.com/uploads_img/ov1ih1568001059.png",
        "https://file.adquan.com/uploads_img/yqu0i1568001063.png",
        "https://file.adquan.com/uploads_img/efzav1568001068.png",
        "https://file.adquan.com/uploads_img/729am1568001063.png",
        "https://file.adquan.com/uploads_img/wcegx1568001069.png",
        "https://file.adquan.com/uploads_img/wuki71568001067.png"
      ],
      "video_url": "https://v.qq.com/txp/iframe/player.html?vid=b0923q4a45q&tiny=0&auto=0",
      "author": "heying",
      "publish_time": "2019-09-09",
      "brand_industry": "互联网",
      "activity_type": "影视",
      "location": "中国大陆",
      "tags": [
        "腾讯",
        "校招"
      ]
    },
    {
      "case_id": 285784,
      "score": 4,
      "score_decimal": "8.4",
      "favourite": 117,
      "thumb": "https://oss.adquan.com/upload/20190703/156213338534de182c5a89159f.jpg",
      "source_url": "https://m.adquan.com/creative/detail/285784",
      "title": "《长安十二时辰》，美术很高级",
      "description": "突然大火的《长安十二时辰》大概是杂草丛生的暑期档最大的惊喜。 故事讲述了大唐上元节前夕，长安城陷入危局，死囚张小敬临危受命，与少年名士李必携手在十二时辰内拯救长安的故事。 宏大华美的画面和精良的拍摄制作，动不动就是长镜头，一部大唐版的反恐24小时，值得全方位打call！ 一开场的长镜头就体现了大唐的热闹繁华，展现了万国来朝的宏大气象！ 为了还原了长安这座世界第一城应有的盛世景象，剧组在开拍前花了七个月搭建场景，打磨道具。抛开这些不说，油画般的美术场景设定就十分惊艳。 长安十二时辰美术概念图 拍摄场景 目前还没有更新到赏灯夜景出现，有点遗憾不能收录进来。 剧中至关重要的长安舆图，可以一览长安盛况。 值得一提的是，拍摄分镜脚本也严谨到了电影级别。 实际拍摄与分镜脚本对比 服装造型 服装是还原历史面貌的重要道具，一部古装剧的美术有没有看点，首先看的就是人物装束。 长安官吏、庶人、军人“缺胯袍” 唐代织锦胡服 澜袍 吸收了西域胡服和中原袍服改良而来的官员服饰，绯色为常见的中高级官员服色，提花纹样和服饰颜色均体现官位等级。 盛唐时期女子服饰腰线上升，，上升至胸部以上以丰胸为美的唐朝，最大限度地修饰女子身材，显得曼妙高挑。 胡服（不仅胡汉兼用，且男女通用） 龟甲背 实战型唐铠，很重很重 百衲衣（祈福逐疫的一种祭祀活动服饰） 唐代参考的道士服饰 唐代文明阶层慕道，学道风气盛行 李必的道家服饰、子午簪、不离手的拂尘，据说，为了原汁原味地还原唐朝道家装束，片方还专门咨询了道教协会。 配色参考 网剧做出了电影的色调，环境和服装呈现出中国传统配色之美。 摄影构图解析 黄金螺旋构图：把一条线段分割为两部分，其中一部分的全长之比等于另一部分与这部分之比，比值近似0.168。 九宫格构图：同样是黄金分割方式的一种，呈现变化与动感，使画面富有活力。 斜线构图：斜线构图能表现动感、力量和方向，是一种容易令人激动的线条。能表现出纵深的效果，通常用来表现自然界。 自然取景中很多都具有水平线，如海平面、地平线。 三分法构图：三分法构图是黄金分割图的一种衍生，通常表现为水平或垂直形态，构图简练。 纵深构图：利用透视关系，引导视线，产生空间感。 精美画面 课代表敲黑板 《长安十二时辰》，里面的文化常识知识点真的太多了！文化不高还真不一定能看懂，什么是天干地支计时法，什么是诏令，什么是致仕等等。下面开始补课： 去年的剧集美术最好的当属《知否》和《延喜》 而今年这部《长安十二时辰》 除了剧情水准在线 精美的画面更是给了我们意外之喜 考究的服装、道具 精致油画般的画面质感 传统味十足的叉手礼 纵横交错的人物关系 总之，值得一看 本文部分内容摘录自微博 来源：文案与美术（公众号：copyart）",
      "main_image": "https://oss.adquan.com/upload/20190703/156213338534de182c5a89159f.jpg",
      "images": [
        "https://file.adquan.com/pic/15621322445e2d217b1165f195.jpg",
        "https://file.adquan.com/pic/15621322446a38090bb1132847.jpg",
        "https://file.adquan.com/pic/15621322451cf6b198595cb5dc.jpg",
        "https://file.adquan.com/pic/1562132245c1cfacec1d5c7ac3.jpg",
        "https://file.adquan.com/pic/1562132245ba43ac50baeb66a1.jpg",
        "https://file.adquan.com/pic/1562132245a805072d7787714b.jpg",
        "https://file.adquan.com/pic/15621322452aaa8cc3450be73f.jpg",
        "https://file.adquan.com/pic/156213224559c0caa8a9a482e0.jpg",
        "https://file.adquan.com/pic/1562132245facd89413c1c7c87.jpg",
        "https://file.adquan.com/pic/15621322455b8ff015ca4a6fb8.jpg",
        "https://file.adquan.com/pic/1562132245015d9dd46b1db849.jpg",
        "https://file.adquan.com/pic/15621322450ac0bf55e69213fd.jpg",
        "https://file.adquan.com/pic/1562132246489a252d378ecd79.jpg",
        "https://file.adquan.com/pic/156213224660c1792d9e58348e.jpg",
        "https://file.adquan.com/pic/1562132246c0e90df081b06491.jpg",
        "https://file.adquan.com/pic/15621322463d2b7532a84a41f5.jpg",
        "https://file.adquan.com/pic/1562132246a196bfb232af0176.jpg",
        "https://file.adquan.com/pic/15621322464343e79410f297c4.jpg",
        "https://file.adquan.com/pic/15621322469ab97a28847e93cd.jpg",
        "https://file.adquan.com/pic/15621322467e74a102b6835da5.jpg",
        "https://file.adquan.com/pic/1562132246b6fb65b32f7c6479.jpg",
        "https://file.adquan.com/pic/15621322461c02d3800aba77ae.jpg",
        "https://file.adquan.com/pic/1562132247e685732ccfc3cefd.jpg",
        "https://file.adquan.com/pic/1562132247f257d63e615b12dd.jpg",
        "https://file.adquan.com/pic/1562132247b9da2d1d3327fe3a.jpg",
        "https://file.adquan.com/pic/1562132247d5ee092ace702266.jpg",
        "https://file.adquan.com/pic/156213224720a2cfdc77219870.jpg",
        "https://file.adquan.com/pic/1562132247b1c44c2f4242dccf.jpg",
        "https://file.adquan.com/pic/156213224700c7a6a7492771a4.jpg",
        "https://file.adquan.com/pic/15621322476f9eb64bda2094ee.jpg",
        "https://file.adquan.com/pic/1562132247627873fcc876cb88.jpg",
        "https://file.adquan.com/pic/1562132247d081c5e63dc3a458.jpg",
        "https://file.adquan.com/pic/1562132247ae7e6d57e92b0894.jpg",
        "https://file.adquan.com/pic/15621322471ce1971f0f1e1de6.jpg",
        "https://file.adquan.com/pic/15621322478102af89d2d95e22.jpg",
        "https://file.adquan.com/pic/15621322480446c27f1d4633e7.jpg",
        "https://file.adquan.com/pic/1562132248f7b5fb8f37e6e6db.jpg",
        "https://file.adquan.com/pic/1562132248705d0778f0c01b84.jpg",
        "https://file.adquan.com/pic/15621322481d2dfcdcc91fa9eb.jpg",
        "https://file.adquan.com/pic/1562132248c74e9c8891040e06.jpg",
        "https://file.adquan.com/pic/15621322484cb5d6744be358e7.jpg",
        "https://file.adquan.com/pic/1562132248af110945cff0807c.jpg",
        "https://file.adquan.com/pic/1562132248ca88cef4dc0d43f7.jpg",
        "https://file.adquan.com/pic/1562132248372364cfc0eea5ec.jpg",
        "https://file.adquan.com/pic/1562132248ec2691c920a96249.jpg",
        "https://file.adquan.com/pic/1562132249c536520c29c83469.jpg",
        "https://file.adquan.com/pic/156213225025ebdd27579453af.jpg",
        "https://file.adquan.com/pic/1562132250d517c0fd74ee0c3c.jpg",
        "https://file.adquan.com/pic/15621322507622e3d52a6ed88e.jpg",
        "https://file.adquan.com/pic/1562132250ef6c3538a88955e2.jpg",
        "https://file.adquan.com/pic/15621322504d236ec7e193c570.jpg",
        "https://file.adquan.com/pic/1562132250a66bc9eae69769d8.jpg",
        "https://file.adquan.com/pic/15621322506db18210c13f75da.jpg",
        "https://file.adquan.com/pic/1562132251b574d2edab05f851.jpg",
        "https://file.adquan.com/pic/1562132251fda299f4cfee1010.jpg"
      ],
      "author": "heying",
      "publish_time": "2019-07-03",
      "brand_industry": "互联网",
      "activity_type": "平面",
      "location": "中国大陆",
      "tags": [
        "《长安十二时辰》",
        "网剧"
      ]
    },
    {
      "case_id": 291706,
      "score": 4,
      "score_decimal": "7.9",
      "favourite": 110,
      "thumb": "https://oss.adquan.com/upload/20200214/158167069223ea168dcf267575.jpg",
      "source_url": "https://m.adquan.com/creative/detail/291706",
      "title": "隔离，不隔爱 | 情人节借势海报",
      "description": "今年，不管是情侣们还是单身狗被迫禁足，在家里过了一个不能出门的特殊情人节，当然，受限的空间不能阻碍站在宇宙中心呼唤爱的品牌们。特殊时期，今年的情人节海报画风也与往年不太一样，一起来看看品牌们是如何撒狗粮的吧~ @小黑书 @饿了么 @可口可乐 @杜蕾斯 @杰士邦 @冈本 @大象 @爱慕 @联想中国 @联想手机 @ThinkPad @魅族手机 @一加手机 @小米手机 @苏宁易购 @苏宁 @京东 @京东手机通讯 @搜狐 @腾讯地图 @高德地图 @360搜索 @360安全卫士 @虾米音乐 @滴滴出行 @一汽丰田 @宝马中国 @华帝 @统帅电器 @香飘飘 @乐乐茶 @瑞幸咖啡 《爱乐之城》 《史密斯夫妇》 《剪刀手爱德华》 《泰坦尼克号》 @COSTACOFFEE中国 @士力架 @德芙 @洽洽 @伊利 @伊利味可滋 @安慕希 @植选豆乳 @蒙牛 @纯甄 @统一老坛酸菜 @统一阿萨姆 @统一爱夸 @元气森林 @ 佐卡伊 佐卡伊分别联合蜻蜓FM、赶集网、咕咚、旺仔推出了一系列“情人节处方单”主题的海报，提取联合品牌特质提出相应的病情诊断，并附上有效的专属品牌特效药。 @良品铺子",
      "main_image": "https://oss.adquan.com/upload/20200214/158167069223ea168dcf267575.jpg",
      "images": [
        "https://file.adquan.com/uploads_img/wdflk1581666894.png",
        "https://file.adquan.com/uploads_img/5jy9h1581666680.png",
        "https://file.adquan.com/uploads_img/szfqy1581667861.gif",
        "https://file.adquan.com/uploads_img/rxpab1581667955.jpg",
        "https://file.adquan.com/uploads_img/3dic11581667987.jpg",
        "https://file.adquan.com/uploads_img/qdlm81581907872.png",
        "https://file.adquan.com/uploads_img/rcbjw1581907889.png",
        "https://file.adquan.com/uploads_img/bqpnh1581668002.png",
        "https://file.adquan.com/uploads_img/3gtfl1581668043.jpg",
        "https://file.adquan.com/uploads_img/2cqsv1581668059.png",
        "https://file.adquan.com/uploads_img/8kj631581668553.png",
        "https://file.adquan.com/uploads_img/0l5891581668084.png",
        "https://file.adquan.com/uploads_img/jriqc1581668104.png",
        "https://file.adquan.com/uploads_img/rgpuc1581668118.png",
        "https://file.adquan.com/uploads_img/unk2r1581668129.png",
        "https://file.adquan.com/uploads_img/w69qd1581668161.png",
        "https://file.adquan.com/uploads_img/7wpia1581668606.jpg",
        "https://file.adquan.com/uploads_img/8flmv1581668681.png",
        "https://file.adquan.com/uploads_img/j9gzr1581668698.png",
        "https://file.adquan.com/uploads_img/75jft1581668718.png",
        "https://file.adquan.com/uploads_img/wbxpi1581668996.png",
        "https://file.adquan.com/uploads_img/9kxo81581670277.GIF",
        "https://file.adquan.com/uploads_img/wqfey1581668834.jpg",
        "https://file.adquan.com/uploads_img/39ktr1581668852.png",
        "https://file.adquan.com/uploads_img/60nc31581668881.png",
        "https://file.adquan.com/uploads_img/uz5m21581668915.png",
        "https://file.adquan.com/uploads_img/tg5ji1581668936.png",
        "https://file.adquan.com/uploads_img/ro1ux1581668945.png",
        "https://file.adquan.com/uploads_img/utnjh1581668952.png",
        "https://file.adquan.com/uploads_img/2gvla1581670251.gif",
        "https://file.adquan.com/pic/15816661005cfe9c5688baf2f8.jpg",
        "https://file.adquan.com/pic/1581666100c40fe16efaa0635c.jpg",
        "https://file.adquan.com/pic/1581666101c4fee7e292494b8f.jpg",
        "https://file.adquan.com/uploads_img/fw3hs1581669124.jpg",
        "https://file.adquan.com/uploads_img/dqaey1581669272.png",
        "https://file.adquan.com/uploads_img/lh5291581669280.png",
        "https://file.adquan.com/uploads_img/p7oj51581669291.png",
        "https://file.adquan.com/uploads_img/4s9hu1581669300.png",
        "https://file.adquan.com/uploads_img/6e2y01581669337.png",
        "https://file.adquan.com/uploads_img/buaxz1581669358.png",
        "https://file.adquan.com/uploads_img/vyife1581669382.png",
        "https://file.adquan.com/uploads_img/eiuk91581669447.jpg",
        "https://file.adquan.com/pic/1581666104690571ba092b995d.jpg",
        "https://file.adquan.com/pic/1581666104834f0dc854604f7b.jpg",
        "https://file.adquan.com/pic/1581666105f0f21d5d74936f32.jpg",
        "https://file.adquan.com/pic/158166610515492dd15328d28f.jpg",
        "https://file.adquan.com/pic/15816661036681f0974bf963a4.jpg",
        "https://file.adquan.com/pic/158166610331f600d2421688a6.jpg",
        "https://file.adquan.com/pic/1581666103782764beb4b8633d.jpg",
        "https://file.adquan.com/uploads_img/8zxwm1581907928.png",
        "https://file.adquan.com/uploads_img/qul851581907956.png",
        "https://file.adquan.com/uploads_img/g0ow21581908100.png",
        "https://file.adquan.com/uploads_img/w28xv1581669666.jpg",
        "https://file.adquan.com/uploads_img/ga0wy1581669707.jpg",
        "https://file.adquan.com/uploads_img/youtp1581669729.png",
        "https://file.adquan.com/uploads_img/421mi1581669758.jpg",
        "https://file.adquan.com/uploads_img/1yeo61581669776.png",
        "https://file.adquan.com/uploads_img/re3po1581669784.png",
        "https://file.adquan.com/uploads_img/tel0a1581669793.png",
        "https://file.adquan.com/uploads_img/ujf391581669802.png",
        "https://file.adquan.com/uploads_img/3w9m41581669825.png",
        "https://file.adquan.com/uploads_img/fq0g21581669838.png",
        "https://file.adquan.com/uploads_img/4wq831581669886.jpg",
        "https://file.adquan.com/uploads_img/m8a7i1581669914.png",
        "https://file.adquan.com/uploads_img/3a86d1581669932.png",
        "https://file.adquan.com/uploads_img/k8zmn1581669946.png",
        "https://file.adquan.com/uploads_img/9w3ps1581669971.png",
        "https://file.adquan.com/uploads_img/qeynv1581670061.png",
        "https://file.adquan.com/pic/1581666098f47a2452d7a98608.jpg",
        "https://file.adquan.com/pic/158166609986f0453fda6b57aa.jpg",
        "https://file.adquan.com/pic/158166609952fc8018a451bd32.jpg",
        "https://file.adquan.com/pic/1581666100f9974bfaac04d069.jpg",
        "https://file.adquan.com/pic/1581666101f51cf235e060f1fa.jpg",
        "https://file.adquan.com/pic/158166610224286723e0471932.jpg",
        "https://file.adquan.com/pic/158166610208e6934de5e97850.jpg"
      ],
      "author": "heying",
      "publish_time": "2020-02-14",
      "brand_industry": "互联网",
      "activity_type": "平面",
      "location": "中国大陆",
      "tags": [
        "情人节",
        "借势海报"
      ]
    },
    {
      "case_id": 294232,
      "score": 4,
      "score_decimal": "7.3",
      "favourite": 141,
      "company_name": "Leo Burnett  李奥贝纳 迪拜 阿联酋",
      "thumb": "https://oss.adquan.com/upload/20200506/1588759178f1f793e9b0042e79.jpg",
      "source_url": "https://m.adquan.com/creative/detail/294232",
      "title": "把广告做成沙漏，麦当劳的户外广告太秀了！",
      "description": "从4月24日到5月24日是伊斯兰国家传统的斋月，按照宗教习俗，这一个月内，除部分特殊人群之外，成年穆斯林从日落到日出期间禁食，商家也要避免在广告中展示食品，以免人们在斋戒期间受到诱惑。尽管如此，麦当劳在沙特阿拉伯还是创造了一种特殊的新方式来宣传其产品，没错，就是图中展示的沙漏。 李奥贝纳为麦当劳特别推出了一款计时沙漏装置，沙漏从装满到完全漏出的时间刚好是12小时，沙子完全漏出之后，沙漏下方的巨无霸、薯条和冰激凌露出真容，提醒人们禁食时间结束，快来吃麦当劳继续享受美食吧。 此外，麦当劳在社交媒体上也同步显示计时沙漏，并且在沙漏顶部藏了McDelivery的优惠码，当沙子全部落下的时候，人们在家可以享受到更加优惠的麦当劳。 沙漏计时装置既美观又巧妙，不但尊重了穆斯林信仰的宗教信仰，还将营销活动玩出了新花样，麦当劳的创意总能让人耳目一新、眼前一亮。",
      "main_image": "https://oss.adquan.com/upload/20200506/1588759178f1f793e9b0042e79.jpg",
      "images": [
        "https://d3nuqriibqh3vw.cloudfront.net/styles/aotw_detail_ir/s3/iftar_sandclock_01a_resized.jpg",
        "https://d3nuqriibqh3vw.cloudfront.net/styles/aotw_detail_ir/s3/iftar_sandclock_03b_resized.jpg",
        "https://d3nuqriibqh3vw.cloudfront.net/styles/aotw_detail_ir/s3/sandclock_bigmac_resized.jpg"
      ],
      "video_url": "https://v.qq.com/txp/iframe/player.html?vid=b0962qeghlj&tiny=0&auto=0",
      "author": "heying",
      "publish_time": "2020-05-06",
      "brand_industry": "快消品",
      "activity_type": "装置/陈列",
      "location": "其他地区",
      "tags": [
        "户外广告",
        "麦当劳"
      ]
    },
    {
      "case_id": 317338,
      "score": 5,
      "score_decimal": "9.2",
      "favourite": 273,
      "thumb": "https://oss.adquan.com/upload/20220725/1658715513b1c9f60d70575d18.jpg",
      "source_url": "https://m.adquan.com/creative/detail/317338",
      "title": "大爷的文案 , 在小红书上杀疯了",
      "description": "大胆的创意，经典的段子式文案，有趣的画面…如果你做过social创意或者曾经是social创意的疯狂爱好者，那么看了下面这套海报，很可能会老泪纵横，然后内心很诚实、身体很自觉的自觉点赞。 一杯敬过去 一杯敬过不去 这里不服务上帝 我们只招待朋友 年轻人少喝酒 喝就来这儿喝 疫情差点倒闭 开门往死卖力 大环境不好 来这儿环境好 疫情关店的日子里 老板学会了直播PK 回忆杀太可怕了。 被大爷反复提及的JOJO全名叫JOJO火山血橙气泡酒：JOJO是品牌名，血橙是口味，气泡酒是品类，而火山则是品牌的超级符号。关于这个赛道，因为有RIO的存在，大家或多或少都会有些印象。但其实这是一个在中国10000亿酒类市场中的新赛道，而且新概念非常多，从预调酒、鸡尾酒再到气泡酒，他们的目标消费群体都是年轻人。作为核心人群同样是年轻人的JOJO，为什么一反常态用老大爷作为主角，他们对年轻人有什么独特的洞察，这背后又有什么关于品牌精神的思考？带着这些疑问，我们面对面的和JOJO的品牌团队进行了深入沟通。 从自我的灰烬中重生？",
      "main_image": "https://oss.adquan.com/upload/20220725/1658715513b1c9f60d70575d18.jpg",
      "images": [
        "https://file.adquan.com/uploads_img/4y6bh1658714777.JPG",
        "https://file.adquan.com/uploads_img/s6vmc1658714781.JPG",
        "https://file.adquan.com/uploads_img/ps4yn1658714787.JPG",
        "https://file.adquan.com/uploads_img/1bms01658714791.JPG",
        "https://file.adquan.com/uploads_img/ep6k91658714794.JPG",
        "https://file.adquan.com/uploads_img/427jb1658714797.JPG",
        "https://file.adquan.com/uploads_img/w16hn1658715230.jpg",
        "https://file.adquan.com/uploads_img/8zhm01658715230.jpg",
        "https://file.adquan.com/uploads_img/2tj0x1658715230.jpg",
        "https://file.adquan.com/uploads_img/l8amp1658715366.jpeg",
        "https://file.adquan.com/uploads_img/xuqwj1658715366.jpeg",
        "https://file.adquan.com/uploads_img/0etn51658715366.jpeg",
        "https://file.adquan.com/uploads_img/amc281658715366.jpeg"
      ],
      "author": "源泉",
      "publish_time": "2022-07-25",
      "brand_industry": "互联网",
      "activity_type": "影视",
      "location": "中国大陆",
      "tags": [
        "JOJO",
        "创意广告"
      ]
    },
    {
      "case_id": 304807,
      "score": 5,
      "score_decimal": "9.7",
      "favourite": 147,
      "thumb": "https://oss.adquan.com/upload/20210521/16215701401eb9c75693b47324.png",
      "source_url": "https://m.adquan.com/creative/detail/304807",
      "title": "讲故事，最怕的就是真实改编",
      "description": "在今年的母亲节营销节点，麦当劳、宝洁、华为等众多国内外品牌相继推出自己的节日广告，这些作品中走煽情路线的占大比重，当然也有无言的、欢乐的亦或是令人沉思的作品。其中，滴滴发布的微电影《时间账本》，凭借女司机冯小琴的真实故事及细致的内心刻画感动到众多网友。 择善而行，三支催泪弹 滴滴母亲节微电影《时间账本》，从单亲家庭的角度切入，讲述礼橙专车成都车队队长冯小琴与女儿之间的情感羁绊。 “冯师傅2015年加入滴滴，服务订单22197单，好评率99.4%！在过去的17年中，作为单亲妈妈，独自撑起了她和女儿的小家，同时资助了另外5个孩子完成学业。”简短几句话，概括了冯小琴这6年来的人生轨迹，但生活不易，这个把时间细分成分秒的“时间超人”，却被自己的女儿“投诉”。 正如片中“母亲”的回答： “时间的账算得清，感情的账算不清。 爱，没有办法平分。” 这句话，不仅道出了冯小琴对女儿缺少陪伴的亏欠与无奈，同时也折射出千千万个缺少陪伴的家庭的影子。在极强的情感共鸣之下，民谣歌手赵雷的一首《妈妈》将观者情绪推至高潮，射出一颗超强“催泪弹”。 片尾，在滴滴司服的协调下，冯小琴也终于得到了女儿的体谅，进一步呼应滴滴“择善而行”的宣传主题。 部分网友评论 「择善而行」系列微电影始于2017年，滴滴当年发布的《落叶归根》改编自滴滴司机周旭的一次善举。 故事发生在2016年，周旭接到一个特殊的订单，乘客是一位身患癌症的病人，在声明弥留之际希望能够回到乌鲁木齐老家落叶归根，但在病人妻子尝试火车和飞机都未能如愿的情况下，最后一棵“救命稻草”落到周旭的肩上。 在周师傅看来： “我的选择虽然改变不了结局，但或许能够改变他们的人生回忆，不管前路如何，我们都应该择善而行！” 不论是出于自己的善念还是一个司机的职责，周旭完成了这个特殊的订单：从重庆到新疆乌鲁木齐，目的地是家，全程3047.3公里，历时33小时，订单0元。 这个故事感动了众多网友，不仅出于司机个人的善举，更为这一路上所收获的来自陌生人的帮助与善意。 2018年，滴滴发布微电影《最后一公里》同样催泪。故事来自一位年迈的滴滴专车司机拾师傅，坚持跑滴滴赚钱替女儿治病。视频中拾师傅接到电话后在车内崩溃大哭的桥段，最令人揪心动容。 台词更是戳人： “没想到，我还撑得住，这车先撑不住了。” 2016年，滴滴通过新闻得知拾师傅的情况，紧急调动新车帮助拾师傅度过难关。为了感恩社会及平台，拾师傅在一年内提前一公里结单2094次。 拾师傅说： “这一公里，是我替女儿说的：谢谢。” 以上「择善而行」三支短片，皆取材于滴滴司机的真实故事，从不同角度展现滴滴司机积极向善的一面，同时展现平台对司机的关怀和帮助。 真实故事，情感营销的利器 在一场情感营销中，讲好「故事」就是其中重要的一环。在这一环中，将品牌想要表达的价值理念、品牌主张注入到故事内核。一方面打动到用户，更重要的是将品牌内涵渗入到用户的心智。“真实故事改编”虽并不是不可缺要素，到它确是触及消费者情感的一剂良药。 长久以来，根据真实故事改编的广告片层出不穷，包括苹果、支付宝、大众银行、中国银联等品牌都有所尝试。早前有斩获金瞳奖微电影组全场大奖的大众银行经典广告《梦骑士》，取材于5位平均年龄81岁的老人追梦的故事；近年来有苹果的品牌大片《女儿》，取材于武汉单身妈妈带着3岁女儿开的士的真实故事；今年，京东手机推出的春节广告《最长的一盘棋》取材于无人区查尔图车站的两位轮流站岗的工作人员…… 这些“眼泪不要钱”系列，往往不需要过多的拍摄技巧，简单、真实、质朴的故事更能打动人。滴滴近年来推出的「择善而行」系列走心广告，在收获了李晨等众多明星和广泛大众的感动与好评的同时，也试图还原了一个真实立体且正向的滴滴司机形象，通过真实故事引起大众产生情感共鸣，传播「向善」的品牌温度。 滴滴借助大众产生情感共鸣的心理，传播品牌温度，一改往日滴滴在大众心目中的形象。 做有“温度”的产品 三支真实且催泪的“择善而行”系列故事就如同一场「情感」Campaign的三个milestone，将滴滴多年来的「情感」营销布局铺展开来。 这场「情感」Campaign战线拉的很长。 自2016年起，滴滴平台就担起了“就业蓄水池”作用。据滴滴官方数据：过去8年，累计逾3100万司机和车主在滴滴平台上获得灵活收入，他们分布在全国2200多个城市，在上百亿次出行中服务了5.5亿乘客。 疫情期间，有超过16万滴滴司机志愿加入滴滴医护车队。急病送医、见义勇为、拾金不昧的善举每天都在发生，这是司机与乘客之间的故事，作为平台方，滴滴也在持续发挥自己的价值。 2017年滴滴专车上线“无障碍专车”，以解决残障人士、老年人等特殊群体出行问题，到今年，滴滴无障碍出行服务已经在全国74个城市开通，超过180万司机加入，为视障用户朋友助力一程。 而身处出行行业，常常面临网络“妖魔化”的曲解，从出生就一直被舆论裹挟的滴滴，推出包括「择善而行」在内的一系列的宣传片，在引导舆论的同时，也将滴滴的暖心形象播种至用户心间。 近年来，《年度十大司机评选》活动、开通老年版打车热线和小程序、成立打击黑产专项组、#酒驾认怂行动#等活动，以不同角度向社会传递积极向上的能量，不断刷新用户对滴滴新的认知。 行至今日，经过长线、全局的营销布局，滴滴不断强化司机身份认同感、深度激发用户情感共鸣，无形中提升了滴滴在用户心中的正面形象。「择善而行」是方向，而走在这条路上的是用户、是司机、也是整个社会，作为平台方，滴滴就是这条路上的领头羊，与各位共同前行。",
      "main_image": "https://oss.adquan.com/upload/20210521/16215701401eb9c75693b47324.png",
      "images": [
        "https://file.adquan.com/uploads_img/16214351723ec1132c60825688.jpg",
        "https://file.adquan.com/uploads_img/1ygkv1621434625.png",
        "https://file.adquan.com/uploads_img/1621435176eb02d0b89c7586a0.jpg",
        "https://file.adquan.com/uploads_img/dqy841621568701.png"
      ],
      "author": "yoyo",
      "publish_time": "2021-05-21",
      "brand_industry": "互联网",
      "activity_type": "影视",
      "location": "中国大陆",
      "tags": [
        "滴滴",
        "择善而行"
      ]
    },
    {
      "case_id": 298319,
      "score": 5,
      "score_decimal": "9.5",
      "favourite": 103,
      "company_name": "环时互动",
      "company_logo": "https://oss.adquan.com/logos/1455525866117254.jpg",
      "thumb": "https://oss.adquan.com/upload/20200918/1600401087de4a5a0a0c65b74b.jpg",
      "source_url": "https://m.adquan.com/creative/detail/298319",
      "title": "给月饼拍了部「伪纪录片」，熟悉的五芳斋又回来了！",
      "description": "上周，五芳斋发布了一支中秋短片《返乡记》，平淡又温情的剧情与之前的画风差距太大，给人一种五芳斋“变了”的错觉，不过看完五芳斋最新的中秋广告片《走近科学，走近月饼》就会发现，果然是错觉，一本，《返乡记》只是拍着玩儿的中秋热身，是时候展现出自己真正的实力了。 好了言归正传，话不多说先来看片： 官方表示这支短片是“劳动人民驯服野生月饼的漫长历史”，实际上就是用不正经的沙雕纪录片形式为观众讲述了月饼的演化发展史，短片风格依旧融合科幻、复古、Y2K等网络流行元素，符合当下年轻人的大众审美趋势，“碳水ufo”“画大饼”“看B站”“被社会毒打的糯米”等非常有梗的比喻表达，既贴合生活又幽默诙谐。片中还巧设了很多有趣的彩蛋，如古人扔月饼的片段致敬《2001 太空漫游》的经典画面，甜甜圈的部分引用的是马格利特的《人类之子》画作，还有小孩吃月饼时舔到手心的三条线等无厘头情节，让内容更加娱乐化，弱化短片的广告感，激发观众主动分享和讨论的热情，让短片自带流量，再次拉近品牌与消费者之间的距离。 短片最后，富人吃月饼太硬硌掉牙的情节，其实也为后面强调五芳斋月饼软糯的卖点埋下伏笔，整支短片给人感觉都在一本正经的胡言乱语，其实还是非常有心机的，毕竟不按套路出牌，本身就是一种套路。 预热海报： 热映海报：",
      "main_image": "https://oss.adquan.com/upload/20200918/1600401087de4a5a0a0c65b74b.jpg",
      "images": [
        "https://file.adquan.com/uploads_img/3vox21600315444.png",
        "https://file.adquan.com/uploads_img/ftriv1600315458.png",
        "https://file.adquan.com/uploads_img/erbwn1600315371.jpg",
        "https://file.adquan.com/uploads_img/mx1pd1600315371.jpg",
        "https://file.adquan.com/uploads_img/iovkx1600315371.jpg",
        "https://file.adquan.com/uploads_img/46xlc1602671434.jpg",
        "https://file.adquan.com/uploads_img/f6q5u1602671434.jpg",
        "https://file.adquan.com/uploads_img/bos2a1602671434.jpg",
        "https://file.adquan.com/uploads_img/021l51602671436.jpg",
        "https://file.adquan.com/uploads_img/wq3lc1602671436.jpg",
        "https://file.adquan.com/uploads_img/ti3wa1602671436.jpg"
      ],
      "author": "heying",
      "publish_time": "2020-09-18",
      "brand_industry": "快消品",
      "activity_type": "影视",
      "location": "中国大陆",
      "tags": [
        "五芳斋",
        "中秋节"
      ]
    },
    {
      "case_id": 284752,
      "score": 5,
      "score_decimal": "9.8",
      "favourite": 89,
      "company_name": "蓝标传媒 BlueMedia等4家公司",
      "company_logo": "https://oss.adquan.com/logos/1617279980994343.jpg",
      "thumb": "https://oss.adquan.com/upload/20190523/1558546667275933.png",
      "source_url": "https://m.adquan.com/creative/detail/284752",
      "title": "奥利奥年度宫廷大戏：10600块小饼干倾情出演",
      "description": "本文为会员专享，订阅会员查看完整内容 本文共计1107字，包含1个视频、12张图片，订阅后阅读全文",
      "main_image": "https://oss.adquan.com/upload/20190523/1558546667275933.png",
      "images": [
        "https://m.adquan.com/images/vip_zk.png"
      ],
      "author": "蓝标传媒 BlueMedia",
      "publish_time": "2020-10-17",
      "tags": []
    },
    {
      "case_id": 300066,
      "score": 5,
      "score_decimal": "9.5",
      "favourite": 100,
      "company_name": "广告研习所",
      "company_logo": "https://oss.adquan.com/avator/229950_1553074220_full.jpg",
      "thumb": "https://oss.adquan.com/upload/20201208/1607420413322156.png",
      "source_url": "https://m.adquan.com/creative/detail/300066",
      "title": "德云社文案，本广告人自愧不如",
      "description": "最近文案总是上热搜，什么某某表白文案，凡尔赛文案，但都抵不过这次的德云社文案。 听惯了“曾经沧海难为水，除却巫山不是云”的古代情诗文案，对比起来，现代人的文案不免让人觉得精妙，言简意赅直指内心，“官宣”、“大家好，这是我男/女朋友XXX”等等，短短数字便将情感宣泄，恰到好处。 这不昨天，为庆祝郭德纲和于谦合作20周年，德云社联合优酷开办了一场合作20周年开幕庆典，然而火上热搜的却是德云社文案，U1S1这也太会玩了——（我们来看看） 郭德纲/于谦 ▼ 中文 【人说知己难寻，我一遇就遇了大半辈子】——郭德纲 【人说入对难成，我一搭就搭了往后余生】——于谦 英文 左：YOU COMPLETE ME. 右：MY PLEASURE. 【20周年，与有荣焉，你我当如此。】 【20周年，小半辈子都搭你身上了。】 【有人相看两厌，有人二十年如初】 孟鹤堂/周九良 【众所周知】——孟鹤堂 【山海可证】——周九良 左：BUT YOU. 右：NO ONE. 【鹤立九天笑凡尘，从此余生孟良人】 高峰/栾云平 【我可以随便说，我知道他什么包袱都接得住】——高峰 【我可以随便问，我知道他什么情形都能圆得回】——栾云平 左：WE CLICK. 右：OF COURSE. 【自然心领神会，默契无需多言，你我当如此】 冯照祥/杨鹤通 【舞台上站在你身边的快乐，都是真的】——冯照洋 【舞台上一个包袱一声响的默契，也是真的】——杨鹤通 左：ALWAYS STAY. 右：BY YOUR SIDE. 【相遇不易，你我当如此】 【恰好合拍，你我当如此】 要不是德云社的忠实观众，光这文案还以为是什么男女表白文案，这完全是暴打最近某小鲜肉的表白文案，还有除了这中文，英文才更让人感动吧，真的是太会玩了。 话不多说，自从德云社门票每次已出都持续热搜榜之后，这个强势大IP就已经可以说是稳扎稳打屹立不倒了，不仅综艺加持知名度速升，连每次的开箱盛典也都是办的热热闹闹。 据透露，德云社2021年计划，在安排商演之外，还将拍摄1000多集影视剧、3部300多集的情景剧、40多集的电视剧和网剧电影等等，可想而知一直致力于相声的德云社已经是在多栖发展，并且最大的视频平台之一优酷也已经成为德云社的流量输出口，这个IP未来不可想象。 *图片来源于网络（部分见水印）",
      "main_image": "https://oss.adquan.com/upload/20201208/1607420413322156.png",
      "images": [
        "https://file.adquan.com/pic/160741847226b73787db95137b.jpg",
        "https://file.adquan.com/pic/1607418472a6ce0684b6424e20.jpg",
        "https://file.adquan.com/pic/1607418472b8d0beb58fd15736.jpg",
        "https://file.adquan.com/pic/160741847302c95b517793ef21.jpg",
        "https://file.adquan.com/pic/1607418473c4702d03041ec9b8.jpg",
        "https://file.adquan.com/pic/160741847370db83aa914db3c0.jpg",
        "https://file.adquan.com/pic/1607418474ec34fb4a8b09da3c.jpg",
        "https://file.adquan.com/pic/16074184745babe1e325a4085e.jpg",
        "https://file.adquan.com/pic/1607418474b4ed9268ea055bcf.jpg"
      ],
      "author": "广告研习所",
      "publish_time": "2020-12-09",
      "brand_industry": "文娱、艺术",
      "activity_type": "微电影",
      "location": "中国大陆",
      "tags": [
        "德云社",
        "广告文案"
      ]
    },
    {
      "case_id": 305933,
      "score": 4,
      "score_decimal": "8.3",
      "favourite": 71,
      "company_name": "时趣",
      "company_logo": "https://oss.adquan.com/app_carousel_img/1503477261666346.jpg",
      "thumb": "https://oss.adquan.com/upload/20210709/1625826539826485.jpeg",
      "source_url": "https://m.adquan.com/creative/detail/305933",
      "title": "汰渍×利路修，一场粉圈突围战",
      "description": "简单理解粉丝经济，明星通过满足粉丝的某种情感体验需求，促使粉丝为之产生消费行为，这是粉丝经济的显著优势。但同时，粉丝经济也面临着一个越来越显著的问题。 走过大众明星时代，如今偶像可以用“量产化”来形容，粉丝们的“圈层化”属性也越来越显著。这导致无论从传播效果还是转化带货，明星营销都开始出现局限性，即品牌很难走到粉丝圈层的外围。 可见，“明星营销，突围粉圈” ，是今天每一个品牌都面临的重要课题。 今年618期间，汰渍面临的正是这个课题。在年中大促节点，汰渍牵手品牌挚友利路修，要打造一个典型的以明星创意为主的电商营销Campaign。 但这次活动汰渍不仅想要吸引粉丝群体，还想引导更多大众“路人粉”也种草产品，进入电商平台购买。如何让品牌在利路修的粉圈中出圈，是第一个问题。 与此同时，利路修作为人气偶像正迎来多家品牌热捧。据不完全统计，在其综艺节目结束不到2个月时间内，他已与18+品牌达成合作。而在618期间，官宣节奏更是紧密，几乎达到“一天一个官宣”，这是品牌面临的第二个问题。 这两个问题，让汰渍当时面临的挑战非常典型： 偶像的高频代言合作中，汰渍要「出圈」，比其它品牌内容更能吸引粉圈；同时，还要在圈层化粉丝群体中「破圈」，吸引非粉丝消费群体，影响大众用户的消费决策。 所以，汰渍最终会如何打赢这场“突围战”？它的思路非常值得品牌借鉴。 时趣作为汰渍618电商营销的Social Leading Agency，分析品牌的双重挑战后，提炼出两个核心策略思考： 1）粉圈「High点」 ： 对粉丝群体来说，在偶像的众多品牌合作内容中，他们的“分享行为”、“购买行为”门槛越来越高，只有创意真正能撩动粉丝心扉的内容，才会赢得粉丝的支持，所以 内容一定要 激发粉丝的情绪High点； 2）路人「种草点」 ： 618作为电商节，品牌的核心目的是要进行带货转化，所以围绕明星的创意，要有产品属性，能够种草粉丝。 同时，产品 种草点的提炼也一定要精准有效，不仅能种草粉丝群体，还能够透过他们的扩散分享行为，让路人也能轻松种草产品； 在两个核心策略指导下，时趣与品牌认为：今天的“明星创意”要实现出圈+破圈，同时有“带货属性”能够让产品种草粉丝与非粉丝，核心创意一定要考虑到三方面—— 创意内容要在「产品端」的种草基础上，既能戳中粉丝的情绪High点，也能轻松种草路人。 在此逻辑下，时趣与品牌开始分析各个要素： ①产品种草点： 汰渍本次主推的产品是——汰渍深层洁净洗衣凝珠和洗衣液，两款产品核心功能是「深层洁净」+「护色防串色」，而凝珠一抛，洁净、护色、防串色的优势，能够让洗衣服变成一件轻松而高效的事情。这正好解决了消费者在日益繁忙的生活节奏中，需要为洗衣“减负”的需求。 据此，「轻松高效」的洗衣方式，是产品应对的种草点，也是明星创意需要围绕的核心点。 ②粉丝High点： 传统明星营销思路，多会聚焦在艺人的颜值、艺能方面，因此最后产出的创意大多趋于相似，很难戳中粉丝的情绪High点。 如何找到不一样的明星创意灵感？经过深度分析，利路修不仅仅有着颜值和才艺，更有其自身独特的“人设故事”。他是选秀圈的一个“逆流”，面对综艺节目——“不想上班，想早点下班”；面对人生——“追求自我，向往简单生活”，这些话题不断登陆热搜，是粉丝最津津乐道的地方，也是路人粉普遍对这个偶像有感知的地方。 据此，时趣和品牌达成共识，不要只是用利路修的“形象”，还要用好他的“人设故事”。 ③路人种草点： 基于上两点的核心洞察，项目挖掘到：在利路修的人设特征中，「追求自我，坚持本色」符合汰渍的护色功效；「早点下班，追求简单生活」，对应汰渍的洗衣省时省力的优势。这些内容，既能借明星人设戳中粉丝，也具备针对路人的产品种草点。 综上，最终的种草要旨就诞生了：「像利路修一样省时省力地洗好衣服」，既打通“产品优势”，也能戳中“粉丝High点”，还具备“路人种草点”。 而这种紧密结合「产品特质+明星特质」形成的种草点，就成为品牌在面对粉丝&非粉丝群体时，一个简单有效的同步种草思路。 三招，出圈再破圈 有了基础的粉丝&大众路人同步种草思路，在创意落地时，又该如何博得粉丝喜爱，也能对路人粉进行花式产品种草？时趣和汰渍只用了三招。 主KV 1. 让出圈概念，成为种草概念 通过前文分析，传播主调锁定在「像利路修一样省时省力地洗好衣服」，那么接下来就要为整个创意提炼一个“灵魂”，一个更为精简有力的出圈概念，它会成为整个Campaign传播的主打概念。 而这个概念正如传播策略的推导，是需要同步考虑到 「产品特质」和「明星特质」 两个特点，共同去组成的一个传播概念。 据此，项目提炼出一个全新的洗衣概念——「修式洗衣」。 作为一个新词，「修式洗衣」是指：当代年轻人下课/下班已经很累，将深浅色衣服分开洗耗时麻烦，所以用汰渍深层洁净洗衣凝珠，一颗深层洁净，护色防串色。 当时这个概念出现后，立马与其它品牌的代言站台形成差异化，在借助明星的人设特征的基础上，完美表达了汰渍洗衣产品的种草点，还引导延伸出一种“洗衣潮流”而快速赢得粉丝热议，开始在粉圈“出圈”。 伴随着概念出圈，产品的种草点也开始从粉圈扩散。从洞察引擎分析的数据来看，利路修首次与家清类品牌的合作，快速抓住粉丝舆情积极评价，提升了品牌和产品的认知度。 2. 创意碎片化，更要稀缺化 如今明星创意很容易陷入的一个“坑”是：面对多个传播渠道，碎片化的创意内容很容易只聚焦明星、粉圈，而忽略路人圈层，这使粉圈外的用户大多会对传播“无感”。 而本次战役从618电商节背景，到提炼「修式洗衣」的出圈概念，能看到核心的目标群体除了粉丝圈层，还包括更多的路人大众消费者。所以落到执行端，汰渍需要让「修式洗衣」这个概念有多种内容表达，在碎片化的同时还能做到撩粉，也能让路人粉Get到创意的趣味与种草点。 在具体执行时，在没有视频大片的情况下，核心思路是即便创意碎片化，也要让每一个碎片创意都稀缺好玩、有梗有互动。 比如，在官宣以“条漫”的创新方式，形象演绎产品的使用场景，快速解读“修式洗衣”的简单高效。 条漫（节选） 再如，项目跳脱大多品牌常用的视频创意思路，而是深挖利路修的“隐藏”特质，借助他本人超有特色的声音，制作了一系列种草语音视频。 这一系列无画面的语音视频，会包含利路修各种不同语气语音视频版本，都会以解锁的方式，吸引粉丝群体进入站内并持续关注。 同时，还会安排无字幕版本，邀请粉丝参与听力考试。利老师的特殊发音引发粉丝调侃，甚至催生“AI机器男友”的社交话题梗，也吸引了一大波路人粉。 这些既围绕明星特质，既吸引粉丝又通俗有趣的产品种草创意，很快就随着用户的好评开始破圈，更激发了粉丝产生大量UGC，进而影响到路人粉的关注。 粉丝UGC “我有而他无”，创意的稀缺性，是今天偶像代言暴涨之后，品牌围绕明星创意的核心思考。 出条漫、做语音视频、想方设法和粉丝玩梗互动，带着核心概念在多个平台种草，这一系列创意，都是深挖利路修与产品结合点的结果。找到一些有别于其它品牌的传播内容，才能赢得粉丝的广泛好评，更能引发路人粉的关注。 3. 多维触达，多元种草 品牌通过前期创意吸引粉圈和路人粉的注意力后，让「修式洗衣」成为一个“简单”版的种草印象后，此时品牌要加快决策转化，就要紧随热度，进行更深度的产品解读，让后续的强势种草能够快速跟进。 在微博端，启用了一批种草博主，制作一系列产品种草视频，跟随主话题「修式洗衣」的热度，轻松吸引粉丝观看内容，进而了解产品更多细节，强化种草。 在抖音端，项目也接住「修式洗衣」的梗，邀请一批抖音KOL，从多个内容角度制作不同创意视频去花式演绎概念，趣味模仿修式洗衣，让这个粉圈出圈的概念在抖音进行破圈，使更多用户了解什么是「修式洗衣」与产品的优势。 这一系列项目传播，最终为品牌2个官方话题赢得6400w+总阅读量，其中仅视频素材总播放量就高达1100w+，为项目斩获极高曝光量；同时这种曝光，全程捆绑产品种草点，助力汰渍618成绩显著提升。 综上， 明星营销走到如今，已经不只是粉丝营销，而是一场“突破品牌包围和粉丝圈层”的双重突围战。 汰渍这个案例的思路：深挖洞察「产品、粉丝、路人」三者的关联，以稀缺好玩的碎片化种草创意，是帮助品牌赢得明星战役的重要经验。",
      "main_image": "https://oss.adquan.com/upload/20210709/1625826539826485.jpeg",
      "images": [
        "https://file.adquan.com/uploads_img/dtubp1625826394.jpeg",
        "https://file.adquan.com/uploads_img/hwai61625826406.png",
        "https://file.adquan.com/uploads_img/yvb2a1625826422.jpeg",
        "https://file.adquan.com/uploads_img/hmauy1625826453.jpeg",
        "https://file.adquan.com/uploads_img/yp3vz1625826470.jpeg",
        "https://file.adquan.com/uploads_img/29hvs1625826497.png",
        "https://file.adquan.com/uploads_img/7yhxd1625826512.png",
        "https://file.adquan.com/uploads_img/8y1ca1625826521.png",
        "https://file.adquan.com/uploads_img/8lko31625826533.png"
      ],
      "author": "时趣",
      "publish_time": "2021-07-19",
      "brand_industry": "互联网",
      "activity_type": "影视",
      "location": "中国大陆",
      "tags": [
        "汰渍",
        "利路修"
      ]
    },
    {
      "case_id": 49002,
      "score": 5,
      "score_decimal": "9.4",
      "favourite": 133,
      "thumb": "https://oss.adquan.com/upload/20190202/1549096882fe7ff9b0f33638c4.jpg",
      "source_url": "https://m.adquan.com/creative/detail/49002",
      "title": "辣眼睛 ! 999感冒灵竟然出秋裤了！！",
      "description": "那个曾经用《总有人偷偷爱着你》收割了人们大把眼泪的999感冒灵，昨晚画风突然一转，出了四套“暖心秋裤套装”，而且这风骚设计简直辣眼睛…… 不凉少年版 看上去很酷其实很暖 社会路上穿秋裤 温暖贴心不装酷 穿久保灵版 越穿越暖 越穿越灵 升职加薪穿久保灵 温暖贴心三九感冒灵 养生朋克版 蹦迪解千愁 高腰暖心头 人参可乐枸杞啤酒 朋弟秋裤999 跪舔客户版 客户暖才是真的暖 logo越大越有感 铺满全身更温暖 意不意外？刺不刺激？竟然还有点想要拥有是怎么回事？999感冒灵的秋裤，听上去就吊的一批。不凉少年版、穿久保灵版、养生朋克版、跪舔客户版每一版都强调了“暖暖的很贴心”，总有一款适合你。妈妈再也不用担心我撞款啦！传上这条999秋裤，我就是这条gai最亮的仔！（推眼镜） 网友也表示惊呆了，纷纷表示：“这是什么沙雕广告，但好想要是怎么回事！”也有人担心：“连体秋裤，怎么上厕所啊？” 据悉，999联合庞门正道举办了《999感冒灵暖心设计大赛》，这四款秋裤就是从中被甲方爸爸选中然后脱颖而出的。还获得了其“最大脑洞奖”。",
      "main_image": "https://oss.adquan.com/upload/20190202/1549096882fe7ff9b0f33638c4.jpg",
      "images": [
        "http://file.adquan.com/pic/15490960827a4210c3b492135d.jpg",
        "http://file.adquan.com/pic/15490960825bf5320869b652f8.jpg",
        "http://file.adquan.com/pic/1549096082fc4cb35c62e9bece.jpg",
        "http://file.adquan.com/pic/1549096083b59f4dc41c6b1595.jpg",
        "http://file.adquan.com/pic/1549096083647d4ca0b373b64b.jpg",
        "http://file.adquan.com/pic/154909608385cec345c92d4922.jpg",
        "http://file.adquan.com/pic/1549096083f542e967d9f9762d.jpg",
        "http://file.adquan.com/pic/154909608349f5905d12d1fa0e.jpg"
      ],
      "video_url": "https://v.qq.com/txp/iframe/player.html?vid=d0834030o1u&tiny=0&auto=0",
      "author": "王威",
      "publish_time": "2019-02-02",
      "brand_industry": "互联网",
      "activity_type": "影视",
      "location": "中国大陆",
      "tags": [
        "999感冒灵"
      ]
    },
    {
      "case_id": 47653,
      "score": 5,
      "score_decimal": "9.3",
      "favourite": 139,
      "thumb": "https://oss.adquan.com/upload/20181213/15446993189d9f4002c8789397.jpg",
      "source_url": "https://m.adquan.com/creative/detail/47653",
      "title": "这次的华为，好！可！爱！",
      "description": "为了即将在长沙召开新品发布会，华为最近拍了一系列广告，都十分的脑洞大。让人一度以为华为要成为“沙雕”的代名词。然而这次的三支广告，扭转了大家的看法，也受到了不少好评。 天台篇 泳池篇 魔术篇 三支短片利用了俯视的角度，用生活中的一些细节和情节来体现华为nova4的摄像头设计。取缔了各大手机厂商的“齐刘海”设计，突出华为“极点全面屏”的卖点。视频简短有力，画面也非常简洁可爱，十分讨喜。并且无论是构图、画面还是色调以及整体感觉，都“高级感”十足。这也贴合了华为的产品理念和卖点。",
      "main_image": "https://oss.adquan.com/upload/20181213/15446993189d9f4002c8789397.jpg",
      "images": [],
      "video_url": "https://v.qq.com/txp/iframe/player.html?vid=u0810t6p9q1&tiny=0&auto=0",
      "author": "王威",
      "publish_time": "2018-12-14",
      "brand_industry": "数码、通讯",
      "activity_type": "影视",
      "location": "中国大陆",
      "tags": [
        "华为"
      ]
    },
    {
      "case_id": 300702,
      "score": 4,
      "score_decimal": "8.6",
      "favourite": 100,
      "thumb": "https://oss.adquan.com/upload/20210106/160990112431709535d334bc50.jpg",
      "source_url": "https://m.adquan.com/creative/detail/300702",
      "title": "元气森林“豪赌”B站",
      "description": "最近，元气森林推出的一组“B站式”广告，谐音梗、B站梗齐飞，沙雕又搞笑。 元气森林重金拿下B站跨年晚会冠名，还相继推出一部爆梗的B站“定制版”系列短片；一支联合多位UP主的跨年励志广告；一支致敬伟人、不甘挫败的跨年预热TVC；一首腾格尔主唱的说唱“广告曲”。一系列“烧钱”举动，可以看出元气森林对B站极高的重视程度。 早在《2020最美的夜》播出之前，先火了两部短片。 另一支短片是元气森林的品牌宣传片，同样带有魔幻、未来式的风格。 元气森林这支品牌主题广告片《你敢不敢》，向六位伟人致敬。比较有趣的是，在短短90秒的短片中竟然隐藏了10个彩蛋。 01 开篇场景是爱迪生的出生地：美国俄亥俄州米兰镇 02 致敬电影《电力之战》 03 荒漠的场景 暗示灵感枯竭 04 场景中融入了《星空》和《向日葵》 05 “呦呦鹿鸣”——《诗经》 画面中的鹿暗指屠呦呦 06 灵感来自宫崎骏的《幽灵公主》 07 阿姆斯特朗火箭飞升月球上第一个脚印 08 乔布斯致敬《苹果1984》经典广告 09 张伟丽 灵感来自《疯狂的麦克斯：狂暴之路》 10 元气森林《权力的游戏》的铁王座 由此可以看出元气森林的“野心”——对标可口可乐，成为饮料品牌的代表。",
      "main_image": "https://oss.adquan.com/upload/20210106/160990112431709535d334bc50.jpg",
      "images": [
        "https://file.adquan.com/pic/160989934197a440ef382990ea.jpg",
        "https://file.adquan.com/pic/160989934185f562557c09208e.jpg",
        "https://file.adquan.com/pic/1609899341104f7fd4af44c815.jpg",
        "https://file.adquan.com/pic/1609899341d97a772b2214363b.jpg",
        "https://file.adquan.com/pic/1609899341fe0bd7f278949f9d.jpg",
        "https://file.adquan.com/pic/1609899341231bdf243a6bbd26.jpg",
        "https://file.adquan.com/pic/1609899342e6c94b65daa53554.jpg",
        "https://file.adquan.com/pic/16098993421ce839e8936cf5b0.jpg",
        "https://file.adquan.com/pic/1609899342306dcad3a7d59fbf.jpg",
        "https://file.adquan.com/pic/16098993420a1dc3ad8ce740db.jpg",
        "https://file.adquan.com/pic/16098993429ec3b011c56961e0.jpg",
        "https://file.adquan.com/pic/1609899343edaa14fe3e1910e6.jpg",
        "https://file.adquan.com/pic/16098993437539b1f7aeb15497.jpg",
        "https://file.adquan.com/pic/1609899343612f9537bf2bb011.jpg",
        "https://file.adquan.com/pic/1609899343670871e758d7918d.jpg",
        "https://file.adquan.com/pic/160989934328b9d3e20adda11c.jpg"
      ],
      "author": "yoyo",
      "publish_time": "2021-01-06",
      "brand_industry": "电商、零售",
      "activity_type": "影视",
      "location": "中国大陆",
      "tags": [
        "元气森林",
        "B站"
      ]
    },
    {
      "case_id": 299529,
      "score": 5,
      "score_decimal": "9.2",
      "favourite": 134,
      "company_name": "adam&eveDDB 伦敦 英国",
      "company_logo": "https://oss.adquan.com/logos/1525768354264498.jpg",
      "thumb": "https://oss.adquan.com/upload/20201116/1605503656d1f29a211c3fa2d6.jpg",
      "source_url": "https://m.adquan.com/creative/detail/299529",
      "title": "圣诞节重头戏，John Lewis今年又出了一支神仙广告",
      "description": "每当英国百货John Lewis发布新的圣诞广告时，圣诞就真的不远了。从2007年至今，John Lewis的圣诞广告每年都不曾缺席，今年依旧如期而至。 短片通过一系列平淡又充满爱的日常生活片段，组合成了一个首位完美衔接的传递爱的故事，当小女孩帮小男孩拿下卡在树上的足球时，爱心仿佛被触发了多米诺骨牌效应，在城市的各个角落之间互相传递，环环相扣的情节到最后又回到短片开头的场景，结尾点明主题“Give a little love,together we can make a big difference”。 一个小小的善举就能引发一系列的连锁效应，John Lewis希望通过这个温暖的小故事让人们意识到“a little love”的强大之处，如果每个人都愿意多付出一点点，这个世界将会有很大的不同。 对所有人来说，今年都是一个难过的坎，对John Lewis来说更是如此。作为英国最大的百货公司，John Lewis仅上半年就亏损了6.35亿英镑，目前已经关闭8家百货商店和4家旗下 Waitrose 超市，削减了1390个职位，不久前宣布将对总部职能重组，削减1500个职位。 生活越是艰难，人们越是渴望用美好和温暖来寻求心灵慰藉。于是John Lewis带来了这样一支可爱又温馨的短片。不管是画面还是配乐，每一个细节都非常用心。 视觉方面是今年最大的亮点。与以往单一的呈现形式不同，从真人、手绘、黏土、毛毡到CGI，全片由8位艺术家采用9种不同风格的片段组成，不同画风之间过渡自然衔接巧妙，毫无违和感。 参与制作的创作者中，既有影视、音乐界专业知名人士，也包括多位艺术家和应届毕业生，英国音乐总监奥斯卡·哈德森、曾获奥斯卡提名的法国导演西尔万·乔梅特、韦斯·安德森动画电影《 Isle Of Dogs》首席动画师安迪·根特等多位行业大咖与大学生协作配合，碰撞出了奇妙的创意火花。 片中的BGM则是英国歌手Celeste为此原创的新歌《A Little Love》，慵懒舒缓的声线和轻松柔和的曲调与“爱”的主题和节日气氛非常契合。 创意之外，持续关注慈善公益事业也是John Lewis每年圣诞的重点。今年，John Lewis和旗下连锁超市Waitrose与公益组织Home-Start和FareShare合作，为100,000个有需要的家庭提供资金以及物质方面的帮助。 Give a little love系列圣诞限定周边也在官网以及线下门店同步发售，包括香薰、胸针、马克杯、帆布包、T恤，还有短片中小女孩的同款爱心雨伞，所有周边的利润都将会捐赠给慈善机构。 此外，背景音乐《A Little Love》也是该项目公益事业的一部分。每当有人在在各大音乐平台购买一次该首歌，Celeste和她的唱片公司Polydor都会向慈善机构捐款10便士；John Lewis还发起短信献爱心的公益活动，人们可以通过向70630发送不同的关键词向公益组织捐赠不同金额。 最后给大家分享几个暖心的小彩蛋。 为了呼应今年「Give a little love」的主题，John Lewis还把网站和社交网站logo中的“ o ”改成了一个小爱心。 疫情期间，John Lewis线下门店多次关闭， 只有Waitrose 超市一直在营业，为人们提供送货上门的服务，这也是短片传递爱心的灵感来源。 短片最后给小女孩贴上爱心贴纸的好心人其实是NHS的医生，借此向疫情期间坚守在第一线的医护人员表示致敬。 看过John Lewis之前圣诞广告的朋友一定非常清楚，圣诞礼物是 John Lewis 广告里每年的核心元素，但是今年，整支短片从头到尾都没有明确提及礼物，反而在不断突出爱心的元素，为大家真正营造出一个童话般的美好世界，言外之意是想告诉人们，爱，才是这个圣诞最好的礼物。 在这个格外寒冷的冬天，让我们对这个世界和身边的人多点善意吧~ 文中视频及图片资料来自于John Lewis官网",
      "main_image": "https://oss.adquan.com/upload/20201116/1605503656d1f29a211c3fa2d6.jpg",
      "images": [
        "https://file.adquan.com/uploads_img/g6us91605501457.png",
        "https://file.adquan.com/uploads_img/ijb0o1605501480.png",
        "https://file.adquan.com/uploads_img/ncw6g1605501322.png",
        "https://file.adquan.com/uploads_img/qz3v51605501345.png",
        "https://file.adquan.com/uploads_img/tuo391605501383.png",
        "https://file.adquan.com/uploads_img/vkf131605501429.png",
        "https://file.adquan.com/uploads_img/16055036640dd4b1a115047088.jpg",
        "https://file.adquan.com/uploads_img/pebwh1605502751.png",
        "https://file.adquan.com/uploads_img/jc3ga1605503053.png",
        "https://file.adquan.com/uploads_img/2zlgr1605505978.png",
        "https://file.adquan.com/uploads_img/noi1g1605509225.png",
        "https://file.adquan.com/uploads_img/vilta1605509250.png",
        "https://file.adquan.com/uploads_img/xder01605509793.png",
        "https://file.adquan.com/uploads_img/7c0lb1605509504.png",
        "https://file.adquan.com/uploads_img/g0me21605516703.gif",
        "https://file.adquan.com/uploads_img/4hyzx1605516893.gif"
      ],
      "author": "heying",
      "publish_time": "2020-12-24",
      "brand_industry": "商超、贸易",
      "activity_type": "影视",
      "location": "欧洲",
      "tags": [
        "John Lewis百货",
        "圣诞节"
      ]
    }
  ]
}