{
  "batch_num": 92,
  "batch_size": 20,
  "created_at": "2026-01-18T10:36:06.136341",
  "cases": [
    {
      "case_id": 44076,
      "score": 5,
      "score_decimal": "9.7",
      "favourite": 14,
      "company_name": "GOODZILLA 意类",
      "company_logo": "https://oss.adquan.com/logo/1534402897503501.jpg",
      "thumb": "https://oss.adquan.com/upload/20180412/1523522998356e72daed4245fa.jpg",
      "source_url": "https://m.adquan.com/creative/detail/44076",
      "title": "易烊千玺 ，天猫首位代言人！",
      "description": "那边易烊千玺中戏成绩专业第一的热度未下，这边易烊千玺成为天猫首位代言人的热度又起。打开微博淘宝天猫优酷芒果等软件皆被四字弟弟刷屏，除了大量的H5广告投放，易烊千玺代言天猫的广告片也在近日发布。 同时，天猫理想生活还开启了“天猫21天元气计划”，自4月12号起的21天内，易烊千玺以天猫首位代言人的身份，向大家发起理想生活倡议，21天养成一个好习惯。每天早晨都能解锁不一样的易烊千玺，粉丝怕是已经按捺不住了。 4.12 第一天福利打包 天猫此次邀请易烊千玺担任代言，也反映品牌宣传重心渐渐向00后新生代转移。",
      "main_image": "https://oss.adquan.com/upload/20180412/1523522998356e72daed4245fa.jpg",
      "images": [
        "http://file.adquan.com/upload/20180412/152352294719700124ae8cddae.jpg",
        "http://file.adquan.com/upload/20180412/1523522984d9f185a2d904c859.jpg",
        "http://file.adquan.com/upload/20180412/15235228737a4437807497b797.jpg"
      ],
      "video_url": "http://v.qq.com/iframe/player.html?vid=k06286y2ar9&tiny=0&auto=0",
      "author": "Garbo",
      "publish_time": "2018-04-12",
      "brand_industry": "电商、零售",
      "activity_type": "影视",
      "location": "中国大陆",
      "tags": [
        "易烊千玺",
        "天猫"
      ]
    },
    {
      "case_id": 317272,
      "score": 4,
      "score_decimal": "8.4",
      "favourite": 17,
      "company_name": "KFC 肯德基",
      "company_logo": "https://oss.adquan.com/logo/20131205180414_74586_320.png",
      "thumb": "https://oss.adquan.com/upload/20220722/1658477483bdf023730e784943.png",
      "source_url": "https://m.adquan.com/creative/detail/317272",
      "title": "肯德基为新品拍恐怖电影，看完你还有食欲吗？",
      "description": "快餐广告往往简短而喧闹，肯德基为宣传新品Pollizza——用炸鸡代替了比萨饼底，发布了一支长达14分钟的恐怖剧情短片《La Massacre 》（大屠杀），其背景和灵感来自 50 年代和 60 年代好莱坞制作的 B 级恐怖片。 短片最初的创意来自，由纽约州立大学执导，讲述了五名青少年前往树林中的一间偏僻小屋度过周末的故事。安顿好后，他们发现只带了饮料而忘记带食品，于是他们决定从一个神秘的披萨店点晚餐，然而没有人想象到他们会遭遇到可怕的结果...... 虽然整部短片充满了恐怖元素，但还是肯德基品牌一贯的幽默和轻松的基调不变。 PS21执行创意总监Víctor Blanco说：“我们都喜欢披萨，但不是每个人都喜欢面团，这正是 Pollizza 所没有的唯一成分。考虑到这一点，我们决定制作一部 13 分钟的 B 级恐怖短片，几个邪恶的“面饼”暴徒袭击了一群准备在湖边的房子中度过周末的年轻人。这是一个不错的想法。” 这部影片自24小时前推出以来，在 Twitter 和 YouTube 上累积了 10 万次访问和 130 万次互动，一天之内通过社交媒体覆盖 1300 万人。短片中出现在披萨盒上的电话号码，是在发布周期间提供优惠和促销活动的号码，2500人致电并以更优惠的价格获得了“Pollizza”。",
      "main_image": "https://oss.adquan.com/upload/20220722/1658477483bdf023730e784943.png",
      "images": [
        "https://file.adquan.com/uploads_img/o0pbi1658477271.jpeg"
      ],
      "author": "Emily",
      "publish_time": "2022-07-22",
      "brand_industry": "快消品",
      "activity_type": "影视",
      "location": "其他地区",
      "tags": [
        "肯德基",
        "恐怖片"
      ]
    },
    {
      "case_id": 45400,
      "score": 3,
      "score_decimal": "6.9",
      "favourite": 10,
      "thumb": "https://oss.adquan.com/upload/20180720/15320958343e7394c12bd585f1.jpeg",
      "source_url": "https://m.adquan.com/creative/detail/45400",
      "title": "生理期的女生，是魔鬼吗！！",
      "description": "生理期，这个只是听了就感到肚子隐隐作痛的词，想必是每个女孩子不可言说的痛。而传说，女生生理期的时候，会化身魔鬼…… 女生来姨妈有多可怕，看了这个视频就知道了，为了应付女友来姨妈，男生还专门请来了“应付生理期专家”，然并卵……男生的下场依旧很惨。生理期的女生焦躁、易怒、控制不住情绪、多疑，这时候你连呼吸都是错的…… 这支广告秉承了泰国广告一贯的风格和特点，脑洞大、夸张+神转折，将女生生理期的负面情绪放大，利用男女主人公之间的冲突，放大生理期给两人带来的影响，然后果不其然……在结尾的时候顺势推出这个名为therma plast的产品，表达出以上复杂而且并不管用的方法，不如简简单单的来个暖宝宝有效的多。",
      "main_image": "https://oss.adquan.com/upload/20180720/15320958343e7394c12bd585f1.jpeg",
      "images": [],
      "video_url": "http://v.qq.com/iframe/player.html?vid=d0731d16ghy&tiny=0&auto=0",
      "author": "王威",
      "publish_time": "2018-07-21",
      "brand_industry": "快消品",
      "activity_type": "影视",
      "location": "泰国",
      "tags": [
        "泰国"
      ]
    },
    {
      "case_id": 317145,
      "score": 4,
      "score_decimal": "7.3",
      "favourite": 33,
      "thumb": "https://oss.adquan.com/upload/20220719/1658226136e5440feaf1e5e6e1.png",
      "source_url": "https://m.adquan.com/creative/detail/317145",
      "title": "语言的杀伤力有多大？这组海报让人陷入沉思",
      "description": "有一种看不见的伤害，叫语言暴力。看似无形，但其实在伤人这块一点都不亚于肢体伤害。埃及达米埃塔大学设计了一系列海报，以用来提醒人们注意话语不当的杀伤力。 01 你的话让我绝望 02 你的话像一把刀，让人很痛苦 03 你的话像一把锯子 鲜红的血液、恐怖的电锯与刀以及忧伤的文案，这些元素结合在一起，将语言暴力带来伤害充分形象化，达到警示的效果。 除了这一系列海报，埃及达米埃塔大学还以“慈悲是一个动词”发布过一组风格类似的海报，很形象地展示了动物因人类遭受的伤害，目的是呼吁大家保护动物，不要为了一己私利，滥杀无辜。",
      "main_image": "https://oss.adquan.com/upload/20220719/1658226136e5440feaf1e5e6e1.png",
      "images": [
        "https://file.adquan.com/uploads_img/fuagy1658224493.png",
        "https://file.adquan.com/uploads_img/tul8v1658224540.jpg",
        "https://file.adquan.com/uploads_img/8airb1658224658.png",
        "https://file.adquan.com/uploads_img/63c9l1658225165.png",
        "https://file.adquan.com/uploads_img/pkoi11658225178.png",
        "https://file.adquan.com/uploads_img/qyvds1658225194.jpg",
        "https://file.adquan.com/uploads_img/v9qoz1658225210.png",
        "https://file.adquan.com/uploads_img/pv9ir1658225228.png",
        "https://file.adquan.com/uploads_img/lmp2x1658225242.png",
        "https://file.adquan.com/uploads_img/2cpqh1658225274.png"
      ],
      "author": "River",
      "publish_time": "2022-07-19",
      "brand_industry": "政府、非盈利机构",
      "activity_type": "平面",
      "location": "其他地区",
      "tags": [
        "语言暴力",
        "保护动物"
      ]
    },
    {
      "case_id": 340447,
      "score": 4,
      "score_decimal": "8.6",
      "favourite": 37,
      "company_name": "Kiehl’s 科颜氏",
      "company_logo": "https://oss.adquan.com/logo/20140122183446_12038_320.png",
      "thumb": "https://oss.adquan.com/upload/20240220/1708414044b4f91cc51eb52124.png",
      "source_url": "https://m.adquan.com/creative/detail/340447",
      "title": "科颜氏CGI广告：蒙娜丽莎皮肤干裂？",
      "description": "冬季， 科颜氏发布CGI广告片，用尔滨雪人、蒙娜丽莎、纽约大楼，展示出「高保湿水光棒」解决冬季皮肤问题的产品功效。 风从四面八方来，尔滨雪人脸都冻红了？ 科颜氏高保湿水光棒，一抹改善冬日泛红。 冬日大降温皮肤干裂？蒙娜丽莎在纽约时代广场发出紧急信号。 科颜氏高保湿水光棒，一抹改善爆皮干纹。 纽约大楼出现玻璃爆裂？ 科颜氏高保湿水光棒，一抹修护受损屏障",
      "main_image": "https://oss.adquan.com/upload/20240220/1708414044b4f91cc51eb52124.png",
      "images": [],
      "author": "永刚",
      "publish_time": "2024-02-20",
      "brand_industry": "时尚、美妆",
      "activity_type": "影视",
      "location": "中国大陆",
      "tags": [
        "科颜氏",
        "CGI"
      ]
    },
    {
      "case_id": 317570,
      "score": 5,
      "score_decimal": "9.2",
      "favourite": 38,
      "thumb": "https://oss.adquan.com/upload/20220801/16593504091e5ce11b5c7be2a4.png",
      "source_url": "https://m.adquan.com/creative/detail/317570",
      "title": "这支床垫广告拍出了失眠精髓，慢一步的反应太真实！",
      "description": "睡眠问题一直是困扰着很多人的永恒问题，美国最大的专业床垫零售商Mattress Firm推出「垃圾睡眠活动」，通过夸张的手法展现了睡不好觉引发的一系列不可控事件。看完这个广告，你想睡个好觉了吗？ 短片用一系列幽默夸张的手法表现了“垃圾睡眠”给各种人带来的不同影响。垃圾睡眠让棒球员的反应慢了200小时，结果比赛都结束了，他才开始挥棒；三胞胎因为睡眠不好，忘记自己和兄弟搬到了一起住，互相碰到后非常震惊；街头表演家因为糟糕的睡眠让背部受伤，使他的表演变得更加糟糕；还有深夜娱乐、社交媒体成瘾...... 通过隐喻各种不良的睡眠习惯，展现Mattress Firm床垫的舒适柔软。 此外，从7月26日开始，Mattress Firm 将在美国全国巡回演出，并在纽约市、底特律和休斯顿的睡眠不足消费者家中停留，帮助他们找到完美的床垫。人们还可以通过在 Instagram 或 Twitter 上发布他们不舒适床垫的照片，并打上固定标签来简短描述他们为什么遭受垃圾睡眠的侵害，将有机会获得新床垫以及Mattress Firm睡眠专家提供个人垃圾睡眠咨询。",
      "main_image": "https://oss.adquan.com/upload/20220801/16593504091e5ce11b5c7be2a4.png",
      "images": [],
      "author": "Emily",
      "publish_time": "2022-08-02",
      "brand_industry": "快消品",
      "activity_type": "影视",
      "location": "美国",
      "tags": [
        "床垫"
      ]
    },
    {
      "case_id": 40636,
      "score": 4,
      "score_decimal": "7.3",
      "favourite": 21,
      "company_name": "Jung Von Matt 汉堡 德国等2家公司",
      "company_logo": "https://oss.adquan.com/logos/1525339521883351.jpg",
      "thumb": "https://oss.adquan.com/upload/20170510/1494385715512352.jpg",
      "source_url": "https://m.adquan.com/creative/detail/40636",
      "title": "这次，三星把瑞士的报纸给“搞乱”了",
      "description": "这次，三星把瑞士的报纸给“搞乱”了。 三星为了在瑞士推广Galaxy S8，决定对瑞士规模最大的德语日报20 Minuten下手，邀请德国广告公司Jung von Matt和当地设计工作室Studio Feixen联手“涂改”日报，谓之“再设计”，把整份报纸都搞成了自己的特刊。 三星表示，此番希望大家能够关注到S8背后的设计理念，故意采用飞溅、曲线、涂鸦式图案覆盖在报纸的文字上。之所以选择报纸，是因为瑞士为报纸密度最高的国家之一，91%以上的瑞士人每天至少阅读一种报纸。而20 Minuten（20分钟）是免费德语日报，专门针对年轻都市白领，在瑞士德语区（瑞士有17个州的官方语言是德语）乃至整个瑞士日报市场都占据着首席地位。",
      "main_image": "https://oss.adquan.com/upload/20170510/1494385715512352.jpg",
      "images": [
        "https://oss.adquan.com/upload/20170510/1494385407809073.jpg",
        "https://oss.adquan.com/upload/20170510/1494385433121734.jpg",
        "https://oss.adquan.com/upload/20170510/1494385444478968.jpg",
        "https://oss.adquan.com/upload/20170510/1494385452706341.jpg",
        "https://oss.adquan.com/upload/20170510/1494385460406353.jpg",
        "https://oss.adquan.com/upload/20170510/1494385470856746.jpg",
        "https://oss.adquan.com/upload/20170510/1494385477966899.jpg"
      ],
      "author": "庄何丽",
      "publish_time": "2017-05-10",
      "brand_industry": "数码、通讯",
      "activity_type": "平面",
      "tags": [
        "三星"
      ]
    },
    {
      "case_id": 314106,
      "score": 5,
      "score_decimal": "9.6",
      "favourite": 21,
      "thumb": "https://oss.adquan.com/upload/20220330/1648634307fc13cf2c26eb8df8.png",
      "source_url": "https://m.adquan.com/creative/detail/314106",
      "title": "与粉丝共创时间循环的科幻大片，有被卷到！",
      "description": "粉丝共创+科幻+时间循环+奥斯卡提名导演， 这支广告的噱头就很吸引人！美国最红的墨西哥快餐塔可贝尔（Taco Bell）为人气产品Nacho Fries辣玉米片薯条的回归发起了一项挑战赛，与粉丝共创了预告片《Fry Again》。 Taco Bell 和创意机构 Deutsch LA 以粉丝的想法为基础，聘请了获得奥斯卡提名的导演肖恩·贝克（Sean Baker）来制作即将上映的完整片。整部短片充满了好莱坞大片传统的华丽视觉效果和惊险刺激的飙车名场面。 Taco Bell 与190 万推特粉丝合作，人们进入一个虚拟作家的房间，回答他们在下一个 Nacho Fries 章节中看到的内容，将这些内容创作成了一个无限循环的一天，使得人们每一个循环中都可以看到自己的影子。粉丝们还帮助选择了主角名字“ Vanessa”，选择她将驾驶的跑车类型，确定主角的服装、搭档，一直到将她的狗命名为“Baja”。这个故事可能没有背景故事或伏笔，但每天重播Nacho Fries总是摆在桌面上，传达粉丝们渴望在菜单上总是有 Nacho Fries，但现实情况是限时供应，增加吸引力。",
      "main_image": "https://oss.adquan.com/upload/20220330/1648634307fc13cf2c26eb8df8.png",
      "images": [],
      "author": "Emily",
      "publish_time": "2022-03-30",
      "brand_industry": "快消品",
      "activity_type": "影视",
      "location": "美国",
      "tags": [
        "科幻",
        "好莱坞"
      ]
    },
    {
      "case_id": 340291,
      "score": 4,
      "score_decimal": "8.3",
      "favourite": 20,
      "company_name": "温氏食品等2家公司",
      "company_logo": "https://oss.adquan.com/logos/1547522666903232.jpg",
      "thumb": "https://oss.adquan.com/upload/20240220/1708415877876409.jpg",
      "source_url": "https://m.adquan.com/creative/detail/340291",
      "title": "温氏食品年味儿广告又双叒来了，这回把世界冠军“馋”上了!",
      "description": "味道，是一段纽带、是一份回忆、是一股力量。 是否有一种味道让你此生难忘？始终支撑着你一直向前？ 这个问题，让我们的世界冠军-雅思组合来回答再合适不过了。 新春之际， 温氏食品×人民网联合献映，年度温情大片《守味人》系列微电影第三季 又双叒来啦!!! 这次，我们继续以一道家常菜为线索， 携手国羽混双世界冠军郑思维与黄雅琼联袂出演，为你揭开世界冠军背后那些鲜为人知的真实故事 ，看看究竟是怎样的味道能够陪伴世界冠军一路拼搏、一起去赢？ 《守味人3》 微电影 根据世界冠军真实故事拍摄 ，采用非线性叙事的手法，讲述了郑思维自幼离家苦练羽毛球的历程。因受到球队新年集训的压力且屡次受挫，年幼的 郑思维赌气拒绝了妈妈千里迢迢送来的鸡汤 ，却也因此辜负了妈妈的心意，内心十分愧疚。 故事回溯到这次探望之前，爸爸妈妈从浙江来探望小思维，随同而来的还有一个巨巨巨巨巨重无比的行李箱，在爸爸妈妈的“重点关注”之下，谁都不知道 箱子里面究竟是什么？ 直到某天，小思维想要跟爸妈道歉， 无意间，却揭开了行李箱里妈妈的秘密… 原来自己喝的 鸡汤都是妈妈千里迢迢带过来训练基地，精心熬制的 。因为知道新鲜的土鸡汤对运动员身体好，妈妈常常会去到当地的温氏土鸡农场，亲自动手抓最活泼的土鸡炖汤， 全心全意想要把最好的营养给到思维，全力支持他成为冠军的梦想。 当真相被揭开，妈妈在背后默默的守味和付出，最后都转化成为了思维努力拼搏的动力。日复一日、年复一年，用汗水和勤奋来 贯彻“球不落地，永不放弃”的精神，并在妈妈和搭档黄雅琼的支持之下，最终赢得宝贵的冠军。 也许是因为这份无私的爱，足够戳心，或是因为真实的感动，更能共情。 《守味人3》经人民网发布，立即引发了公众的讨论狂潮 ， 更是以自然流量登上了视频热榜TOP3，最终 收获 两大热搜， 引发无数的网友在人民网微博留下了真情实感的评论，并且主动转发。 鸡汤的力量很强大，但真正使得它强大的永远是妈妈在背后付出的爱。 这份爱不会随时间而变淡，只会越来越强，不断传递。 来自真实的日常@郑思维---，郑思维赛前主动晒出滋补鸡汤 在一个快节奏的世界里，永远有一些人愿意慢慢来，慢慢熬一份鸡汤，慢慢地奉献自己，永远将你的梦想视作自己的梦想，用自己的努力去成就你的胜利，这个人就是父母，如同片尾所说： 默默陪你去赢的人，才是最爱你的人。 从第一季“妈妈”的红烧肉，满载深情厚意，到第二季的香菇炖鸡，传递温暖陪伴，历时五年，《守味人》系列也迎来了第三季，第三季更是首次将世界冠军的真实经历与《守味人》系列故事相融合，用一碗鸡汤，带出了世界冠军平常不平凡的成长历程。这不仅体现了“守味人”IP自带的创意生命力，也进一步印证了好的传播内容从来不缺市场和观众。 不一样的守味故事，一如既往地充当起家的味道与情感的纽带，带来同样的温情与感动，这正是《守味人》系列IP的魅力所在 ，背后也是温氏食品41年坚持信念的外在展现，41年，始终与消费者并肩同行，41年，用心守护从农场到餐桌的每一步。 温氏对品质好肉的坚持，支撑了妈妈做出有营养的鸡汤； 妈妈对爱心鸡汤的坚持，支撑了思维勇夺冠军的信心； 越来越多对食材和味道有所追求的消费者认可，又支撑起了温氏越做越好的决心。 默默付出、相互陪伴的“守味”的故事还在不断延续， 2024，我们羽你同行，一起去赢 。 点击回顾《守味人》第一季 点击回顾《守味人》第二季",
      "main_image": "https://oss.adquan.com/upload/20240220/1708415877876409.jpg",
      "images": [
        "https://file.adquan.com/uploads_img/17072079652zt9e.gif",
        "https://file.adquan.com/uploads_img/1707207965sypg4.gif",
        "https://file.adquan.com/uploads_img/1707208001zkia0.gif",
        "https://file.adquan.com/uploads_img/17072109169w5iq.gif",
        "https://file.adquan.com/uploads_img/17072155447ztc0.gif",
        "https://file.adquan.com/uploads_img/1707208060zuwv2.gif",
        "https://file.adquan.com/uploads_img/17072109805gcym.gif",
        "https://file.adquan.com/uploads_img/1707215449kenst.gif",
        "https://file.adquan.com/uploads_img/1707208138rphlk.gif",
        "https://file.adquan.com/uploads_img/1707208138vy1fm.gif",
        "https://file.adquan.com/uploads_img/1707217098rksu1.png",
        "https://file.adquan.com/uploads_img/170841417054g08.jpg",
        "https://file.adquan.com/uploads_img/17085742486ypix.jpg",
        "https://file.adquan.com/uploads_img/1707206509c8s6y.png",
        "https://file.adquan.com/uploads_img/17072215706vfre.jpg",
        "https://file.adquan.com/uploads_img/17072163178xlr3.jpg",
        "https://file.adquan.com/uploads_img/1708415346tmqdb.jpg",
        "https://file.adquan.com/uploads_img/1708415637hv6xe.jpg"
      ],
      "author": "无二Zero2Creative",
      "publish_time": "2024-02-22",
      "brand_industry": "快消品",
      "activity_type": "微电影",
      "location": "中国大陆",
      "tags": [
        "春节",
        "春节营销"
      ]
    },
    {
      "case_id": 43303,
      "score": 4,
      "score_decimal": "7.8",
      "favourite": 34,
      "company_name": "Anomaly 非常创意 上海",
      "company_logo": "https://oss.adquan.com/logos/1500098366937463.jpg",
      "thumb": "https://oss.adquan.com/upload/20180126/1516938846b68964daffcb2189.jpg",
      "source_url": "https://m.adquan.com/creative/detail/43303",
      "title": "百威这支新春大片戳中了多少人的心窝子？",
      "description": "你会设置朋友圈屏蔽父母吗？是爸妈真的不懂我们，还是我们根本没给机会？百威出了一支H5戳了很多人的心窝子。看了这支H5不禁反思了下自己。 2018百威新春大片《马拉松》 这支H5里的短片讲述了一个关于年轻人的故事，一个关于上一代人和下一代人的故事。腾讯新闻数据：超过50%年轻人曾在微信朋友圈屏蔽爸妈。看到这个数字的时候有什么感想？父母本来应该是我们最亲近的人，可是却成为了我们的“圈外人”。也许我们是烦于他们的唠叨，也许是怕他们担心。但是，可曾想过，他们努力的想要缩短与我们之间的距离，想要靠近我们，而我们却把他们推开。 百威的广告向来是以很燃的快速剪辑为主，这次反其道而行之走起了暖心路线。没有了熟悉的“百威，敬真我”却多了些动容。不过也有网友表示质疑：什么是孝，什么是不孝？朋友圈屏蔽就代表不孝吗？其实症结并不是在“是否屏蔽朋友圈”，而是“沟通”。 这支H5在最后的页面还有一个互动活动，给父母打一个电话，时间的长短可以领到不同金额的优惠券。旨在让大家与父母聊一聊，多沟通一下，靠近他们的主题和初衷。也可以通过活动带来一部分的客源，一举两得。 扫描二维码观看完整H5 其实在去年的时候百威也出过这样一支广告，它曾是国内社交媒体上观看次数最多、最具话题性的内容之一。讲述了女儿想要一场自己骑行的毕业旅行，为这不惜与父亲闹翻。而在她经历16天跨越1200公里之后，才发现，这一路，她一直都不是一个人。背景音乐一直是《爱的代价》，非常的贴合剧情。父亲那种深沉的爱也让人为之动容。 2017年百威新年广告 从剧情来看还是2017年的短片更胜一筹，情感更加细腻丰富，情节更跌宕起伏，更能触动人的内心。不过2017年的H5增加了与用户的互动，也是有自己的亮点。",
      "main_image": "https://oss.adquan.com/upload/20180126/1516938846b68964daffcb2189.jpg",
      "images": [
        "http://file.adquan.com/upload/20180126/1516938281181dc92ea5ed5f3c.jpg",
        "http://file.adquan.com/upload/20180126/151693829916731a61e54774e6.jpg",
        "http://file.adquan.com/upload/20180126/1516938345e7cdcf51313923d3.jpg",
        "http://file.adquan.com/upload/20180126/15169383619653e15d5f5ade0f.png"
      ],
      "video_url": "http://v.qq.com/iframe/player.html?vid=g05370q3d3m&tiny=0&auto=0",
      "author": "王威",
      "publish_time": "2018-01-26",
      "brand_industry": "快消品",
      "activity_type": "影视",
      "tags": [
        "百威"
      ]
    },
    {
      "case_id": 43505,
      "score": 4,
      "score_decimal": "8.4",
      "favourite": 28,
      "thumb": "https://oss.adquan.com/upload/20180211/1518317678982c7f42f5c67516.jpg",
      "source_url": "https://m.adquan.com/creative/detail/43505",
      "title": "百草味：你陪父母的样子，真假！",
      "description": "春节营销必不可少，百草味这支春节广告却怼了所有的年轻人。并没有一味的说教，这支欲抑先扬的广告却让很多年轻人无地自容，婉转客观的角度，更容易让人接受。 百草味《你陪父母的样子，真假！》 新春营销，多半以亲情、爱情、友情为中心，以回家、团圆为情节，以催泪、煽情为最终目的。百草味这支春节广告也不能免俗，但这支广告巧妙在并没有一味的煽情，狠命的戳人泪点。只是用一种独特的方式，以一个冷眼旁观的态度解释年轻人的状态。 你学会了赞美 你懂得了倾听 变得更加专注 知道了感恩 \"你长大了，你学会了赞美、倾听、更专注、知感恩，以及情感细腻...\"看似赞美，也确实没错，你学会了。但是，你学会的这些美好的品格，却没有传达给你最爱的人。我们可以对着朋友、同事甚至陌生人都可以轻易脱口而出的赞美、表达爱意，但是对父母呢？ 这支广告会让人非常不舒服。不舒服的来源是你根本不配得到这些夸奖，这些夸奖在现实的对比中化作了一根根利剑戳向你的心。让人自发的反思总比一味的说教更能让人接受。 在产品带入方面，百草味的坚果是推动情节发展的一个重要线索，也是串联整个短片的一个重要线索。与故事情节较高的契合度，既能引起观众的关注，也不会引起太大的反感，短片结束的时候也能给观众留下产品的印象。",
      "main_image": "https://oss.adquan.com/upload/20180211/1518317678982c7f42f5c67516.jpg",
      "images": [
        "http://file.adquan.com/upload/20180211/1518317285fc993accae6970c4.jpg",
        "http://file.adquan.com/upload/20180211/1518317315038f644d07502c8e.jpg",
        "http://file.adquan.com/upload/20180211/1518317330794a4c1aa88a34fb.jpg",
        "http://file.adquan.com/upload/20180211/151831733929d900c3c3c596d3.jpg",
        "http://file.adquan.com/upload/20180211/1518317479ea26ae2ade17444e.jpg",
        "http://file.adquan.com/upload/20180211/1518317492743f0bb66f8685b4.jpg"
      ],
      "video_url": "http://v.qq.com/iframe/player.html?vid=w0534huhrkp&tiny=0&auto=0",
      "author": "王威",
      "publish_time": "2018-02-11",
      "brand_industry": "快消品",
      "activity_type": "影视",
      "location": "中国大陆",
      "tags": [
        "百草味",
        "新春广告"
      ]
    },
    {
      "case_id": 44262,
      "score": 5,
      "score_decimal": "9.6",
      "favourite": 55,
      "thumb": "https://oss.adquan.com/upload/20180503/1525327094b55c8a9a40f8a89d.png",
      "source_url": "https://m.adquan.com/creative/detail/44262",
      "title": "鬼知道张子栋这些年都经历了什么！",
      "description": "我曾经的快乐源泉 —— 笑点担当张子栋出山了！这次，他扮演了一只上班狗。 张子栋的喜剧力无须多言，自带喜剧效果的他只要往那一杵，就自成笑点。而在小牛电动车的脑洞广告里，他还原了你我上班路上的真实写照，并用精湛演技告诉着我们：鬼都知道你们上班路上到底经历了什么！ 没在北京地铁上被挤掉过鞋的人，不足以谈早高峰。一直以来，我都觉得北京地铁有股神秘力量，它使你即使凭空站着，也不会因为惯性而跌倒，因为你身后的百来个兄弟姐妹就是你坚强的后盾，他们时刻簇拥着你，确保你即使不扶，也能屹立不倒。 夏天夏天悄悄来临，带来的不只有小秘密，还有一个移动的桑拿房。在高温的炙烤下，面对热气腾腾的邻座，我们往往只能在夹击中自求多福。 地铁的爆挤和公交的酷热还不足以刻画上班狗的艰辛，对于开车上班的人们来说，他们不仅要忍受堵车的煎熬，还要和四方车主斗智斗勇。前车上前一尺，却只让你一寸，好不容易你也要向前移动了，却又被其他车辆无情加塞，面对此景你束手无策，只能疯狂按喇叭，最后大家都在这条比登天还难的上班路上一点点地蠕动，期间遇上脾气不好的主儿，可能还得停车撕他一撕。 看到这里，不要以为打车上班就能幸免于难。上班时间的 rush hour 就连出租车也变得紧俏起来，每个赶时间的上班族都会在这一刻被激发潜能，为了抢车他们可以使出深藏已久的十八般武艺。 对于「上班困难综合症」，小牛电动车看得相当透彻，所以它以无厘头的表演形式演绎了我们上班路上可能遇到的所有问题，荒诞的创意配合张子栋那张生无可恋的脸，让我忍不住笑出一把辛酸泪。虽然在这支广告里，小牛电动车的产品没有露出，但它自有办法让自己把脸刷个够本。 一张图告诉你到底什么叫：张子栋往那一杵，就自带喜剧效果。 在这支广告里，张子栋是一名忠实的电动车拥有者，他热爱骑车的同时，又深受其困扰。 作为电动车车主，他首先需要面临的问题是 —— 防盗。这不，为了防盗，张子栋用大铁链把爱车和别人家的移动摊位绑在一起，结果城管一来，移动摊位就移动了，并且不剩下一个车轱辘。 电动车毕竟是敞篷车，难免遇到一些安全问题，尤其是当车主不遵守交通规则，无视红灯先行一步时，一旦遇上交通事故，就注定是个「我用生命赌明天，赔了一天又一天」的悲惨结局。 防盗、安全是小牛电动车主推的产品优势，所以在这支广告里，小牛电动车理性地剖析了电动车车主的使用心理。每个电动车车主似乎都有一个不翼而飞的电瓶以及一颗面对红灯蠢蠢欲动的侥幸之心，因此电动车的高风险和高被盗率是行人和车主讨厌电动车的客观原因，而从小牛电动车的广告表达来看，它的产品能够尽可能地规避这些问题。 不拼代言人也不尬销量，名声不大的小牛电动车就这样猝不及防地杀到了我们面前，而我也猝不及防地被它种草了一辆居然买得起的敞篷坐骑。",
      "main_image": "https://oss.adquan.com/upload/20180503/1525327094b55c8a9a40f8a89d.png",
      "images": [
        "http://file.adquan.com/upload/20180503/1525326851df7407696217c21b.png",
        "http://file.adquan.com/upload/20180503/152532686979427016b2f7504e.png",
        "http://file.adquan.com/upload/20180503/1525326882a56d82cfdc9d5832.png",
        "http://file.adquan.com/upload/20180503/1525326920a4d4118331216a8c.png",
        "http://file.adquan.com/upload/20180503/1525326934e4c17329c3e79281.png",
        "http://file.adquan.com/upload/20180503/1525326949175b0e6878b335c2.png",
        "http://file.adquan.com/upload/20180503/15253270282a49478b66c76d6c.png",
        "http://file.adquan.com/upload/20180503/1525327045c2912278009b1d05.png",
        "http://file.adquan.com/upload/20180503/1525327060a5dac631227bab8e.png",
        "http://file.adquan.com/upload/20180503/15253270836fa48e704e58db39.jpg"
      ],
      "video_url": "http://v.qq.com/iframe/player.html?vid=e0632qtwukn&tiny=0&auto=0",
      "author": "杜玥",
      "publish_time": "2018-05-03",
      "brand_industry": "数码、通讯",
      "activity_type": "影视",
      "location": "中国大陆",
      "tags": [
        "小牛电动车",
        "创意嘿店"
      ]
    },
    {
      "case_id": 344893,
      "score": 4,
      "score_decimal": "8.6",
      "favourite": 23,
      "company_name": "闲鱼等2家公司",
      "company_logo": "https://oss.adquan.com/logo/20171120164140_85333_320.png",
      "thumb": "https://oss.adquan.com/upload/20240704/1720096013798460.jpg",
      "source_url": "https://m.adquan.com/creative/detail/344893",
      "title": "别慌，面包会有的",
      "description": "七月，又迎来找工作的高峰期。 面包会有的 上闲鱼搞副业，还能多赚一笔 01 闲鱼跨界卖面包 创意灵感来自电影《列宁在1918》中的著名台词：“面包会有的，牛奶会有的，一切都会好起来的。” 02 地铁是打工人川流不息的地方，我们把杭州1号线也包装成了面包。 车厢里特地构思了两类文案，一类在地板上清楚地告诉大家，在闲鱼搞副业的有趣之处，帮助大家了解闲鱼副业。 我在闲鱼#兼职伴娘，拼命堵门，对抗整个伴郎团，走过红毯，护送婚戒，接到过手捧花，赚回今年出的份子钱。——上闲鱼#兼职伴娘，还能多赚一笔 是金子总会被看见，再小的技能也都能变现。 梦想和面包要两手抓，兴趣和专长也能赚钱花。 哪有一辈子的铁饭碗，不如给自己多找几个饭碗。 人生不是轨道，还有各种技能变现的门道。 收到面包后的海量返图~ 特别感谢中国广告青年创想计划，协助联系多所高校，让毕业的大学生在互动中感受到品牌的鼓励。 03 闲鱼简历是本次的重磅新品，我们直接将其作为视频和平面创意中的超级符号。当这块形似简历的巨大背景板出现时，你会发现自己身上，竟然还有那么多可以赚钱的隐藏技能！ 04 上百种副业等你开挂",
      "main_image": "https://oss.adquan.com/upload/20240704/1720096013798460.jpg",
      "images": [
        "https://file.adquan.com/pic/1720095031c8c39b611c588173.jpg",
        "https://file.adquan.com/pic/1720095031cc3948df3f8fca19.jpg",
        "https://file.adquan.com/pic/17200950311a36c5616e31d3f0.jpg",
        "https://file.adquan.com/pic/17200950325c4781014e9214b0.jpg",
        "https://file.adquan.com/pic/1720095033c5a1cdaa06ca4a87.jpg",
        "https://file.adquan.com/pic/17200950336b6d1a1104b72c60.jpg",
        "https://file.adquan.com/pic/1720095033a0f7b5fe7b0b5760.jpg",
        "https://file.adquan.com/pic/1720095034cef53113463123c9.jpg",
        "https://file.adquan.com/pic/1720095034acc57ceb9643903b.jpg",
        "https://file.adquan.com/pic/172009503489d74a3ada5d90e1.jpg",
        "https://file.adquan.com/pic/172009503566fb94868219ff26.jpg",
        "https://file.adquan.com/pic/17200950364c2082211a73627b.jpg",
        "https://file.adquan.com/pic/17200950377b3ce9dbad74c983.jpg",
        "https://file.adquan.com/pic/1720095037526876d705f90e9b.jpg",
        "https://file.adquan.com/pic/1720095037576dc5241f4a6a63.jpg",
        "https://file.adquan.com/pic/1720095038587094db8d84a707.jpg",
        "https://file.adquan.com/pic/172009503852d6b235e6a8c747.jpg",
        "https://file.adquan.com/pic/17200950392de2de48bd02d589.jpg",
        "https://file.adquan.com/pic/172009503943912cfbe1186a31.jpg",
        "https://file.adquan.com/pic/1720095040d7e4237cb455346e.jpg"
      ],
      "author": "天与空",
      "publish_time": "2024-07-05",
      "brand_industry": "互联网",
      "activity_type": "整合营销",
      "location": "中国大陆",
      "tags": [
        "闲鱼",
        "年轻人"
      ]
    },
    {
      "case_id": 317233,
      "score": 5,
      "score_decimal": "9.2",
      "favourite": 21,
      "thumb": "https://oss.adquan.com/upload/20220721/1658394818e8e91c3005c936b5.png",
      "source_url": "https://m.adquan.com/creative/detail/317233",
      "title": "Netflix洗脑音效，将故事氛围感拿捏到位！",
      "description": "对于影视爱好者来说，奈飞Netflix标志性的“Tudum”可谓是潜意识中最熟悉的声音，成为了生活的一部分。就像游戏爱好者对于“TiMi”的熟悉，只要听到它，“好戏”就要开场了。Netflix利用声音为创意点，发布了短片《The Sound of Stories》（故事之声），强化声音与故事的联系。 短片展现了不同的日常场景：一个电话在一个地铁站神秘地响起；一只狗在晚宴上送出了一份尴尬的礼物；两名步行者在雾蒙蒙的森林里迷路并失去了信号链接；餐厅服务员在结账单中夹入写有电话号码的餐巾纸；屋外电闪雷鸣突然停电...... 这些“不寻常”的事件配上网飞标志性的“Tudum”，犹如恐怖片中“不详”事件发生前的恐怖音效，预示着一个好故事即将开场。 Netflix以“洗脑”的音效为切入点，将日常场景与之关联。一方面提醒大众，以积极的心态面对生活，即使是日常场景也可以变成精彩的电视节目或电影的开始。另一方面，加强观众心中“Tudum”音效与好故事之间的联结。",
      "main_image": "https://oss.adquan.com/upload/20220721/1658394818e8e91c3005c936b5.png",
      "images": [],
      "author": "Emily",
      "publish_time": "2022-07-22",
      "brand_industry": "互联网",
      "activity_type": "影视",
      "location": "美国",
      "tags": [
        "奈飞",
        "Netflix"
      ]
    },
    {
      "case_id": 45023,
      "score": 5,
      "score_decimal": "9.2",
      "favourite": 26,
      "thumb": "https://oss.adquan.com/upload/20180626/1530009908cf38a9141061b9c0.jpg",
      "source_url": "https://m.adquan.com/creative/detail/45023",
      "title": "奥迪借势营销，庆祝沙特解除女性驾驶禁令",
      "description": "6月24日，零点钟声刚过，沙特阿拉伯的女司机就迫不及待的上路了，这是1990年之后沙特首次允许女性合法驾车上路，在解禁令颁布之前，沙特阿拉伯是世界上唯一一个要求车辆必须由男性成员驾驶的国家，为了这一天的到来， 多方 进行了长达30年的努力，为了庆祝来之不易的社会进步，奥迪发布了一支名为《Time to open new doors》的视频广告。 一位接受采访的沙特女司机说，开车上路“意味着我今天是个独立的人”，这并不是一句官方回答，在宗教礼法严苛的沙特，独立上路意味着对女性人格的逐步认可和尊重，广告片中，身着黑袍的女主角优雅自信，打开车门，示意男人坐在副驾驶位置的时候坚定骄傲，为那一刻，太多人等待了太久。 尽管沙特阿拉伯女性还有许多不得不遵守的在我们看来不合理的“法度”，尽管她们取得驾驶证比男性更难，但还是有许多人在努力，在为女性力量喝彩加油，奥迪这支没有一句台词的广告，以女主角一人的气度风华致敬女性，庆祝禁令解除，不仅打开沙特女性市场，而且有利于树立良好形象，提高品牌好感度。",
      "main_image": "https://oss.adquan.com/upload/20180626/1530009908cf38a9141061b9c0.jpg",
      "images": [
        "http://file.adquan.com/upload/20180626/15300092307f5d6f957fc03128.png",
        "http://file.adquan.com/upload/20180626/15300092548ff99884ad1ac269.png",
        "http://file.adquan.com/upload/20180626/153000908610eeca519bfec62c.png"
      ],
      "video_url": "http://v.qq.com/iframe/player.html?vid=a07029z0o7y&tiny=0&auto=0",
      "author": "Garbo",
      "publish_time": "2018-06-27",
      "brand_industry": "汽车",
      "activity_type": "影视",
      "location": "其他地区",
      "tags": [
        "沙特阿拉伯",
        "奥迪"
      ]
    },
    {
      "case_id": 324177,
      "score": 4,
      "score_decimal": "8.5",
      "favourite": 39,
      "company_name": "Tmall 天猫等2家公司",
      "company_logo": "https://oss.adquan.com/logo/20150813155452_18034_320.png",
      "thumb": "https://oss.adquan.com/upload/20230329/1680089119180141.jpg",
      "source_url": "https://m.adquan.com/creative/detail/324177",
      "title": "天猫《重启今日》：生活循环往复，却又时刻崭新",
      "description": "这是一部时间循环题材的影片。 主角叫李循环，这是他的故事，但也同样是你的故事。 《重启今日》主海报 回到故事的开始 剥开超现实题材的外壳，李循环则是无数当代人的缩影。 关于这个故事，还要从brief说起。今年3月，天猫打造「天猫上新月」，提出“生活不断上新”的核心主张，来面相用户进行「上新」的心智传递，也是一种积极生活观的输出。 但生活真的在不断「上新」吗？我们询问了很多身边的朋友，得到的答案很一致“并没有，感觉每天都过得一样”，我们陷入了难题。 在思考的过程里，我们听见了一首歌，陈绮贞《最初的起点》。其中有句歌词：“今天重复昨天，星期六有个约会，是我唯一能够期待的明天”，我们真实的生活似乎就是这样，一天天地重复，仿佛永远在同一天里生活，但也还是对生活有新的期待，哪怕只是因为一场约会，一束鲜花，甚至一张好吃的煎饼。 我们似乎有了点思路，在此也感谢陈绮贞老师隔空传递的灵感。 既然生活就是循环往复的，我们也希望把这个真实的洞察表达出来。关于新生活的大道理很多，但我们相信越真实的内容，越能打动人。 于是有了李循环的故事，一个代表着无数平凡人的循环故事。 关于新生活的道理，没那么深奥 在创作的过程中，关于跳出循环的转机是什么，我们也思考了很久。 我们希望这个转机能足够平实。因为新生活，并不是遥远的事物，也没那么深不可测。它其实就在我们的身边，在每一个日常里，等待着我们去发现。 最终，我们设定成了煎饼摊大爷的一番话。煎饼摊大爷就像你生活中那个最普通、最平凡、因为太常接触反而容易被忽视的人。也是最朴实的道理，让李循环对生活有了新的思考。 在剧情中，我们也将煎饼摊大爷设定成同样身陷循环的人，有着和主角一样的宿命，但他却依旧让每天煎饼车装扮的不同，每天煎饼口味的不同，用一点点的新变化，积极地对抗着循环的宿命。 而在影片结尾，李循环的生活真的有颠覆性的变化吗？并没有。他还是那个需要起床、上班、交房租的李循环。但和往常相似的一天，却有了许多新的东西。 新生活，其实就藏在循环往复的日常里。 它藏在一个拥抱里 藏在一个鱼缸里 藏在一个工位里 藏在一杯奶茶里 藏在一束鲜花里 藏在一张新口味的煎饼里 藏在无数看似平凡的事物里 我们也把想对你说的话，放在了影片的最后： 生活循环往复，却又时刻崭新 。 故事之外的故事 1. 在拍摄的过程当中，齐天佐导演对李循环扮演者何廖侣匀强调最多的话是“不要眨眼睛”。原因是愤怒的人是不眨眼的，正视生活的惨淡，才能成为打破循环的勇士。 2. 我们也曾犹豫，要不要在影片中植入产品，但客户和我们最终都希望，《重启今日》不仅是一条天猫的广告，也能成为繁复日常里，让人会心一笑，也能有所启示的故事。 3. 卖书的科学家，和摊煎饼的大爷，都为同一人扮演。有时创造问题和解决问题的人，可能是同一个人。 4. 本片致敬了经典电影《土拨鼠之日》，影片中随处可见土拨鼠的形象，去找找看有几个。 5. 此次项目最开始的故事脚本，其实和目前完全是不同的故事（至于是什么故事，来我们办公室，我讲给你听）。项目的中途想到了《重启今日》的故事，凭直觉和信念提报给了客户，也感谢天猫客户相信了这直觉，用对创意的热爱和保护，让这个故事得以诞生。 6. 为了吸引大家，我们在短片上线前“故弄玄虚”，上线了一套悬念海报，如果你刚好没看过，可以注意下每句小文案里埋下的梗。 新的开始 截止发文前，《重启今日》上线日全平台总曝光近10亿，总互动超60W，播放量破2700W，实现双微、B站多平台热度突破。 B站上线6小时即斩获全站热门榜单+首页热点推荐，截止目前视频播放量破70W+，网友围绕循环、宝藏片、生活的意义、上新月等丰富维度展开讨论。 从往年天猫把三八节作为3月主要沟通节点，到今年天猫把整个三月拉长成「天猫上新月」。这也像是天猫跳出循环，所做的一个全新的尝试，也是新的开始。也希望此次「天猫上新月」带给你的，不仅仅是新的商品，也能带给你全新的、积极的生活观。 生活循环往复，却又时刻崭新。我们的新生活，就在今天。 品牌方：天猫 创意代理商：赞意 导演：齐天佐 首席创意官：Soyar 创意总监：卢博 客户总监：Vidoula 创意组长：Sera 资深文案：Benny、鲸鱼 资深客户执行：Nicole 制片：熙瑶 特别鸣谢：TT 周天鸿、Yoni、小铭、Robin、菜丝、菲姐、小澜",
      "main_image": "https://oss.adquan.com/upload/20230329/1680089119180141.jpg",
      "images": [
        "https://file.adquan.com/uploads_img/1680086758igc9w.jpg",
        "https://file.adquan.com/uploads_img/16800940514iadj.png",
        "https://file.adquan.com/uploads_img/1680094161su5bh.png",
        "https://file.adquan.com/uploads_img/1680094250x51qr.png",
        "https://file.adquan.com/uploads_img/1680094317i3vh4.gif",
        "https://file.adquan.com/uploads_img/168009433571us8.gif",
        "https://file.adquan.com/uploads_img/1680094352ld4ob.gif",
        "https://file.adquan.com/uploads_img/1680094369u9c3j.gif",
        "https://file.adquan.com/uploads_img/168009438836mox.gif",
        "https://file.adquan.com/uploads_img/1680094401o69rw.gif",
        "https://file.adquan.com/uploads_img/1680094418tvosg.gif",
        "https://file.adquan.com/uploads_img/1680094449fa40k.png",
        "https://file.adquan.com/uploads_img/1680094516w2uy6.png",
        "https://file.adquan.com/uploads_img/1680094570uoftg.png",
        "https://file.adquan.com/uploads_img/1680094589rj9bx.png",
        "https://file.adquan.com/uploads_img/168009461304sp1.png",
        "https://file.adquan.com/uploads_img/1680094791ai1ew.png",
        "https://file.adquan.com/uploads_img/1680094811g2jtm.jpg",
        "https://file.adquan.com/uploads_img/16800948275krpt.png"
      ],
      "author": "赞意",
      "publish_time": "2023-03-29",
      "brand_industry": "互联网",
      "activity_type": "影视",
      "location": "中国大陆",
      "tags": [
        "品牌",
        "视频"
      ]
    },
    {
      "case_id": 285594,
      "score": 4,
      "score_decimal": "8.7",
      "favourite": 8,
      "thumb": "https://oss.adquan.com/upload/20190626/1561521191c212ac64ababd79a.jpg",
      "source_url": "https://m.adquan.com/creative/detail/285594",
      "title": "GUCCI最新手表广告大片，这个产品露出的姿势好评！",
      "description": "近日，GUCCI发布最新2019系列手表的广告大片。灵感来自于时装摄影师阿里·马尔科普洛斯(Ari Marcopoulos)捕捉到的一种代表包容性的温暖行为——握手。 摄影师阿里·马科波洛斯(Ari Marcopoulos)在一系列的见面和问候中，描绘了一位富有魅力和自信的领导人，在访问活动中与社会各界人士的不同会面场景，强调了个性的多样性。除了发布了平面大片，还在Instagram上发布了剧情短片： Grip系列推出了由Alessandro Michele设计的全新无性别区分款式，表盘无指针真空电镀表盘盒，复古与科技融合，搭配多种不同皮革或金属表带，简约与奢华的碰撞，非常吸睛！",
      "main_image": "https://oss.adquan.com/upload/20190626/1561521191c212ac64ababd79a.jpg",
      "images": [
        "https://file.adquan.com/uploads_img/pymrd1561518901.jpg",
        "https://file.adquan.com/uploads_img/0ciqt1561518900.jpg",
        "https://file.adquan.com/uploads_img/0lycn1561518903.jpg",
        "https://file.adquan.com/uploads_img/wd2lq1561518901.jpg",
        "https://file.adquan.com/uploads_img/2l0oe1561518901.jpg",
        "https://file.adquan.com/uploads_img/2kh1c1561518904.jpg",
        "https://file.adquan.com/uploads_img/1oi5m1561518903.jpg",
        "https://file.adquan.com/uploads_img/8otdy1561518902.jpg"
      ],
      "video_url": "https://player.youku.com/embed/XNDI0MjQwNDQ0OA==?spm=a2h3j.8428770.3416059.1",
      "author": "Kilek",
      "publish_time": "2019-06-26",
      "brand_industry": "时尚、美妆",
      "activity_type": "平面",
      "location": "欧洲",
      "tags": [
        "GUCCI",
        "手表"
      ]
    },
    {
      "case_id": 345196,
      "score": 4,
      "score_decimal": "8.1",
      "favourite": 7,
      "company_name": "Pocari Sweat 宝矿力水特",
      "company_logo": "https://oss.adquan.com/logo/20161117191346_10747_320.png",
      "thumb": "https://oss.adquan.com/upload/1721207548597eb7d3536898c9.jpg",
      "source_url": "https://m.adquan.com/creative/detail/345196",
      "title": "宝矿力水特：行动起来，汗水会让你充满力量",
      "description": "新电视广告“潜在能力は君の中”（潜力在你身上）夏季篇于7月12日在日本全国陆续播放。 大塚制药株式会社启用女演员椿（Tsubaki）和池端杏慈（Anji Ikehata）作为饮料“宝矿力水特”的品牌广告代言人。 （左：椿 ；右：池端杏慈） “宝矿力水特” 广告，一气呵成冲上120米楼梯 本次传播活动以“えるより先に動いてみよう。汗をかけば君の力は満ちてゆく。”（在思考之前先行动起来。汗水会让你充满力量。）为思想主题，以“游戏”为表现主题开展创作。 为了真实地捕捉生命力超越游戏世界的过程，工作团队使用智能手机拍摄了两位主角全力奔跑120米阶梯的场景。沿途出现的虚拟物体是基于扫描和数字化的拍摄技术，根据两人的动作进行展示。 此外，工作团队还开发了一个AR系统，能够根据全力奔跑的速度显示物体。角色和物体是由2000年代流行文化的代表性设计师田中秀幸和多位游戏设计师制作。 音乐由Tomggg和ena mori合作创作，他们在TikTok上深受年轻一代的喜爱。 （菲律宾和日本血统的创作型歌手ena mori） （音乐制作人Tomggg） 此外，“宝矿力水特”还在TikTok举办了广告活动（截至7月31日）“潜力在你身上，世界大赛。”用户只需拍摄上传TikTok，即可合成带有广告歌曲和品牌LOGO的视频。“宝矿力水特”会从TikTok上带有“#潜力在你身上”标签的视频中，抽选100名用户赠送田中秀幸设计的角色T恤。 日本2000年代前后的流行文化，在近几年成为“平成复古”和“Y2K”再次受到年轻人关注。 20多年前，街头潮流代表田中秀幸设计的时尚服装，在近几年被某位著名艺术家穿着后，迅速成为话题。他的设计也在现代年轻人中，重新成为最新潮流广受欢迎。因此，此次创作特别邀请田中秀幸进行角色设计。 故事和剧情 故事描述了椿和杏慈没赶上巴士后的情景。 没有过多思考，杏慈说：“我们从后面走！”然后冲向巷子深处。故事镜头转到椿追赶的视角，她们进入到一个游戏般的世界。 穿过树木形成的隧道，她们从正常的AR游戏世界，来到一个充满AR信息故障和混乱的隐藏世界。虽然她们困惑于这个混乱又奇妙的环境，但还是选择继续奔跑，直到AR混乱的信息追赶不上她们，出现了画面故障和加载标记。 在现实和想象交织的世界中，椿和杏慈穿越混乱区域，一路奔跑到山顶。她们额头上挂着真正的汗水，充满生命力，同时也意识到自己内在的力量，喝下宝矿力水特，感受着行动过后内心获得的自信和喜悦。最后，她们选择再次出发。 关于 导演柳沢翔 此次广告的亮点和特别注重的地方是哪些？ 我参与开发并拍摄了屋外AR系统，我认为我们成功地体现了“游戏”这一主题，同时也表现了宝矿力水特广告的象征——“真正的汗水”。开发和拍摄过程都非常有趣，让我很享受。 撮影过程中遇到的挑战是什么呢？ 主要的拍摄地点是一段120米长的楼梯，演员和工作人员都必须在一个镜头内跑完，这非常辛苦。演员们为了拍摄，完成了教练设计的为期两个月的训练计划。 关于广告制作的团队结构？ 最重要的是田中秀幸先生的参与。2000年代我还是青少年的时候，他的作品给我一种既触手可及又永远无法真正触及的感觉，这种微妙的平衡感非常酷。 他的作品对90年代的氛围也充满了讽刺意味。所以，当我听说“宝矿力水特”要用Y2K主题制作广告时，我决定在视频制作方面请田中先生这位2000年代的代表人物来参与。 关于设计师 田中秀幸 接受角色设计委托时的感想？ 这次的项目主要面向现在的年轻人，并将Y2K主题形象融入宣传活动，起初我在想是否适合由我来完成。因为过去我更多是以导演、总监的身份参与广告创作，所以这次能以一种新鲜的心情投入到这个角色设计的工作中，我感觉非常有趣和愉快。 对角色制作的概念？ 关于角色制作的概念很明确，客户寻求的是我从2000年代初期开始就一直绘制的风格。最初只是依靠广告中角色的设定随意画了一些草图，意外地受到了大家的喜爱。角色头顶的瓶盖设计是根据广告内容的草稿直接采纳的。这个设计已经成为本次项目中一个很受欢迎的元素。 在制作过程中特别重视的地方和遇到的困难点？ 尽量减少使用的颜色数量，以及在少数的色彩中也能表现出角色可爱的效果。 导演柳沢翔那些一镜到底的广告和个人故事（点击链接查看） *文章图片来自大塚制药 如有侵权请联系 我们删除",
      "main_image": "https://oss.adquan.com/upload/1721207548597eb7d3536898c9.jpg",
      "images": [
        "https://file.adquan.com/uploads_img/lwdsa1721206036.png",
        "https://file.adquan.com/uploads_img/4dctj1721206144.jpg",
        "https://file.adquan.com/uploads_img/byc2m1721206292.jpg",
        "https://file.adquan.com/uploads_img/i0vlx1721206388.jpg",
        "https://file.adquan.com/uploads_img/1ecln1721206661.jpg",
        "https://file.adquan.com/uploads_img/m380d1721206767.png",
        "https://file.adquan.com/uploads_img/e7gt91721206784.jpg"
      ],
      "author": "广告门 Jimmie",
      "publish_time": "2024-07-17",
      "brand_industry": "快消品",
      "activity_type": "影视",
      "location": "日本",
      "tags": [
        "宝矿力水特",
        "柳沢翔"
      ]
    },
    {
      "case_id": 317947,
      "score": 4,
      "score_decimal": "8.7",
      "favourite": 27,
      "thumb": "https://oss.adquan.com/upload/20220815/1660531023d82ea3e9343f5e88.png",
      "source_url": "https://m.adquan.com/creative/detail/317947",
      "title": "将沙雕广告融进DNA里的品牌 , 大概只有它了",
      "description": "还有多少人记得Old Spice？",
      "main_image": "https://oss.adquan.com/upload/20220815/1660531023d82ea3e9343f5e88.png",
      "images": [
        "https://file.adquan.com/pic/166053042554ab9a92c87ca6d8.jpg",
        "https://file.adquan.com/pic/1660530425ec2803ddecb9301e.jpg"
      ],
      "author": "River",
      "publish_time": "2022-08-15",
      "brand_industry": "快消品",
      "activity_type": "影视",
      "location": "美国",
      "tags": [
        "Old Spice",
        "沙雕广告"
      ]
    },
    {
      "case_id": 44551,
      "score": 3,
      "score_decimal": "6.1",
      "favourite": 12,
      "thumb": "https://oss.adquan.com/upload/20180529/152757965180fda9caef8dedcb.jpg",
      "source_url": "https://m.adquan.com/creative/detail/44551",
      "title": "衣二三的潮，关年龄什么事？",
      "description": "在脸上开始有皱纹之后，慢慢懂得了秦始皇晚年不惜耗费举国之力，也要找到长生之法的心情。被时间催着走，是一件太可怕的事情，尤其心中还有如此想得而不可得的东西。所以在没被叫“老阿姨”之前，趁早体验未知才是正经事儿。 可在这支广告片里，逝去青春的阿姨只能对镜神伤了，直到一个神秘包裹的出现，然后好像获得通关秘籍一般，之前老态龙钟的那个人荡然无存，神采奕奕走出房间的小姐姐一下子年轻了二十岁。 接着，潮范儿十足的阿姨更是通过一个swag手势变身嘻哈少女。魔法故事之后，甜蜜的爱情故事随之上演。夜游美术馆，在酒吧飙歌炫舞，凌晨压马路......故事到这里让人不禁担心，过了12点的灰姑娘会不得不离开王子吗？ 然而万万没想到，这个魔法进行到最后，两个人一起变成了小孩子......以年轻人的恋爱为主线，跨越老阿姨，嘻哈少女，儿童三个年龄层次，体现品牌的消费者定位已不仅局限于职业女性。 在衣二三“谁说我是老阿姨”的营销战略中，除了这支线上视频，品牌还在上海组织了“广场舞101”的线下活动，不仅借势综艺《创造101》，还向A班发起call out。阔腿破洞裤，18最in印花裙，潮流鸭舌帽，时尚的广场舞势力让人不得不低头。",
      "main_image": "https://oss.adquan.com/upload/20180529/152757965180fda9caef8dedcb.jpg",
      "images": [
        "https://wx1.sinaimg.cn/mw690/0066u6Mkly1frrz5rds9ij30rs15o133.jpg",
        "https://wx4.sinaimg.cn/mw690/0066u6Mkly1frrz5mnf2aj315o0rsthf.jpg",
        "https://wx2.sinaimg.cn/mw690/0066u6Mkly1frrz5mwtagj315o0rstju.jpg",
        "http://file.adquan.com/upload/20180529/15275777538bd1bfbad5dc3258.png",
        "http://file.adquan.com/upload/20180529/1527577691c89c101060039c3a.png",
        "http://file.adquan.com/upload/20180529/1527577801e49c5335f16b3376.png",
        "http://file.adquan.com/upload/20180529/1527578504705a2c1ef6af4d5b.jpg"
      ],
      "video_url": "http://v.qq.com/iframe/player.html?vid=u0668jr4o0t&tiny=0&auto=0",
      "author": "Garbo",
      "publish_time": "2018-05-29",
      "brand_industry": "电商、零售",
      "activity_type": "影视",
      "location": "中国大陆",
      "tags": [
        "衣二三"
      ]
    }
  ]
}