{
  "batch_num": 56,
  "batch_size": 10,
  "created_at": "2026-01-18T23:38:58.201685",
  "cases": [
    {
      "case_id": 347216,
      "score": 4,
      "score_decimal": "8.3",
      "favourite": 1,
      "thumb": "https://oss.adquan.com/upload/17294961053b669219eefc8b10.jpg",
      "source_url": "https://m.adquan.com/creative/detail/347216",
      "title": "特朗普惊现麦当劳",
      "description": "近日，有媒体称美国前总统唐纳德·特朗普周日访问宾夕法尼亚州的一家麦当劳门店。 该消息在社媒上火速传播。 特朗普此次造访麦当劳是他在 11 月总统大选前的竞选活动的一部分。而选择在麦当劳工作则是因为他对竞争对手副总统卡马拉·哈里斯曾在此前的演讲中提到的“中产阶级背景”和在麦当劳工作过的说法提出了质疑。 特朗普挖苦民主党候选人说：“看看这里的顾客。他们很高兴，因为他们有希望。他们需要希望。我现在比哈里斯还多工作了 15 分钟。” 特朗普和哈里斯都在宾夕法尼亚州频繁举行集会和竞选活动，该州是即将到来的选举的关键州。两位候选人还在其他关键州进行竞选，以在选举前获得支持。 为了证明该活动并非AI合成，还有人放出了相关视频：",
      "main_image": "https://oss.adquan.com/upload/17294961053b669219eefc8b10.jpg",
      "images": [
        "https://file.adquan.com/uploads_img/uj0bk1729495796.jpg"
      ],
      "author": "源泉",
      "publish_time": "2024-10-21",
      "brand_industry": "政府、非盈利机构",
      "activity_type": "影视",
      "location": "中国大陆",
      "tags": [
        "特朗普",
        "美国大选"
      ]
    },
    {
      "case_id": 318334,
      "score": 4,
      "score_decimal": "7.8",
      "favourite": 17,
      "company_name": "Tmall 天猫",
      "company_logo": "https://oss.adquan.com/logo/20150813155452_18034_320.png",
      "thumb": "https://oss.adquan.com/upload/20220829/16617598608d099fb3451fe8e1.png",
      "source_url": "https://m.adquan.com/creative/detail/318334",
      "title": "天猫中秋童趣短片，原来月饼也要讲“哲学”！",
      "description": "没想到，月饼有一天也能打“健康”的卖点。 临近中秋，天猫发布了一支充满童趣与可爱的小短片。在月饼们关于“轻哲学”的对话中，发现轻月饼原来与健康息息相关。 “我们为什么不能吃点甜的呀”“开始为对方的健康着想，就已经够甜了啊”……中秋吃月饼是一个约定俗成的习俗，很少有人在吃的时候，想到“健康”。而随着健康习惯的养成，越来越多的年轻人倾向于选择低糖、低脂与低卡的消费品。在这种趋势下，天猫推出“轻月饼”的概念，不仅顺其自然，而且也能与大多数竞品进行区分。 你觉得这支短片怎么样？",
      "main_image": "https://oss.adquan.com/upload/20220829/16617598608d099fb3451fe8e1.png",
      "images": [
        "https://file.adquan.com/uploads_img/5obm61661759389.jpg"
      ],
      "author": "River",
      "publish_time": "2022-08-29",
      "brand_industry": "电商、零售",
      "activity_type": "影视",
      "location": "中国大陆",
      "tags": [
        "天猫",
        "中秋"
      ]
    },
    {
      "case_id": 355706,
      "score": 4,
      "score_decimal": "7.3",
      "favourite": 2,
      "company_name": "Huawei 华为",
      "company_logo": "https://oss.adquan.com/logos/1545130649958288.jpg",
      "thumb": "https://oss.adquan.com/upload/17586002172f91501f1293067f.jpg",
      "source_url": "https://m.adquan.com/creative/detail/355706",
      "title": "华为：将人生的方向盘握在自己手中",
      "description": "2025年，1222万毕业生竞争有限的工作岗位，就业率仅为55%。 华为nova14想要将共同的挑战转化为真正的联系和更深层次的信任。因此，当其他品牌专注于校园怀旧时，华为选择围绕毕业季面临的迷茫、焦虑和挣扎来与 Z 世代对话。 为了捕捉毕业生的集体不确定性，影片创造了失控的毕业巴士象征那些“失控的日子”。一名毕业生离开校园，登上公共汽车，穿过被拒绝工作、残酷的研究生考试以及探索多样化的职业和生活方式的场景。在告别、想象的未来、闪回和赋权的时间线中，主角抓住方向盘，驶向自己的道路。",
      "main_image": "https://oss.adquan.com/upload/17586002172f91501f1293067f.jpg",
      "images": [],
      "author": "23",
      "publish_time": "2025-09-23",
      "brand_industry": "数码、通讯",
      "activity_type": "影视",
      "location": "中国大陆",
      "tags": [
        "华为",
        "毕业季"
      ]
    },
    {
      "case_id": 315405,
      "score": 4,
      "score_decimal": "8.1",
      "favourite": 3,
      "thumb": "https://oss.adquan.com/upload/20220516/1652693760d617864774cdceed.png",
      "source_url": "https://m.adquan.com/creative/detail/315405",
      "title": "30部上海电影混剪，将百年上海影史浓缩为抗疫短片",
      "description": "上海电影集团发布由30部上海电影连缀剪辑而成的抗疫短片。30部影片剪辑把近百年的上海电影史囊括，通过演绎上海都市百态的前世今生，鼓舞人民坚持抗疫，在最后的攻坚时刻，以饱满的精神迎接上海的回归。 《马路天使》《春满人间》《护士日记》《万紫千红总是春》《大李老李和小李》《女篮五号》《1921》《攀登者》《爱情神话》《大城大楼》...... 30部影片记录了上海各个历史时期的生活片段，剪辑而成上海人抗疫的心路历程。最初封闭居家，无奈、沮丧、崩溃，各种负面情绪上涌。生活还要继续，洗衣、做饭、健身、护肤，互相安慰、相互勉励。各地物资援助，慢慢走出恐慌和困境，“我们共同期待，上海如常归来” 抗疫胜利。 短片导演程亮表示：“百年上海，砥砺前行。新一辈上影人把这些片段精心挑选出来，结合新媒体视频的传播形式加以剪辑连缀，希望这些光辉的银幕瞬间能鼓舞到更多上海市民和热爱电影的观众。希望这条短片在抗疫进入最后攻坚的时刻给大家打气，一起以更饱满的精神和意志去迎接这个美丽城市如常回归。”",
      "main_image": "https://oss.adquan.com/upload/20220516/1652693760d617864774cdceed.png",
      "images": [],
      "author": "Emily",
      "publish_time": "2022-05-16",
      "brand_industry": "政府、非盈利机构",
      "activity_type": "影视",
      "location": "中国大陆",
      "tags": [
        "疫情",
        "上海"
      ]
    },
    {
      "case_id": 350066,
      "score": 4,
      "score_decimal": "8.0",
      "favourite": 1,
      "company_name": "多邻国Duolingo",
      "company_logo": "https://oss.adquan.com/ccma_image/20250316/1742129857381700.png",
      "thumb": "https://oss.adquan.com/upload/173995379121c60d2f87c8f610.jpg",
      "source_url": "https://m.adquan.com/creative/detail/350066",
      "title": "多邻国死因终于公布了",
      "description": "2月19日，多邻国之父Luis von发布视频，公开了多邻国吉祥物多儿的死因：一场源于互联网那个大卡车的不幸车祸。 与此同时，多邻国还发起了复活挑战，只要用户学习就可以获得经验，累计获得500亿经验之后，多儿将重新复活。",
      "main_image": "https://oss.adquan.com/upload/173995379121c60d2f87c8f610.jpg",
      "images": [
        "https://file.adquan.com/uploads_img/mpydw1739953766.png",
        "https://file.adquan.com/uploads_img/7q0tz1739953766.png"
      ],
      "author": "源泉",
      "publish_time": "2025-02-19",
      "brand_industry": "教育",
      "activity_type": "影视",
      "location": "美国",
      "tags": [
        "多邻国"
      ]
    },
    {
      "case_id": 348868,
      "score": 4,
      "score_decimal": "8.4",
      "favourite": 1,
      "company_name": "RIO锐澳鸡尾酒等2家公司",
      "company_logo": "https://oss.adquan.com/logo/1560837659931016.jpg",
      "thumb": "https://oss.adquan.com/upload/202412253f9c3502bd9858e7.jpg",
      "source_url": "https://m.adquan.com/creative/detail/348868",
      "title": "RIO这波迷之魔改，主打一个“猜不透”！！",
      "description": "脆皮公主咬下巫婆的苹果，竟然... 巧克力厂长研发出神秘新配方，结果... 巫婆转行做起了咖啡师，谁知... Hold on！ 怎么RIO微醺上演的冬日童话故事和咱听过的不一样！ 速戳视频，坠入奇幻的微醺世界！ 现在，让我们把时间线拨回到起点—— 这个岁末 RIO微醺联手Tims天好咖啡 推出 冬季限定 「苹果白巧拿铁」 风味 当三个都能担任C位的口味 首次组团出道 如何让消费者产生认知并拉满好奇 成为了壹捌零集团上海办公室的 头 等 大 事 苹果×白巧×拿 铁 ~ 一种魔改的滋味，还怪好喝的 ~ 在喝了大概10086瓶RIO微醺后 壹捌零上海的小伙伴们 眯着眼红着脸陷入沉思…… 这味道，该怎么去形容你，最贴切？ 不是小清新的花香果香 一口入喉，酸甜 苹果 味首当其冲 香浓 白巧 滋味就迫不及待紧随其后 一抹苦醇的 拿铁 尾调惊鸿一现—— 丰富的滋味层次给味蕾一波又一波高潮 不是苹果汁不是白巧不是拿铁 却又是苹果汁又是白巧又是拿铁…… = 等等 = 这种说不清好喝在哪里的混合滋味 不正是一种超级魔改的抽象味道吗！ 苹果公主×巧克力厂长×咖啡师 ~ 一部魔改过的童话，怪好看的~ 魔改滋味，自然要用魔性方式去演绎 此次，我们重金（bushi）请来三位 最能代表三种滋味的角色—— 来一场童话界里的世纪大魔改 无需理解成本 消费者自己就能代入联想！ 苹果代言人——命运和苹果难舍难分的公主 白巧代言人——吃巧克力长大的厂长 拿铁代言人——每个早C都必见的咖啡师 加戏小彩蛋——视频上线之前还特别释出 一张“RIOFILM“出品的预热海报 嗯，既然要drama那就贯彻到底咯 ~一部魔改过的线下互动，怪好玩的~ 圣诞前夕，空气里满满都是奇幻氛围 而在12月21-24这几天 每个在上海BFC外滩金融中心city walk的人 都会遇见一处更奇幻的童话小屋—— RIO微醺 × Tims 好看更好拍的微醺奇幻小屋 满满都是三种口味的卡通元素 作为品牌双方合作的线下快闪店 这间“小屋”也是本次传播中的重要一环 要通过有互动感的玩法夯实新品认知 更要让用户自发传播分享反哺线上热度 我们决定将魔改进行到底—— 「真人版拉霸机」横空出世！ 按下NPC面前的苹果start键 公主、巧克力厂长和咖啡师 就会奉上一段E人快乐舞 并从面前三个“口味”道具中随机拿出一个 如果拿出一样的，挑战成功，周边送上！ 有一说一 现场火爆氛围真心一扫上海冬日的严寒 新奇简单的互动形式娱乐性拉满 线下排起了长队 线上也炸翻了讨论热度！ “苹”实力“白拿”圣诞好礼 谁会不心甘情愿当一波自来水！ 奇幻，不只是一种滋味 魔改，也不只是一个玩法 它是我们在2024的岁末从现实世界里的片刻抽离 欢迎沉浸在RIO微醺苹果白巧拿铁风味的奇幻世界里 Let’s 继续微醺！",
      "main_image": "https://oss.adquan.com/upload/202412253f9c3502bd9858e7.jpg",
      "images": [
        "https://file.adquan.com/upload/wx/202412251c6e8057bc3f0781.jpg",
        "https://file.adquan.com/uploads_img/1735113004z2794.gif",
        "https://file.adquan.com/uploads_img/1735113025gf3v6.gif",
        "https://file.adquan.com/upload/wx/202412253680de3c0afdb28e.jpg",
        "https://file.adquan.com/upload/wx/2024122504c798884852207d.jpg",
        "https://file.adquan.com/upload/wx/202412258fd2a5d6761579ce.jpg",
        "https://file.adquan.com/upload/wx/20241225ed2efd2b122e47f5.jpg",
        "https://file.adquan.com/uploads_img/17351136895i31d.png",
        "https://file.adquan.com/upload/wx/20241225815bf0ceb8aab552.jpg",
        "https://file.adquan.com/upload/wx/20241225de9e5bbbf0652cb8.jpg",
        "https://file.adquan.com/uploads_img/1735113415iut0z.gif",
        "https://file.adquan.com/uploads_img/1735113453poub3.gif",
        "https://file.adquan.com/uploads_img/17351134689c2gq.gif",
        "https://file.adquan.com/upload/wx/20241225c5b67c363f0112f6.jpg",
        "https://file.adquan.com/upload/wx/20241225a23d6368215a72c9.jpg",
        "https://file.adquan.com/upload/wx/20241225f47c5938dcb59d51.jpg"
      ],
      "author": "壹捌零创意集团",
      "publish_time": "2024-12-25",
      "brand_industry": "互联网",
      "activity_type": "影视",
      "location": "中国大陆",
      "tags": [
        "圣诞",
        "RIO微醺"
      ]
    },
    {
      "case_id": 347643,
      "score": 4,
      "score_decimal": "8.0",
      "favourite": 4,
      "thumb": "https://oss.adquan.com/upload/1730792322b91299ca9845fba9.jpg",
      "source_url": "https://m.adquan.com/creative/detail/347643",
      "title": "史无前例的美国总统竞选宣传片",
      "description": "全世界都在关注的美国大选正在如火如荼地举办中，哈里斯的这条大选宣传视频也火了。这条视频 可以说是史无前例的美国总统大选宣传片——一个母权社会的宣传片。 哈里斯的妈妈是印度移民，19岁来到美国。后来成为乳腺癌研究专家，哈里斯7岁时，母父离婚，大部分时间，是母亲养大两个女儿。怪不得她虽然长期在男权重灾区的司法系统和政界工作，身上仍洋溢着罕见的放松和自在，充满幽默感，这是母权家庭的后代才有的健康内核。 这个视频以哈里斯母亲的故事开启叙事，以母女传承作为铺垫，描述母亲的伟大，展开到女性治国带来和谐社会的美好愿景。音乐、节奏和叙事，都深情、庄严又亲和，这其实就是母权社会的宣传。 这个宣传片里面的母亲，不是那种含辛茹苦、面目模糊、自我燃烧的妻母，而是不受男性压迫的、男权历史之前的人类漫长母权历史上，母亲真正的样子：健壮、坚强、自主、机警、坚韧、强大、智慧、珍惜生命，保护孩子，并教会孩子们保护她人。 “当你成为母亲，你的某些部分豁然开朗，你意识到，在你离开此世很久之后，这些孩子也会是你留给这个世界的遗赠。",
      "main_image": "https://oss.adquan.com/upload/1730792322b91299ca9845fba9.jpg",
      "images": [],
      "author": "源泉",
      "publish_time": "2024-11-05",
      "brand_industry": "政府、非盈利机构",
      "activity_type": "影视",
      "location": "美国",
      "tags": [
        "美国大选",
        "哈里斯"
      ]
    },
    {
      "case_id": 349766,
      "score": 3,
      "score_decimal": "5.0",
      "favourite": 4,
      "company_name": "Mountain Dew 激浪",
      "company_logo": "https://oss.adquan.com/logos/1526545157408732.jpg",
      "thumb": "https://oss.adquan.com/upload/17389833246b7c98ee68db3c03.jpg",
      "source_url": "https://m.adquan.com/creative/detail/349766",
      "title": "激浪超级碗广告，创飞观众",
      "description": "如果超级碗广告要评选一个最奇葩奖项，那么今年的激浪广告毫无疑问会夺得冠军。 这条由格莱美奖得主、著名艺术家席尔 (Seal) 所拍摄的激浪(Mountain Dew)的最新超级碗宣传广告很明显引起了轩然大波。 新广告的名字很贴切也很搞笑，叫做“酸橙之吻”（出自席尔的热门歌曲“玫瑰之吻”），并且连续第二年围绕该品牌备受欢迎的 Baja Blast 口味展开。 该广告由广告公司Goodby Silverstein & Partners策划，并由奥斯卡获奖导演 Taika Waititi 通过制作公司 Hungry Man 执导。 它以 Mountain Dew 的Baja Blast为中心，庆祝超级碗的文化影响。 此次活动还邀请了流行歌星Becky G和该品牌古怪的吉祥物Mountain Dude共同出演。 最搞笑的是席尔，他以一只真正的海豹的形象出现，搞笑演绎了他最著名的歌曲之一“玫瑰之吻”。 他在一份声明中谈到了该广告背后的创作过程：“我很高兴能想出新歌词，并且很高兴与他们的团队合作，以如此有趣和出乎意料的方式将这个活动变为现实。”",
      "main_image": "https://oss.adquan.com/upload/17389833246b7c98ee68db3c03.jpg",
      "images": [],
      "author": "源泉",
      "publish_time": "2025-02-08",
      "brand_industry": "快消品",
      "activity_type": "影视",
      "location": "美国",
      "tags": [
        "激浪",
        "超级碗"
      ]
    },
    {
      "case_id": 40307,
      "score": 4,
      "score_decimal": "7.1",
      "favourite": 3,
      "company_name": "FOX Networks Group",
      "company_logo": "https://oss.adquan.com/logos/1525767943677818.jpg",
      "thumb": "https://oss.adquan.com/upload/20170310/1489125805915122.jpg",
      "source_url": "https://m.adquan.com/creative/detail/40307",
      "title": "厌倦了剩女？SK-II和国家地理合作拍起了纪录片",
      "description": "文/House 2月28日，SK-II官方YouTube频道中出现了四支纪录短片。 这是SK-II与国家地理共同合作的《Face the Wild，Face the Camera》。其中出镜的4位嘉宾分别为日本演员有村架纯，时尚偶像Chiara Ferragni，韩国演员&拳击手李诗英以及中国演员倪妮。 以往在聚光灯下美艳动人的几位明星将被送往世界上气候环境最为极端的地方进行SK-II护肤精华的终极测试。在这里，她们不仅要面对恶劣环境的刁难，还要应对镜头的严苛考验。 Chiara Ferragni，SK-II来自意大利米兰，时尚博主。这一次她远征安萨-波瑞哥沙漠，而这里是美国西部最干旱的地区之一。 日本女演员、SK-II品牌形象大使有村架纯徒步进入位于日本冲绳的丛林，体会炙热稠密的热带雨林酷暑与紫外线的强照射。 韩国女演员&拳击手李诗英此次去到位于印尼的Ijen火山，同时这里也是世界上最危险的地方之一。在这里她所面对的是富硫的空气与灰尘。 而中国演员、SK-II品牌形象大使倪妮 所要迎接的则是中国北方的寒冷山区。在这里有干燥的寒风，并且要抵抗极低的温度，防止冻伤。 在脱水、干热、冰冻、干燥、昏眩的气候考验与人体极限挑战下，四位明星能否完成挑战？这样以纪录片的手法为SK-II产品进行宣传既能激发受众好奇，又运用出镜人IP影响力保障了campaign关注度，而形式上的突破也是用（十）心（分）至（心）极（机）了。截止目前，四支预告片在SK-II官方YouTube频道的累计浏览量已超过20万。",
      "main_image": "https://oss.adquan.com/upload/20170310/1489125805915122.jpg",
      "images": [],
      "video_url": "http://v.qq.com/iframe/player.html?vid=t0382oqi42y&tiny=0&auto=0",
      "author": "house",
      "publish_time": "2017-03-10",
      "brand_industry": "时尚、美妆",
      "activity_type": "影视",
      "tags": [
        "国家地理"
      ]
    },
    {
      "case_id": 349030,
      "score": 4,
      "score_decimal": "7.9",
      "favourite": 5,
      "company_name": "Chivas 芝华士等2家公司",
      "company_logo": "https://oss.adquan.com/logo/20140102221216_25376_320.png",
      "thumb": "https://oss.adquan.com/upload/202501026c0f028108d0359a.jpg",
      "source_url": "https://m.adquan.com/creative/detail/349030",
      "title": "芝华士 x 陈小春 ｜ 这一次，江湖再见",
      "description": "不知道从何时起， “ 下次 ”“ 下次 ”“ 再下次 ” 成了我们这个时代的口头禅，曾经潇洒写出的“江湖再见”，少有再见。但见个面，真的这么难吗？或许，每个人都有无数个理由不见。但兄弟间，不该留遗憾。 江湖再见，说好再见，就一定要再次相见 FRED & FARID 上海 为 CHIVAS 打造以“江湖再见”为传播主题的年度campaign，并在2024年12月，感动上线。在当下，洋酒传播相对缺少与中年男人情感产生链接的实际感。想要唤醒中产男性对于黄金时代的独特情怀与回忆，我们找到了一个重要元素——兄弟。 “ 一支穿云箭，千军万马来相见 ” 说见就见，是独属于兄弟间的默契，也是独存于男人间的时代回忆。基于此，我们在提案阶段，便推荐与具有绝对“江湖大哥气质”的演员陈小春进行合作，结合“属于兄弟的歌”—— 《友情岁月》 作为主要传播元素，提出 “ 江湖再见 —— 说好再见，就一定要再相见 ” 的传播主题。并以兄弟重聚的真实故事为底，用极具真实感、生活感的记录方式，打造了一支属于男人们的“年度怀旧MV”——《友情岁月2025》。 整个项目，前期由小春哥发起“与陈小春合唱友情岁月”，引起社交平台的强烈关注。再通过来自不同行业的抖音KOL诠释“不同重聚时刻”，唤起中年男性的情感共鸣，达到万人合唱《友情岁月》，实现全平台互动的新突破。 最终，这支满载兄弟情谊的《友情岁月2025》，在年末压轴上线，将重聚情绪推向高潮。 契合芝华士绿茶“江湖再见”的主题，我们还将《友情岁月》副歌歌词部分进行相应改编，既保留原曲的深情厚谊，又融入了品牌元素，以更好地传达“江湖再见”的意境。 话过再见 我们还要再见 打个电话约好想见就见 不相信无人呢 饮芝华士绿茶 在约定里碰杯 为再见面碰杯 本次战役由 FRED & FARID 上海 全程主导，我们希望通过 “ 江湖再见 ” ，鼓励大家 “ 说好再见，就一定要再相见 ” 。相信让那些“相忘于江湖”的兄弟情谊，也将因芝华士+绿茶的出现而相聚。现在，带上这瓶芝华士。用经典口味致敬一起走过的情谊，为再见面干杯。",
      "main_image": "https://oss.adquan.com/upload/202501026c0f028108d0359a.jpg",
      "images": [
        "https://file.adquan.com/uploads_img/173580817820yix.jpg",
        "https://file.adquan.com/uploads_img/1735808347o42tz.png",
        "https://file.adquan.com/uploads_img/1735809080xmp4k.jpg",
        "https://file.adquan.com/uploads_img/1735809211ityqc.png"
      ],
      "author": "FF佛海佛瑞",
      "publish_time": "2025-01-03",
      "brand_industry": "快消品",
      "activity_type": "整合营销",
      "location": "中国大陆",
      "tags": [
        "芝华士"
      ]
    }
  ]
}