{
  "batch_num": 6,
  "batch_size": 10,
  "created_at": "2026-01-18T22:58:54.132381",
  "cases": [
    {
      "case_id": 340276,
      "score": 4,
      "score_decimal": "8.2",
      "favourite": 18,
      "company_name": "快克药业等2家公司",
      "company_logo": "https://oss.adquan.com/logos/1713324452637272.jpg",
      "thumb": "https://oss.adquan.com/upload/20240206/1707187871957128216ed1e42f.png",
      "source_url": "https://m.adquan.com/creative/detail/340276",
      "title": "2024超人归来 | 能走过冬天，你就是超人",
      "description": "过去一年，慢性呼吸系统疾病流行，受到越来越多人的重视，感冒药也成了很多家庭不可或缺的常备药。而提到感冒药，很多人应该会记得一个有着30年历史的经典品牌——快克。对于快克的标识性符号——绿色超人，很多人也是记忆犹新。 还记得我刚入行广告业的时候，当时我所在部门负责快消品行业的品牌代理，隔壁办公室则是负责医药品牌。那会我就特别羡慕医药部门的小伙伴，觉得他们的工作特别简单、轻松。 那时节，药品广告多为功效诉求，创意手法较为单一，药品文案中使用最多的词就是“管用”；然后药企拍一条TVC可以连续使用两三年不更换，对广告公司来说特别省事。 然而十多年过去了，对于今天的药品营销来说，单纯的功能宣传已经很难被消费者所认知，尤其无法打动年轻人的心，而且今天已经不是一条TVC打天下的时代了，纯粹靠硬广很难吸引消费者关注和讨论，根本就难以撬动流量。 那么在今天，药品乃至整个大健康行业应该如何做品牌，如何实施营销推广呢？接下来给大家提供一个非常值得参考的品牌打法与案例。 01 超人归来，IP营销新范式 提到快克，很多人第一时间会想到快克的视觉符号绿超人。现在，快克将超人打造成为品牌IP，以其作为品牌营销的中心，以及和消费者展开持续沟通的传播阵地。 过去在传统年代，企业通过一条TVC、一套系列平面稿来全年进行投放，就可以和消费者建立持续沟通，形成长期认知和记忆。 而在今天，虽然很多企业每天都在发布大量的图文和短视频，做非常多的活动、事件、话题，但问题是今天是一个碎片化的时代，媒体多元，消费者注意力稀缺。企业虽然做了大量的内容和传播，但是消费者却越来越难对品牌形成整体性印象，认知不清晰，记忆不深刻。 而且更严重的问题是，这些内容都是一次性的，无法复用，无法形成累积效应。一切都是方生方死，上午发布的内容下午就过时了。企业不仅无法持续抓住消费者，形成一整年的沟通，而且每一次开展营销推广都要从零开始，重新创作内容，重新和消费者建立连接，并且花费大量预算去购买流量推广这些一次性内容。 所以，我一直反复强调今天做营销必须打造IP，用IP承接流量和粉丝，让每一次营销推广有积累；用IP建立品牌资产，形成用户长期认知。 但是， 很多人对IP的理解有误区，以为做IP就是设计一个吉祥物或者虚拟形象，作为一个视觉符号让其出现在产品包装上、活动海报上、自媒体上就完事了。但这其实不是IP，而是物料。 我对IP的定义是品牌化的内容产品，并且可持续、可迭代。 IP的实质是内容产品化，将内容当成产品一样去设计、去推广、去迭代、去变现，实施品牌化运作（IP要有自己的名称、logo、形象、固定的推广节点和用户参与仪式）。并且持续去运营，不断注入新的内涵，演绎新的形式，衍生新的玩法。 当IP成型，它就能承载用户认知和记忆，成为品牌的核心资产。比如双11之于天猫，“上校”和疯狂星期四之于肯德基等等。 快克的超人IP同样是一个典型案例，它不只是设计一个视觉形象，更重要的是用这个IP和消费者产生大量真实的交互。这种做法不仅有效继承了快克过去二三十年累积下来的品牌资产，而且将其激活并发扬光大。 快克的具体做法就是打造了一个全年的演员招募计划，面向全社会不同行业的平凡工作者发出邀约，请他们来扮演超人，展示自己的“快”技能，拍摄12部不同类型的“快电影”。 当然，扮演超人不只是穿上一件超人的衣服，而是在每个普通人的工作与生活中看到闪光点，看到他们超越凡俗之处，每个人都可以是自己生活中的超人。 这种IP运作理念，不仅强化了品牌和消费者之间的联系，让消费者成为品牌经营的主角，快克就是我们的超人；而且为快克IP注入了内涵，也升化了整个快克品牌的形象，体现了品牌的社会责任与担当。 这12部“快电影”有一个共同的名字，叫做《快超12克》。它以月度为节奏，每月一部对外释出，连续12个月进行发布。每一部都选择一个节气为主题，结合一种职业，输出一则人生故事，表达一种平凡超人的精神。可以说，这是真正的国民级电影短片，透过各行各业看见整个社会的众生相。 《快超12克》实际上是另一种IP形式。 我把品牌IP划分为5种类型：人设IP、活动IP、作品IP、文创IP、场景IP。 人设IP是品牌形象爱豆化，是对品牌形象的升级和具象，让品牌变得可以被追随； 活动IP是推广活动节庆化，打造持续运作的活动赛事和用户经营活动，让品牌变得可参与； 作品IP是广告内容节目化，把一次性的广告变成可持续、可共鸣的艺术作品； 文创IP是周边物料产品化，打造体现品牌内涵、独立设计的周边文创，让品牌变得可拥有； 场景IP是门店景点化，对店铺实施景点化改造，把品牌变成可体验的剧场。 快克就是人设IP“超人”和作品IP《快超12克》的双IP运作，二者共同成为品牌全年度，乃至未来数年品牌营销的中心，以此突破今日传播碎片化、一次性的困境，有助于品牌扩大流量与声量，沉淀品牌资产。 尤其可贵的是，这种做法为千篇一律的大健康营销吹来了一股清新之风，打破了过往医药营销的单一套路，和缺乏个性的老派形象。 围绕着“超人”招募，快克还打造了一个有趣好玩的线上玩法。前些天，一场#日赚30000，快克找你演超人# 的招募活动冲上微博热搜，引发了很多人的好奇与热议。 快克通过“报名+互动+片单”的三重链路去影响消费者，强化了和年轻消费者的沟通。活动上线后，微博话题阅读量总曝光破2.8亿，招募视频播放量超过1200万，微博大屏强势曝光量达到4000万。 02 双效融合，节气营销新玩法 快克打造的这个IP项目《快超12克》，另一个值得称道的玩法是以节气为载体进行演绎。对于节气营销的玩法，令人拍案叫绝。 我以前也专门写过文章，强调节气对于营销的价值。二十四节气是中华历史文化的重要组成部分，蕴含有悠久的文化内涵和历史积淀，对于品牌方，尤其是中国品牌来说，是非常好的营销节点。 节气在网络上的走红，最早可以追溯到2012年摄影师青简的一组“二十四节气”摄影作品，当时在微博、豆瓣等平台被疯转。2016年底，二十四节气在联合国申遗成功，申遗视频中还用了青简的作品。 2022年初，北京冬奥会开幕式中还特意使用了24节气来做倒计时，引发了全民盛赞。 早在2013年的时候，我所在广告公司做一个外国旅游观光厅的在华传播项目，当时我们提出的概念就是以24节气作为核心传播节点，那时候我们就认为，做传播何必非要以15秒TVC+系列主平面+年度大活动为中心。 近几年来，大家也可以看到很多品牌打造了非常成功的节气营销。最近的案例比如2023年初蕉下打造的《惊蛰令》；2023年6月，伊利高考营销以芒种节气为切入点，表达“青苗生芒，种有所获”的美好祝愿。还有曾经引发全网热议的奥迪小满广告，虽然这一广告因为抄袭而翻车，但是创意概念和小满这个节点的策划都值得称道。 快克选择节气为切入点，用12个节气来拉通全年的营销推广。在策略上又不单单是文化上的考量，更妙的是将节气与产品、消费者需求和生活习惯巧妙融合在一起。 因为节气反映的是历法中的自然节律变化，每一个节气，都代表着气候的变动。而众所周知，当气候变化之时，忽冷忽热、时晴时雨、或干或湿，正是最容易感冒、感染呼吸道疾病的时候。 快克选择节气切入，对于展示产品功能价值，影响消费者的生活习惯极有作用。 事实上，自从2020年开始，快克就围绕节气展开营销推广，发起#快克节气说 等话题，并和中国天气合作打造了“节气变化与感冒趋势联合研究院”，深入探索节气与气候变化、感冒之间的关系，并用公益性科普报告的形式，让大家及时做好防范，用更科学有效的方法预防感冒、治疗感冒。 比如2020年11月立冬，快克和中国天气联合推出了“全国感冒指数地图”； 2021年1月小寒，推出了“全国冻哭预警地图”； 2021年10月寒露，推出“秋裤预警地图”；2022年3月春分，推出“全国春捂指数地图”等等。 可以说，快克通过节气营销，真正将品牌融入到消费者生活之中，强化了品牌在用户生活中出现、以及被选择的机会。 所以顺理成章地，快克这一次将超人IP与节气融合在一起，借助12个节气演绎超人IP。昨天2月4日恰逢立春，这是二十四节气的第一个节气。那么在这个立春时节，快克给我们献了一份什么样的惊喜呢？ 03 立春大片，春节营销有新意 眼下春节临近，各大品牌竞相开展春节营销。相信大家最近这段时间都看了不少新春贺岁广告。但是不用说，这些广告中绝大多数都是千篇一律的红火喜庆氛围，和随处可见的龙元素，让人眼花缭乱，完全分不清到底谁是谁做的。 说到生肖，其实在真正的传统习俗中，新的生肖并不是从大年初一这一天算起，而是从立春这天开始。立春一过，新的生肖就要走马上任。 所以在这个龙兔交替之际，快克就结合立春这个节气，打造了一条关于生肖更换的大片。辛苦陪伴了我们一整年的兔子站完最后一班岗，交接让位给新的龙生肖。 龙和兔子是一组鲜明的对比。龙深受人们喜爱，代表着强大、繁荣、尊崇；而兔子在人们心目中则是弱小、灵活、顽强生命力的象征。 顺便说一句，可口可乐公司的品牌战略就叫做“龙与兔子”，可口可乐将公司旗下的一众品牌划分成龙品牌和兔子品牌两种，龙是承担主销量的核心品牌，兔子是填补市场空间的细分创新品牌。 这两个生肖的对比，其实恰恰就是这两年人们心态的生动写照。2023年不容易，很多人在工作与生活中都疲于奔命，甲流乙流支原体又轮番来袭。我们像弱小的兔子一样，顽强地生存，到处寻找藏身之窟，并且怀抱着一份微小的希冀，渴望明年会更好，渴望在新的龙年能够龙飞九天、龙年转运。 所以在这则立春好《运》的电影短片中，快克向我们捎来了一份温暖而美好的祝福：“立春了，一切都会好起来。龙年，我们看好你”。 在过去这辛苦的一年中，兔子作为“生肖守护者”守护了我们一整年，来到龙年，快克告诉我们只要挺过了这难熬的一年，那么来年就会更好；只要经历过寒冬的考验，那么春天就在不远处，因为 “ 能走过冬天，你就是超人 ” 。 这就是快克这条立春大片的主题，它不仅给每个人带来了希冀和祝福，同时也为“超人”IP注入了灵魂，高度契合了立春这个节点、新年这个当下一种普遍性的社会情绪。 以上这些就是快克品牌的完整打法，它以品牌IP经营为中心，以节气时令为载体，通过优质内容+用户参与来整合营销传播，占领用户心智。 作为一个要持续整个2024年的项目，这条立春大片为这新的一年开了一个好头，现在我又迫不及待想看到快克剩下11期电影、11个节气、11个超人的精彩表现了。 THE END. 我是空手。 《传神文案》作者，前上市公司高级营销群总监&内容营销中心副总经理，科特勒增长实验室导师。 《卧虎藏龙》里说过：“把手握紧，里面什么也没有；把手放开，你将得到整个世界。” 所以叫我空手。",
      "main_image": "https://oss.adquan.com/upload/20240206/1707187871957128216ed1e42f.png",
      "images": [
        "https://file.adquan.com/pic/170718623418a7ce3d063c3dbd.jpg",
        "https://file.adquan.com/pic/1707186234677cb84a84b93edf.jpg",
        "https://file.adquan.com/pic/1707186234c78304b5eca1f3ce.jpg",
        "https://file.adquan.com/pic/170718623545697e037d0a46de.jpg",
        "https://file.adquan.com/pic/17071862350fe1a2f070a132e6.jpg",
        "https://file.adquan.com/pic/17071862368be73a57fd7960a4.jpg",
        "https://file.adquan.com/pic/1707186236198068fc64d528c1.jpg",
        "https://file.adquan.com/pic/170718623604716529fa025c29.jpg",
        "https://file.adquan.com/pic/17071862373e96d9d69b730d02.jpg",
        "https://file.adquan.com/pic/1707186238b688362d0698b9fb.jpg",
        "https://file.adquan.com/pic/1707186239afaf5a1296a8cd27.jpg",
        "https://file.adquan.com/pic/170718623974663fde691fcb5a.jpg",
        "https://file.adquan.com/pic/1707186239e8062a30cd11c68f.jpg",
        "https://file.adquan.com/pic/17071862409bdd4191eb4d0e5f.jpg",
        "https://file.adquan.com/pic/170718624044dc7c52bc1e819c.jpg",
        "https://file.adquan.com/pic/17071862412061a9eec370eea6.jpg"
      ],
      "author": "Faye",
      "publish_time": "2024-02-06",
      "brand_industry": "互联网",
      "activity_type": "微电影",
      "location": "中国大陆",
      "tags": [
        "快克"
      ]
    },
    {
      "case_id": 347856,
      "score": 4,
      "score_decimal": "8.1",
      "favourite": 1,
      "company_name": "京东等2家公司",
      "company_logo": "https://oss.adquan.com/logos/1629706454101437.jpg",
      "thumb": "https://oss.adquan.com/upload/20241114f765def54c068b61.jpg",
      "source_url": "https://m.adquan.com/creative/detail/347856",
      "title": "这波京东服饰的广告，居然像衣橱一样一直在上新！",
      "description": "从9月份，到未来12月份的暖冬， 线下梯媒投放 在当今电商竞争激烈的背景下，壹捌零助力京东服饰通过一系列精心策划的品牌宣传，成功重塑了消费者对京东服饰的传统认知，从“品牌选择少”、“类目不够时尚”的刻板印象，转变为一个引领时尚潮流、提供丰富穿搭灵感的电商平台，展现出强大的市场竞争力。 这次品牌Campaign的核心目标，就是要打破消费者对京东服饰的固有偏见，特别是在年轻女性群体中，树立起“买服装 上京东”的心智。 让大家想买衣服的时候，就会来京东买，突破类似“男人一年下2次单”的购买现状。 京东服饰面临的挑战是显而易见的，我们如何改变这种固有印象，达成“买服装上京东”的用户心智，让穿衣的每一位都想来京东逛一逛呢？这是京东服饰要解决的目标与难题。 回到消费者每一天的穿衣，每一天出门前的OOTD，都离不开穿搭。穿搭好看的衣服，会让人想看、想挑、想买、想分享。穿搭好看的衣服，会给人提供情绪价值，WOW~到所有人。 京东服饰决定从趋势穿搭入手，为消费者提供灵感，满足他们对时尚和个性化的需求。 1. 提供趋势穿搭灵感： 京东服饰敏锐捕捉当下新潮的穿搭趋势，展示了不同季节、不同场合的穿搭灵感。不仅展现了京东服饰的时尚感，更为消费者提供了实际的穿搭建议，帮助他们找到适合自己的风格。 2. 展现海量品牌标签： 为了强化品牌丰富度的认知，京东服饰在广告中展示了大量穿搭品牌标签。展示了京东服饰的品牌多样性，也让消费者明白，在京东可以找到各种风格的服饰，满足他们的不同需求。 3. 提供穿衣情绪价值： 京东服饰深知，穿搭不仅仅是外表的装扮，更是情绪的表达。因此广告中不仅展示了时尚的穿搭，更通过真实的生活场景与模特穿搭的情绪张力，传达了穿搭带来的自信、快乐和愉悦。这种情绪价值的提供，更加打动了消费者，特别是女性消费者。 01 穿搭展示是必要的， 京东站内直接上线「趋势穿搭方案」 品牌主线内容创意： 创意内容的展现很纯粹，所有的视频与大平面，都是为了让消费者记住6个大字「买服装 上京东」。 全力做到硬广的同时，也能用时尚打动人。 而如果你有被某个「趋势穿搭单品」种草，也能记下这些标签。更可以上京东搜索“趋势穿搭”，发现更多穿搭灵感。 02 品牌TVC广告： 朋友圈/TOPVIEW/视频号/线下梯媒 《秋尚新》 《秋出游》 《秋入冬》 03 趋势穿搭LOOK #旷野美拉德 #城市轻户外 #舒适宅生活 地铁站KV投放视频 此次品牌Campaign取得的显著成功，不仅提升了京东服饰的时尚感和品牌丰富度的认知，还成功吸引了大量年轻女性消费者的关注和购买。 创作企业名单 客户：京东服饰 代理商：壹捌零 制作：赤马、启李、必火 创作成员名单 客户：一博、晓月、Maggie 创意：光哥、蓉蓉、珺哥、Momo、毛毛 阿康：Vanessa、Joanna、lvan、 观平 导演：Zika 摄影师：薛龙 穿搭师：浩浩",
      "main_image": "https://oss.adquan.com/upload/20241114f765def54c068b61.jpg",
      "images": [
        "https://file.adquan.com/uploads_img/17315710163emoq.jpg",
        "https://file.adquan.com/uploads_img/1731571036oj9si.png",
        "https://file.adquan.com/uploads_img/1731583996he18t.png",
        "https://file.adquan.com/uploads_img/17315747933nz4p.jpg",
        "https://file.adquan.com/uploads_img/1731574824u8v4m.jpg",
        "https://file.adquan.com/uploads_img/1731574851fxiz6.jpg",
        "https://file.adquan.com/uploads_img/1731574874h47sv.jpg",
        "https://file.adquan.com/uploads_img/17315748989tdq8.jpg",
        "https://file.adquan.com/uploads_img/1731574914hausc.jpg"
      ],
      "author": "壹捌零创意集团",
      "publish_time": "2024-11-15",
      "brand_industry": "互联网",
      "activity_type": "影视",
      "location": "中国大陆",
      "tags": [
        "京东",
        "双十一"
      ]
    },
    {
      "case_id": 346023,
      "score": 4,
      "score_decimal": "8.0",
      "favourite": 5,
      "company_name": "McDonald’s 麦当劳",
      "company_logo": "https://oss.adquan.com/logos/1727344407b40ad44aada194cf.jpg",
      "thumb": "https://oss.adquan.com/upload/17242062827e0e11f692d46cd6.jpg",
      "source_url": "https://m.adquan.com/creative/detail/346023",
      "title": "被网友骂惨了的日本麦当劳AI广告，后来怎么样了？",
      "description": "马斯克点赞的这支日本麦当劳AI美女广告，被网友骂惨了…… 8月17日，日本麦当劳在X发布一支15秒AI广告片，推广其限时薯条优惠活动。视频由艺术家Kaku Drop使用Luma AI制作而成，截至目前在日本麦当劳的账号已经收获了1286万次播放。Luma AI官方账号也转发了这条推文，其6月发布的AI视频生成模型Dream Machine，被视为Sora的强劲竞争对手。 这支AI广告片甚至吸引到了马斯克的目光，他评论道：“Cool”。 但在日本麦当劳的官方账号下，大量网友对AI的使用产生了质疑， “恶心”“毛骨悚然”“消除食欲” ，高赞评论多数呈现负面态度。 事件发生后，日本麦当劳并未做出任何回应，继续用广告片和海报等物料对薯条优惠活动进行推广，但却再也没有使用过AI。 而在其后续的传播中，尤其值得一提的是8月26日发布的这支广告片，在不到10秒的时间里，日本麦当劳简单记录了一段炸薯条的过程，却在X收获了54万次播放，以及评论区的一片赞美。 日本麦当劳的AI美女广告被吐槽“没食欲”，一段炸薯条视频却收获大量好评…… 对于品牌使用AI做广告， 你怎么看？",
      "main_image": "https://oss.adquan.com/upload/17242062827e0e11f692d46cd6.jpg",
      "images": [
        "https://file.adquan.com/pic/1724205932da94ec3575ea5c74.jpg",
        "https://file.adquan.com/pic/172420593337ee60909f46f268.jpg",
        "https://file.adquan.com/uploads_img/kzi5e1725341716.png"
      ],
      "author": "永刚",
      "publish_time": "2024-08-21",
      "brand_industry": "快消品",
      "activity_type": "影视",
      "location": "日本",
      "tags": [
        "马斯克",
        "AI"
      ]
    },
    {
      "case_id": 349931,
      "score": 4,
      "score_decimal": "8.0",
      "favourite": 3,
      "company_name": "McDonald’s 麦当劳",
      "company_logo": "https://oss.adquan.com/logos/1727344407b40ad44aada194cf.jpg",
      "thumb": "https://oss.adquan.com/upload/17394370350c5e218b863edf0c.jpg",
      "source_url": "https://m.adquan.com/creative/detail/349931",
      "title": "为了卖汉堡，香港麦当劳打造感人爱情故事",
      "description": "为了推广香港麦当劳最受欢迎的汉堡之一玉子将军汉堡，麦当劳决定在这个情人节将该款汉堡重新上架。 并且为了与情人节元素更契合，麦当劳还制作了一支将军胜利归来与爱人重新相聚的日系短片，在 汉堡之外赋予其爱情元素。",
      "main_image": "https://oss.adquan.com/upload/17394370350c5e218b863edf0c.jpg",
      "images": [],
      "author": "源泉",
      "publish_time": "2025-02-13",
      "brand_industry": "快消品",
      "activity_type": "影视",
      "location": "中国香港",
      "tags": [
        "麦当劳",
        "玉子将军"
      ]
    },
    {
      "case_id": 332924,
      "score": 4,
      "score_decimal": "7.7",
      "favourite": 9,
      "company_name": "美团门票",
      "company_logo": "https://oss.adquan.com/logos/17424599183aaa90cdf28e1bb0.jpg",
      "thumb": "https://oss.adquan.com/upload/20230602/1685674303554444.jpg",
      "source_url": "https://m.adquan.com/creative/detail/332924",
      "title": "他们做了这些让你更想出去玩 旅游热潮后的思考",
      "description": "夏天的脚步越来越近，随着气温一通升高的，那就是人们对于出门旅游的热情。根据文旅部发布的“五一”假期旅游数据，全国国内旅游出游合计2.74亿人次。在这波旅游热潮中，我们看到了全国各地很多新老“朋友”的面孔，有的在淄博做着烧烤、有的在竹林间打滚、有的迎接了一波波“特种兵”们的检阅。 （图片来自网络） 在人们迫切的出门走走的需求下，假期的旅游热潮是可预期的。但热潮仅仅是因为假期么？其实并不尽然，随着社交媒体平台的持续发力，各地旅游局、景点、平台的积极发力，消费者对于旅游的目的性也在逐步增强，如何利用旅游这件事，完成自我享受的同时，完成社交资本的积累，更是成为各方努力的目标。 所以我们能看到在国宝展区外的人山人海、可以看到“特种兵“五岳打卡的壮举、可以看到各地的寺庙中，佛祖忙着接待摩肩接踵的年轻人。他们在感受大好河山的同时，也给自己的朋友圈中留下了一串串点赞。 就好像最近看到的美团门票做的一支527主题TVC，就很好的展现了当今人群的旅游现状，不管是流量当担，国民爱豆大熊猫、还是自然风光、名胜古迹或者主题乐园，都很好的体现了现在的旅游现状。 （熊猫带给人的治愈感，每个去亲眼见过的人都会懂，国宝级的治愈能力） （特种兵拉练式游玩，边玩还能边减重，划算！） 通过旅游获得马斯洛需求层级中的自我成就，不管是在旅游过程中获得精神的抚慰，还是在旅游后获得社交媒体中的点赞，其实都是一种自我成就的满足。美团门票这支527的TVC也很好的抓住了受众旅游中的各类洞察，将受众旅游中会想要获得满足的利益点进行了生动且趣味性的展现，让看到的人都能会心一笑。特别是一整天的心理咨询室篇，寺庙作为社会的“缓冲地带”之一，为年轻人提供了一个短暂逃离焦虑、寻求情绪出口的空间，而年轻人的寺庙游，其是对一种新的消费主义叙事的积极拥抱。 而景区在此过程中也嗅到了很大的机会，从各地文旅局长的缤纷出击，大展身手后，景区也在思考如何更好的能够在社交媒体网络上展现出自己的“小性格”。官方玩“梗”最为致命，将社交媒体中的热点进行生动展现，也是为景区自身积攒社交媒体资产。 红山动物园在竹排上的猴子 被以为是登顶的泰山售票处 进一步降低受众的认知门槛，为景区景点带来扩大曝光，拉进受众和景区之间的关系，这也就是美团门票把这次的传播称为“代言人”的原因之一，无论是时下热点，热门话题，大众所好，都依巧妙的托洞察比喻，让当代年轻人敏锐的情绪gap更上一层。人格化的景区呈现，也使得出游一事不仅是出游，而是更加生动富有感召地与世界接触与体验，必然会获得受众的认可。 在人们迫切的出门走走的需求下，假期的旅游热潮是可预期的。但在节点之后，如何将热度延续，如何应对当消费者在热度消退后，更加理性的出游需求，把已有的热度进行蓄能，转化为对非假期时间的出游势能，这次美团门票527的尝试也许能给出一些答案。 不知看完之后，你是否也有了出游的心之所向。如果你对这次的广告有自己的观点，欢迎在评论区探讨",
      "main_image": "https://oss.adquan.com/upload/20230602/1685674303554444.jpg",
      "images": [
        "https://file.adquan.com/uploads_img/168567336593m1u.png",
        "https://file.adquan.com/uploads_img/16856736371sm7c.png",
        "https://file.adquan.com/uploads_img/1685673803afq9v.jpg",
        "https://file.adquan.com/uploads_img/1685673818itd5j.jpg",
        "https://file.adquan.com/uploads_img/1685673903y9ek3.jpg",
        "https://file.adquan.com/uploads_img/1685673924bn0c6.png",
        "https://file.adquan.com/uploads_img/1685674007so6lu.png",
        "https://file.adquan.com/uploads_img/1685674043xrzt4.png",
        "https://file.adquan.com/uploads_img/1685674054t63s5.png",
        "https://file.adquan.com/uploads_img/1685674062iq6yk.png"
      ],
      "author": "TopAgency",
      "publish_time": "2023-06-02",
      "brand_industry": "互联网",
      "activity_type": "影视",
      "location": "中国大陆",
      "tags": [
        "旅游",
        "社会热点"
      ]
    },
    {
      "case_id": 334917,
      "score": 3,
      "score_decimal": "6.0",
      "favourite": 6,
      "company_name": "MUJI 無印良品",
      "company_logo": "https://oss.adquan.com/logo/20160304120051_63223_320.png",
      "thumb": "https://oss.adquan.com/upload/20230810/16916592285c1bb8454a5c3c0a.png",
      "source_url": "https://m.adquan.com/creative/detail/334917",
      "title": "MUJI治愈广告，强迫症舒适度+100%",
      "description": "前不久MUJI golbal发布了《我们出门吧》系列广告，广告一共有四支。 没有特别的文案，而是以一种独特的治愈内容表达方式像用户传达信息。 不论是穿上MUJI还是出门走走，都如此简单。 有时候广告内容不需要太多的文案或者表达，一个简单的创意让用户感到舒适，就能很好地传达品牌所想要表达的理念。 但其实这种超脱文字之外的表达往往更需要创意人有强烈的表达能力，去用多元的形式来完成创意内容。",
      "main_image": "https://oss.adquan.com/upload/20230810/16916592285c1bb8454a5c3c0a.png",
      "images": [],
      "author": "源泉",
      "publish_time": "2023-08-10",
      "brand_industry": "互联网",
      "activity_type": "影视",
      "location": "中国大陆",
      "tags": [
        "MUJI",
        "无印良品"
      ]
    },
    {
      "case_id": 337297,
      "url": "https://m.adquan.com/creative/detail/337297",
      "title": "天猫 × bilibili双11广告，何同学更新了？",
      "error": "HTTPSConnectionPool(host='m.adquan.com', port=443): Read timed out.",
      "crawl_time": "2026-01-18T22:58:47.294943"
    },
    {
      "case_id": 314213,
      "score": 2,
      "score_decimal": "4.0",
      "favourite": 6,
      "thumb": "https://oss.adquan.com/upload/20220402/1648869520f993c1da8b9fae13.png",
      "source_url": "https://m.adquan.com/creative/detail/314213",
      "title": "朱一龙监制欧莱雅音乐剧，为什么有点看不下去？",
      "description": "巴黎欧莱雅携手品牌代言人朱一龙拍摄了一部态度音乐剧。片中，朱一龙变身音乐制作人监督表演，舞台上的演员们以音乐剧的形式表达恋爱与合群的态度，借此输出第二代紫熨斗「新一代 更厉害 」的产品卖点。 01 “可以合群，但没必要” 02 “可以恋爱，但没必要” 巴黎欧莱雅属于欧莱雅集团的大众化妆品部，欧莱雅旗下还有兰蔻、乔治阿玛尼、YSL、碧欧泉、欧珑和科颜氏等众多品牌。关于它的品牌代言人，它往往会根据其调性邀请适合的代言人。在粉丝心中，欧莱雅有一个别称，叫做“流量收割机”，品牌涉及的代言人涵盖易烊千玺、张艺兴、朱一龙、迪丽热巴、关晓彤和陈晓等众多知名艺人。",
      "main_image": "https://oss.adquan.com/upload/20220402/1648869520f993c1da8b9fae13.png",
      "images": [],
      "author": "River",
      "publish_time": "2022-04-02",
      "brand_industry": "时尚、美妆",
      "activity_type": "影视",
      "location": "中国大陆",
      "tags": [
        "巴黎欧莱雅",
        "朱一龙"
      ]
    },
    {
      "case_id": 48525,
      "score": 5,
      "score_decimal": 10,
      "favourite": 11,
      "company_name": "阿里妈妈",
      "company_logo": "https://oss.adquan.com/logo/1548324230214398.jpg",
      "thumb": "https://oss.adquan.com/upload/20190116/15476490183a4be2070c71c1de.png",
      "source_url": "https://m.adquan.com/creative/detail/48525",
      "title": "联合利华有支排雷兵和护航舰，从全域营销推动品牌数字化进程",
      "description": "从今年开始，借助于阿里巴巴Uni Marketing全域营销提供的解决方案，阿里生态环境中诞生了越来越多的网红爆款。 今年双11期间，联合利华旗下的柔顺剂品牌金纺，整合了数据银行、策略中心、Uni Desk等全域营销的工具平台，为品牌带来的新客占比超过70%。 自1992年底进入中国，金纺几乎成为衣物护理剂的代名词。作为柔顺剂品类TOP1的领导型品牌，其自身的品牌形象也一直都停留在与功效本身密切相关的“柔顺”二字上。但相比较护肤、日化等行业，洗护在推陈出新上最大的挑战在于消费者的感知和参与度不强，教育成本高。 “全域营销一方面帮助品牌在全触点找到更多潜在消费者，另一方面通过提供数据化支持，定向精准投放，激发需求，不断验证和优化人群策略和营销策落，提升品牌价值。”联合利华大数据&数字化发展资深总监Susan REN表示。 从全域营销概念提出至今，联合利华作为先锋品牌集团，参与共创了数个阿里数据产品工具。如今对于品牌来说，对阿里巴巴数据工具的运用已变成品牌在阿里生态环境中的常态化操作，并形成了一套可输出、可复制的流程机制，进一步推广到集团的多个品牌在与阿里的全域营销策略中去。 而放眼全球市场，越来越多各行业的知名品牌，也开始将全域营销深入骨髓地应用至日常运营中，甚至在推动企业数字化转型中扮演重要角色。 2018年双11金纺消费者资产大爆发，新客占比超过70% 数字化运营已经融入到了金纺整个品牌的运营中。“数据回流至品牌数据银行”之下，以银行为中心联动其他阿里工具，进一步对人群做深度挖掘和再应用，为金纺在2018年双11的品牌爆发埋下伏笔。 销售额之外，金纺的消费者资产也实现了显著增长，在阿里巴巴于今年双11首次推出的消费者资产榜单中，位列行业前十位。 在Susan看来，这主要得益于以下原因。 首先，串联站内站外媒体，跨触点定向沟通高潜人群，显著提升拉新效率。 双11预热期间，针对品牌高潜人群，金纺利用阿里Uni Desk实现站内和站外跨触点沟通和转化。针对全新升级的花漾香芬系列产品，金纺对其目标人群在站外投放微博信息流广告，之后通过品牌数据银行回流广告曝光和互动人群，并在双11期间通过阿里妈妈钻展广告在站内持续沟通，触发购买。Susan透露，站外曝光触发的购买人群中，70%以上是品牌新客，拉新效果相比纯站内广告高出约20%。 其次，精细化人群运作，跨类目挖掘高潜力高意向消费者。 联合阿里数据工厂、数据银行、策略中心三大工具平台，金纺根据品牌消费者的高相关购买品类及人群特征标签，挖掘了来自非家清类目的跨类目人群，运用于双11预热及爆发。跨类目人群的运用，使金纺跳出原有柔顺剂品类的潜客圈选范围，实现品牌的跨品类拉新。双11期间，金纺因此转化了大量新客，其中品类新客占比相较整个柔顺剂行业高出6.4%。 一个有趣的新发现是，来自隐形眼镜/护理液类目的人群，也会是金纺的潜在消费者吗？数据化洞察后给出的答案是，yes。 按照以往的用户调研、市场观察，我们或许也会得出隐形眼镜的用户群体，会对洗护、清洁有更高要求，但数据工具的使用，能更精准地还原人群的差异性和共同点，从而辅助做出确定性的决策。 从共创到推动，全域营销成全球品牌的常态化运营 事实上，在双11金纺消费者资产爆发之前，联合利华公司对数字化的认识便已十分深刻。Susan率领的这支大数据队伍始于联合利华刚开始接触电商之时，对外连接阿里等合作伙伴，对内协同市场部、电商部等部门，至今已有多年的经验沉淀。 新理论的建立，思维上的转变是最难的。在理解什么是全域营销时，品牌和阿里巴巴需要长期持续的沟通。 联合利华内部的改变同样在发生。在组织架构上，大数据团队在这一年招兵买马，不断补充优秀人才保证团队能力的丰富性；在实操过程中，则通过创新案例的操练，让概念和工具更好地应用到实际场景中。 “如果只是沉淀到品牌数据银行，那它只能作为看板或报表。但对于品牌来说，它应该发挥更大的作用，通过对数据的运用，变成可以操作的工具和连接的桥梁。”Susan说。 同时，大数据团队形成有节奏的运作机制，设置操作流程模式，输出给其他部门，也逐渐变成跨部门的常态化操作，推动了品牌全部门广泛的应用能力的提升。 不只是联合利华，网红品牌戴森也曾在与全域营销的模式共创中受益。 这些探路者们验证了，全链路打通在数据营销层面存在的必然性、普适性，进而推动了社交+电商这条“高速公路”的通行。今年6月13日，阿里巴巴集团和微博在北京共同宣布启动“U微计划”，携手打造社交✖消费的全域解决方案。而这也在逐渐实现全域营销包含的三大重要方面——全媒体触达、全渠道商业生态和全链路消费者运营。 数字化带来商业价值最大化 品牌养成数字化洞察市场和消费者的习惯之后，可以为品牌拓展更多机会。不过，在运营模式上轻车熟路，并不意味着就能完美演绎全域营销。 消费者不断成长、需求日新月异，他们在品牌数据银行沉淀成的消费者资产，也像活水一样是实时变化的。既然以消费者运营为中心，全域营销的产品工具、理念内涵也在不断升级。 比如品牌数据银行，Susan认为它正发挥出更动态化的工具属性，真正让资产流动起来，为品牌生利。只有数据工具不断结合场景应用，才能让数字化的进程如同大江奔腾，最终实现商业价值的最大化。 看上去天时地利，还有一个关键，是背后深谙运营之道的人。面对每一个升级时，这支大数据团队的使命，就如同排雷兵和护航舰：率先试水，从失败中总结雷区，在成功中沉淀经验，之后提炼成自己的认知，细化成员工使用手册；而在将提炼和复盘输出给其他团队时，布道重要，情感上的保驾护航同样重要。 “我相信一万个小时定律，所以宽容失败，鼓励尝试。”Susan说，“数字化建设和数字工具如果要提升生产力，只有一部分人用很难实现价值，需要不断锤炼，所有人都用。对于整个组织架构来说，每个人都失败，不如几个人先失败，避免试错成本不断累积，实现价值的有效掌控。”她对大数据团队定下的kpi之一，就是熟悉产品应用到给阿里团队提出改进需求。 谈及联合利华及金纺接下去在数字化营销的布局，Susan觉得有两大方向。首先是全链路运作，盘活阿里生态内更多工具的组合使用价值。其次是尝试新零售的全域营销拓展，目前已经与大润发展开合作，试图搭建更多业务的新场景。 这正如阿里巴巴集团首席市场官董本洪在此前演讲中所提到的，从数字化营销开始串联起整个商业生态，进而实现从零售营销到零售商品商业的整体转型、升级。",
      "main_image": "https://oss.adquan.com/upload/20190116/15476490183a4be2070c71c1de.png",
      "images": [
        "http://file.adquan.com/uploads_img/mrnb51547648980.jpeg",
        "http://file.adquan.com/uploads_img/fak351547648961.jpeg"
      ],
      "author": "晓云",
      "publish_time": "2019-01-17",
      "brand_industry": "快消品",
      "activity_type": "其它",
      "location": "中国大陆",
      "tags": [
        "阿里妈妈",
        "全域营销"
      ]
    },
    {
      "case_id": 40246,
      "score": 4,
      "score_decimal": "7.6",
      "favourite": 5,
      "company_name": "Droga5 纽约 美国",
      "company_logo": "https://oss.adquan.com/logos/1525429213436009.jpg",
      "thumb": "https://oss.adquan.com/upload/20170228/1488261069961123.jpg",
      "source_url": "https://m.adquan.com/creative/detail/40246",
      "title": "为了三个基础款,优衣库找Droga5和两位大导演拍了三支艺术大片",
      "description": "文/Vicky “我们为什么穿衣打扮？”这是2016年夏天优衣库抛出的问题，而就在前几天，优衣库回答了这一问题。 以“Because of life, we made lifewear（因为生活，所以服饰人生）”为主题，优衣库为旗下三个基础款产品推出了三支广告大片，而这幕后制作团队的来头并不小，由创意代理公司Droga5伦敦办公室+两位著名导演Autumn de Wilde和Nick Gordon共同执导的三支广告也透着浓浓的艺术气息与复古风。 无钢圈内衣的这支广告与之前KENZO为其WORLD香水推出的疯狂姑娘的广告有相似之处，都在传递突破女性固有的刻板印象。这支广告是重点在突出“打破常规的舞动”，由舞蹈家Ryan Heffington领舞，Autumn de Wilde执导。Autumn de Wilde还曾执导PRADA的“ The Postman Dreams ”的Campaign。 AIRism是一种排汗透气技术，它强调的是优衣库的高科技内衣。广告通过黑白的电影风格，妙地捕捉人们在日常活动中，没有任何衣服，汗水从身体蒸发。而正如广告语所言：“我们的衣服不应该和我们一起呼吸吗？”。广告由Nick Gordon执导，在圣地亚哥取景。 牛仔裤的广告也是由Nick Gordon执导，广告中男女在加油站浪漫相遇，他们都穿着仿旧的破洞牛仔裤，并用大量的特写镜头来显示牛仔裤的舒适。 一直以来主打简约的基础款都是优衣库最主要的特色，而这此的动作优衣库似乎想再加一个新的标签——文艺。 据Droga5 伦敦办公室的首席创意官David Kolbusz说：此次广告通过抽象的表达方式传递优衣库使生活更美好的品牌追求，并希望消费者能采取理性的理由购买优衣库的衣服。 优衣库的母公司Fast Retailing的全球创意总裁John C Jay也表示：这次的Campaign是一个很好的例子，通过不一样有特色的故事讲述服饰人生的意义。",
      "main_image": "https://oss.adquan.com/upload/20170228/1488261069961123.jpg",
      "images": [
        "http://wx3.sinaimg.cn/mw690/68722f9dly1fd64xa26k8g20go0cib29.gif",
        "http://wx3.sinaimg.cn/mw690/68722f9dly1fd64xey231g20go06yb2a.gif",
        "http://wx4.sinaimg.cn/mw690/68722f9dly1fd64xc7044g20go06zkjl.gif"
      ],
      "video_url": "http://v.qq.com/iframe/player.html?vid=u0379qfp5i3&tiny=0&auto=0",
      "author": "vicky",
      "publish_time": "2017-02-28",
      "brand_industry": "时尚、美妆",
      "activity_type": "影视",
      "tags": [
        "文艺"
      ]
    }
  ]
}