{
  "batch_num": 97,
  "batch_size": 20,
  "created_at": "2026-01-18T10:41:54.459042",
  "cases": [
    {
      "case_id": 43304,
      "score": 4,
      "score_decimal": "8.6",
      "favourite": 24,
      "thumb": "https://oss.adquan.com/upload/20180126/15169491486dabb11e5b0c5236.jpg",
      "source_url": "https://m.adquan.com/creative/detail/43304",
      "title": "《西游记女儿国》的海报，看一眼就美醉了",
      "description": "来源：创意嘿店（ID：highlight1207） 作者：店长 春节将至，一大波贺岁电影正在赶来的路上，而最先成功引起店长注意的，是被豆瓣提名为 “ 最值得期待的华语电影 ”《西游记女儿国》的电影海报。 视觉瑰丽惊艳、笔墨横姿生风，这张抓人眼球的古风海报，来自为《大护法》、《奇门遁甲》、《九州海上牧云记》等影视作品设计画作的80后画师张渔。在这张海报里，她以女儿国国王的娇柔背影作主体，将师徒四人乘风破浪的取经之道巧妙糅入画中。 经典著作《西游记》中，师徒四人误入西梁女国的这番经历是唐僧与女色距离最近的一次，面对女儿国国王对自己的一见倾心，唐僧内心也曾为之所动，但这段儿女情最终以唐僧一句 “ 若有来生 ” 无疾而终。而《西游记女儿国》则是重点演绎唐僧师徒在女儿国中遭遇的儿女情长及引起的沧桑剧变。 《西游记女儿国》的这张海报则完全体现了出家之人林立世俗之间的凡俗杂念与气定神闲。 概念海报 万念归心 一水留情 “ 动情 ” 海报 《西游记女儿国》的导演是拍摄《狗咬狗》、《军鸡》等片的香港导演郑保瑞，他的影像风格以凄厉著称，陈冠希都难逃他的诡谲之手。 而《西游记女儿国》中郭富城、赵丽颖、冯绍峰、小沈阳、梁咏琪、罗仲谦、刘涛等一众演员更是在他的角色设计下判若两人。 角色海报 赵丽颖 冯绍峰 罗仲谦 小沈阳 梁咏琪 郭富城 “ 鹿人皆知 ” 海报 “ 倾国倾城 ” 海报 “ 手到情来 ” 海报 “ 一念永恒 ” 海报 “ 春节盛宴 ” 海报 唐僧万般无奈诵佛号 无计可施只得求天意 师徒被困女儿国皇宫 悟空纵火欲破阵寻路 国王寻路嬉戏御花园 意外擒获四大 “ 采花贼 ” 八戒口涎仙草目含情 美色当前被捕也是福 沙僧驭水假作浇花状 老实人竟动旁门心思 为了击中大众心中那份永恒的「大圣情结」，《西游记》作为永不过时的经典题材，几乎年年都要被电影人换汤不换药地进行二次创作，但是，这些作品质量的参差不齐一度让观众想哭但是哭不出来。 而这部《西游记女儿情》原始定位就是：大型奇幻爱情喜剧。话已至此，店长就不对这部贺岁电影作过多猜测，想必它的最终目的就是让大伙儿大过年的图个乐呵，除了票房别无他求，而且在此新春佳节到来之际，《西游记女儿情》能够贡献如此海报以饱眼球已属不易。 《西游记女儿情》首发预告 《西游记女儿国》 大年初一 全国上映 店长官方唯一指定微博 @ 创意嘿店",
      "main_image": "https://oss.adquan.com/upload/20180126/15169491486dabb11e5b0c5236.jpg",
      "images": [
        "http://file.adquan.com/upload/20180126/1516949226160cc46c226dfdbb.jpg",
        "http://file.adquan.com/upload/20180126/15169491924ad28ac7ecd14249.jpg",
        "http://file.adquan.com/upload/20180126/1516949248355128639a3c65d7.jpg",
        "http://file.adquan.com/upload/20180126/151694966609ee0b80e50971f2.jpg",
        "http://file.adquan.com/upload/20180126/1516949686fde6a1ce9a815007.jpg",
        "http://file.adquan.com/upload/20180126/1516949715a5f331274b1fd612.jpg",
        "http://file.adquan.com/upload/20180126/15169497456fd35573e09e53a9.jpg",
        "http://file.adquan.com/upload/20180126/1516949768ba563adde6c84028.jpg",
        "http://file.adquan.com/upload/20180126/15169497956283cdb5bece2f14.jpg",
        "http://file.adquan.com/upload/20180126/151694981500e736762f2fb2a2.jpg",
        "http://file.adquan.com/upload/20180126/15169498577c1171d055ee4562.jpg",
        "http://file.adquan.com/upload/20180126/15169498756266e8c32805ec1c.jpg",
        "http://file.adquan.com/upload/20180126/151694990022eeb0f55621423e.jpg",
        "http://file.adquan.com/upload/20180126/15169499227964b4b3a64b176a.jpg",
        "http://file.adquan.com/upload/20180126/1516950032e0c857afca737f3a.jpg",
        "http://file.adquan.com/upload/20180126/151695006341ac70a51d0f8b03.jpg",
        "http://file.adquan.com/upload/20180126/15169500805fb6d1a39dc500f7.jpg",
        "http://file.adquan.com/upload/20180126/15169501441f0323fdf14fa1ba.jpg",
        "http://file.adquan.com/upload/20180126/1516950172c00e9b3745bfb0ac.jpg",
        "http://file.adquan.com/upload/20180126/1516950315a7d78d0b4930df66.jpg",
        "http://file.adquan.com/upload/20180126/1516950339c046212878669c1d.jpg",
        "http://file.adquan.com/upload/20180126/1516950372a1b575568cd237ab.jpg",
        "http://file.adquan.com/upload/20180126/151695038181d8e48f61e6b50e.jpg",
        "http://file.adquan.com/upload/20180126/151695041888c555c68ebdc5fe.jpg",
        "http://file.adquan.com/upload/20180126/1516950443713f5aed9e6ec72f.jpg",
        "http://file.adquan.com/upload/20180126/1516950516deae3fe975950914.jpg",
        "http://file.adquan.com/upload/20180126/15169505486b1820aec7205a8e.jpg",
        "http://file.adquan.com/upload/20180126/1516950572221fa6205be780ca.jpg",
        "http://file.adquan.com/upload/20180126/1516950624d912464d5e05e6e6.jpg",
        "http://file.adquan.com/upload/20180126/151695060013bcba4acf3f21b1.jpg",
        "http://file.adquan.com/upload/20180126/1516950705f6567d4b20f1c558.jpg",
        "http://file.adquan.com/upload/20180126/1516950676bffe9598c479d0f9.jpg"
      ],
      "video_url": "http://v.qq.com/iframe/player.html?vid=z0531vjc2u1&tiny=0&auto=0",
      "author": "杜玥",
      "publish_time": "2018-01-26",
      "brand_industry": "政府、非盈利机构",
      "activity_type": "平面",
      "tags": [
        "西游记女儿国",
        "创意嘿店"
      ]
    },
    {
      "case_id": 302638,
      "score": 4,
      "score_decimal": "8.0",
      "favourite": 14,
      "company_name": "淘宝天下",
      "company_logo": "https://oss.adquan.com/logos/1629960184183805.jpg",
      "thumb": "https://oss.adquan.com/upload/20210316/1615875100903516.jpg",
      "source_url": "https://m.adquan.com/creative/detail/302638",
      "title": "天猫小黑盒魔性表达：一想到你我就嘿嘿嘿~",
      "description": "天猫小黑盒作为天猫官方的全球顶尖新品始发阵地，将于六一儿童节前夜举办盛大的开「新」盛典，隆重推出「HEYLIVE」官方新品直播间，并同时揭晓旗下新IP——天猫小“嘿”盒。 八卦、互动、表达欲是善于冲浪的互联网er们与生俱来的基因。深谙Z时代social方式的天猫小黑盒「HEYLIVE」在此次上新营销中很好得验证了这点。 魔性话题，讨论不停 针对“天猫小黑盒HEYLIVE新直播”这一事件天猫小黑盒先是给出了一波悬念，结合小“嘿”盒这一虚拟形象的核心关键词“嘿”，延展到用于表达开心的语气词“嘿嘿嘿”，将小“嘿”盒与“开心”进行强关联，再加上热门歌曲《芒种》中走红的歌词“一想到你我就….”设定有记忆度的传播话题词#一想到你我就嘿嘿嘿#。通过洗屏式营销的大胆操作引发悬念、揭晓悬念，充分调动受众的好奇心及加深记忆点。 不少粉丝也忍不住留言，有跟着傻乐的吃瓜群众、也有燃烧八卦之魂想打破沙锅问到底的、还有围观迷惑行为大赏的……无论评论如何，天猫小黑盒成功调动起了用户的窥探欲，为营销预热做足了功课。 小时候，那些容易满足的开心，往往与买到新玩具，尝到新体验有关。同样的，长大后愈加珍贵的开心，也可以来自于买到喜欢的新品。HEYLIVE直播间正是通过小小的屏幕，让明星与消费者共享从小到大不变的开心，把“买新品等于开心”的心智辐射给已经长成大人的小孩。 social 玩得够好，抽奖也能营销 把抽奖跟social话题结合一起操作，不得不说天猫小黑盒有点东西。 在长达近24小时的悬念后，由天猫小黑盒官微正式发布《嘿嘿嘿之歌》，揭秘谜底，引出小“嘿”盒隆重出场。同时，官微还设置了有奖转发机制，鼓励大家将解密微博进行广泛扩散，强化大众认知。 当KOL纷纷亮出为了中奖的沙雕操作，成功吸引网友关注，有效增加锦鲤抽签活动的曝光。随着话题关注度的走高，在KOL文案中预埋信息点，并成功在评论区置顶位顺势露出抽奖地址，天猫小黑盒品牌再次“有趣”地引起大家注意和好奇，为抽奖蓄力，为品牌实现更大关注打下基础。 品牌调性传达，辐射用户心智 预热最后一步由天猫小黑盒官微申请成为#一想到你我就嘿嘿嘿#话题主持人，并将话题头像、导语设置为HEYLIVE上新直播的相关预告。所有前一天投放大号由于均没有带物料，在文案下方自动更新显示话题头像、导语内容，顺势完成悬念揭晓及直播预告。网友可通过点击话题词进入话题页，并在置顶位置看到天猫小黑盒官网的详细内容，从而完成传播信息的反复透传。 第一天预热环节的集中爆发，成功将大众期望值拉到了最高，为第二天的悬念揭晓加足了戏码。在第二天的悬念揭晓过程中，通过话题头像和导语自动承接的形式新鲜有趣，前后呼应形成闭环，有惊喜有惊讶，极大加深了大众对小“嘿”盒的记忆度，引发大量网友前往天猫小黑盒官微打卡。 天猫小黑盒HEYLIVE新直播巧妙利用试探性的social方式，成功预热营销盛典，得到了亿万级曝光量的同时，更让小黑盒神秘、有趣的品牌调性深入人心。",
      "main_image": "https://oss.adquan.com/upload/20210316/1615875100903516.jpg",
      "images": [
        "https://file.adquan.com/uploads_img/v76u91615874162.png",
        "https://file.adquan.com/uploads_img/yv9su1615874162.png",
        "https://file.adquan.com/uploads_img/rpcx21615874789.png",
        "https://file.adquan.com/uploads_img/to84x1615874759.png",
        "https://file.adquan.com/uploads_img/7zxyv1615874759.jpg",
        "https://file.adquan.com/uploads_img/nhc2q1615874841.png",
        "https://file.adquan.com/uploads_img/62n9i1615874841.png",
        "https://file.adquan.com/uploads_img/sj6zp1615874841.png",
        "https://file.adquan.com/uploads_img/ve92w1615874841.png",
        "https://file.adquan.com/uploads_img/yxe1v1615874883.png",
        "https://file.adquan.com/uploads_img/95qub1615874883.png",
        "https://file.adquan.com/uploads_img/krzj21615874920.gif"
      ],
      "author": "淘宝天下",
      "publish_time": "2021-03-16",
      "brand_industry": "互联网",
      "activity_type": "影视",
      "location": "中国大陆",
      "tags": [
        "魔性",
        "内容营销"
      ]
    },
    {
      "case_id": 325964,
      "score": 4,
      "score_decimal": "8.4",
      "favourite": 13,
      "company_name": "Jissbon 杰士邦等2家公司",
      "company_logo": "https://oss.adquan.com/logo/20140114121534_17869_320.png",
      "thumb": "https://oss.adquan.com/upload/20230517/1684310554090148fdf67b8749.png",
      "source_url": "https://m.adquan.com/creative/detail/325964",
      "title": "杰士邦：爱的关键时刻，男人都在想什么！",
      "description": "520将至，杰士邦为添加液态苯佐卡因的「持久」系列拍了部广告片。 为爱鼓掌时，男生却慢慢闭上了眼睛，此时TA的脑袋里在想什么呢？ 是篮球姿势？ 是广播体操？ 还是眼前的她？ 怎么脑海里面什么都有…… 其实不用想这些来分散注意力，专心去爱，持久的事交给杰士邦就好！ 此外，杰士邦还限量发售杰士邦×FATKO「花式想你持久礼盒」，内含避孕套+FATKO限定周边（花盆+随机种子）。",
      "main_image": "https://oss.adquan.com/upload/20230517/1684310554090148fdf67b8749.png",
      "images": [
        "https://file.adquan.com/uploads_img/16843107342h7nt.jpg",
        "https://file.adquan.com/uploads_img/1684310734so025.jpg",
        "https://file.adquan.com/uploads_img/1684310778glxn2.jpg"
      ],
      "author": "永刚",
      "publish_time": "2023-05-17",
      "brand_industry": "快消品",
      "activity_type": "影视",
      "location": "中国大陆",
      "tags": [
        "杰士邦",
        "避孕套"
      ]
    },
    {
      "case_id": 40298,
      "score": 4,
      "score_decimal": "7.1",
      "favourite": 12,
      "company_name": "BETC 巴黎 法国",
      "company_logo": "https://oss.adquan.com/logo/20170509174423_79108_320.png",
      "thumb": "https://oss.adquan.com/upload/20170308/1488954003360239.jpg",
      "source_url": "https://m.adquan.com/creative/detail/40298",
      "title": "三八妇女节别人家都在玩促销，这家公司居然把发言权做成了一个APP",
      "description": "文/Saber 正值女生和女神节之日，当我们还在为各种女神撸段子的时候，另一个半球的同类已经撸出了一款为平等发声的APP。 你有没有听说过“Manterruption”？这个词来源于当女性在说话的时候，男性毫无意义以及毫无必要的强行打断女性的发言。女性在发言的时候被无理的打断，这种事发生在任何场合任何时间。 这个名为“Woman Interrupted”的APP，为女性而生，这个APP通过录音对话，分析对话中女性被打断了多少次。 以及非常有调性的一组海报。 “All voice are born equal.”",
      "main_image": "https://oss.adquan.com/upload/20170308/1488954003360239.jpg",
      "images": [
        "https://oss.adquan.com/upload/20170308/1488953440854511.jpg",
        "https://oss.adquan.com/upload/20170308/1488953493375445.jpg",
        "https://oss.adquan.com/upload/20170308/1488953513115623.jpg",
        "https://oss.adquan.com/upload/20170308/1488953525609932.jpg",
        "https://oss.adquan.com/upload/20170308/1488953535432351.jpg",
        "https://oss.adquan.com/upload/20170308/1488953582915673.jpg",
        "https://oss.adquan.com/upload/20170308/1488953604836471.jpg",
        "https://oss.adquan.com/upload/20170308/1488953620737906.jpg",
        "https://oss.adquan.com/upload/20170308/1488953642223368.jpg"
      ],
      "author": "庄何丽",
      "publish_time": "2017-03-08",
      "brand_industry": "政府、非盈利机构",
      "activity_type": "平面",
      "tags": []
    },
    {
      "case_id": 314978,
      "score": 4,
      "score_decimal": "8.9",
      "favourite": 22,
      "company_name": "W ",
      "company_logo": "https://oss.adquan.com/logos/1658829041262877.jpg",
      "thumb": "https://oss.adquan.com/upload/20220502/1651498330343500.jpg",
      "source_url": "https://m.adquan.com/creative/detail/314978",
      "title": "2022·别再放我鴿子 by 溫哥華中文電台 + W 公益",
      "description": "咕...咕...咕，俺乃鴿中白話者也。 壬寅新春，羽下膘肥，展翅高飛。 一鴿如油膩而不自覺，與人又何異。 奮力西渡，落咗基輔月台，睇見冚家老少。 吾問：「此貴國春運啫？」 客答：「春運你老母，吾等今只求復國，不使復歸。」 借道南飛，見維港而降，爪落李小龍肩。 自忖：「我眼裡睇不到敵人。」 自揣：「何止無敵人，路人也無哂， Bruce，神人珍重。」 更向東去，有寶島孤懸。 內唱：「明天該去哪？」 外合：「回家。」 返咗上海野狗窩，身邊親友皆囿於疫情. 苦如頓巴斯，冷似維港，孤比綠島... 是夜，感悟成歌，遂唱與溫哥華鴿友， 友邦鴿友察而覺之：「呢個鴿歌係咩道理？」 白鴿默然，一旁野狗笑而歌道： 「無非尋常家禽，如何放過人間。」 「我都仲未放 過自己， 尚輪不到誰未來放我鴿子，知咩？」 「来，和野狗一起唱」 《2022·别再放我鴿子》 W#唱俾未來廣告嘅歌#第廿二季 by W野狗音樂艙 我這小鴿子 遠走他方 飛到頓巴斯 I am a little pigeon. Fly far away to Donbas 煙處處升 火處處燃 人比螻蟻輕 The smoke and fire of war Rises into the sky, burning everywhere Human’s life is lighter than that of ants 點解这天空 遮掩 這哭泣地面 Why the sky to cover up This weeping earth 我拼命爭脫 宿命 炮彈落下烽煙 I'm struggling to get out of my fate Cannonballs fall and raise smoke 我這小鸽子 飛獅子山 飛不過維港 I am a little pigeon, fly to Lion Rock Can not fly over Victoria Harbour 密密的大樓 空空的街上 人隔離家中 Crowded buildings, empty streets They are isolated at home 點解这天空 空虛 病毒似無邊 Why the sky is emptiness The virus seems boundless 我戴著口罩 希望 等日出東方 I'm wearing a mask Looking forward to the eastern sunrise 我這小鸽子 飛經寶島 作中場休息 I am a little pigeon Fly past the treasure island Take an intermission 睡夢之中 卻被驚擾 不能再停留 I was disturbed by accident in my sleep Can't stay here any longer 點解这天空 辜負 逐我似根草 Why the sky betray me Abandon me like a blade of grass 一樣的五官 樣貌 本是同根生 We have the same features We have the same ancestor 從今以後 別再放我睇 Don't let me take a glance from the very today 疫症里偷生 世界再美都也無用 No matter how beautiful the world is It has nothing to do with me Who spent time on pandemic 從今以後 別再放我聽 Don't let me hear from the very today 炮聲隆隆 蓋过教堂響起鐘聲 The sound of the cannons Drowned out the church bells 從今以後 別再放我飛 Don't let me fly from the very today 亂世太紛擾 好想天光終於來到 The troubled world is too turbulent I want the light come finally 從今以后 伴我再遠飛 Fly with me from the very today 定遠走高飛 飛到那裡總會遇到 We must fly far away Fly to somewhere we will meet someday 飛到未來 翅膀如舊長在我身 Flying into the future The wings still grow on me 願不再有一處天空 I wish there was no more sky 能阻我高飛 That could stop me from flying high",
      "main_image": "https://oss.adquan.com/upload/20220502/1651498330343500.jpg",
      "images": [
        "https://file.adquan.com/pic/165149448391be53597f28e2b1.jpg",
        "https://file.adquan.com/pic/165149448395a678158b19548d.jpg",
        "https://file.adquan.com/pic/16514944841b840f91a82d9081.jpg",
        "https://file.adquan.com/pic/1651494485c68199efaeb39c46.jpg",
        "https://file.adquan.com/uploads_img/16514964034a2wr.jpg",
        "https://file.adquan.com/pic/16514944866d3821997458cf20.jpg"
      ],
      "author": "W",
      "publish_time": "2022-05-02",
      "brand_industry": "互联网",
      "activity_type": "影视",
      "location": "中国大陆",
      "tags": [
        "公益",
        "情怀"
      ]
    },
    {
      "case_id": 313927,
      "score": 4,
      "score_decimal": "8.2",
      "favourite": 14,
      "company_name": "bilibili 哔哩哔哩",
      "company_logo": "https://oss.adquan.com/logos/1523428957886590.png",
      "thumb": "https://oss.adquan.com/upload/20220325/1648198733dc5f11ae487bea9a.png",
      "source_url": "https://m.adquan.com/creative/detail/313927",
      "title": "B站和传说中的宛平南路600号合作了？！",
      "description": "近日，B站宣布与宛平南路600号开启合作，并发布了一支宣传视频。 视频末尾字幕显示“在这个世界里，你并不孤单。我们愿意，也期待着，给你一个温暖的怀抱”，这也是B站收集自身平台的数据，从发现到主动反馈，给用户的属于平台的温暖社会关怀。 其实，宛平南路600号是上海市精神精神中心，也是全国最大的精神卫生机构之一。自B站2019年成立“能量加油站”以来，有超过10万人在这里倾诉自己的心事和烦恼。视频中介绍本次合作，请来了专业的心理医生，并接入了上海市心理热线，希望从专业角度科普心理健康知识，为有需要的小伙伴提供心理疏导。",
      "main_image": "https://oss.adquan.com/upload/20220325/1648198733dc5f11ae487bea9a.png",
      "images": [
        "https://file.adquan.com/uploads_img/hiv3r1648198676.jpg"
      ],
      "author": "Annabelle",
      "publish_time": "2022-03-25",
      "brand_industry": "互联网",
      "activity_type": "影视",
      "location": "中国大陆",
      "tags": [
        "B站"
      ]
    },
    {
      "case_id": 337880,
      "score": 5,
      "score_decimal": 10,
      "favourite": 23,
      "company_name": "SKECHERS 斯凯奇等4家公司",
      "company_logo": "https://oss.adquan.com/logo/20170227181901_14192_320.png",
      "thumb": "https://oss.adquan.com/upload/20231122/1700648063446186.jpg",
      "source_url": "https://m.adquan.com/creative/detail/337880",
      "title": "案例 | 与Z世代交朋友，斯凯奇走出会员焕新全链路",
      "description": "IP作为一种情感连接的符号和文化体系，具有从精神上链接消费者和品牌的天然优势，借助流行IP自身的吸引力，为品牌提供丰富的内容输出和互动方式，从而有效拉近品牌与受众的距离。类似IP联名案例相信大家都能如数家珍，娓娓道来， 但品牌自有IP全链路呢？ 在品牌达到一定知名度后，只有真正留下来的用户量不断增加，才能提升营销效果及降低营销投入，提升复购和转化，实现长效运营形成真正的降本增效。 因此：流量是平台的，只有会员（留量）才是品牌的！ 所以本次项目我们从一开始即锁定目标： 盘活现有沉睡用户问题。 在Brief前期我们从品牌方了解到，斯凯奇会员资产高达千万级，且以18~29岁女性用户为主，Z世代浓度极高，但由于缺少会员连接纽带，产生了数量庞大的沉睡会员。 而面对坐拥极具消费力的Z世代，我们是何做到一步步唤醒TA们，并使之成为全新的增长引擎？ Z世代，一届热情活跃且充满消费力的群体，他们进寺庙上香、淄博赶烤，善于分享并拥有无尽创造力。 他们身上或多或少有专属于时代的二次元ACG文化气息，热爱收集手办及愿意为IP埋单。 而Z世代对二次元文化的热衷，让虚拟IP成为各大品牌为年轻消费者打造的新宠。 因此，斯凯奇“会员虚拟IP”成为了我们为品牌进入Z世代圈层的“社交钥匙”，以“次元破壁”加速品牌全圈层渗透效率，同时使品牌焕发新的活力。 人人都会做IP，斯凯奇会员虚拟IP到底有什么不同？ 品牌自有IP设计需要把握唯一性原则，让消费者在了解IP的同时能产生直接的品牌联想。所以，我们选择了品牌经典爆款产品——熊猫鞋，并结合了讨喜的国宝级动物“熊猫”，以其外表毛茸茸的特征，从视觉上带给用户舒适感的印象。 塑造个性（人设）是打造独特形象的重要方式之一，树立鲜明的IP人格个性能更大程度上引发消费者情绪共鸣。 在斯凯奇IP搭建初期，我们运用DISC性格模型为IP塑造了多样化的人格个性，使其更生动，同时也让会员产生自我代入的共鸣感。 拥有开放的创意空间是品牌自建IP的核心优势之一。 为了让IP更好融入电商平台，我们在设计过程中紧扣运动出行的产品消费场景，并结合IP不同人格化性格，根据不同会员群体量身打造了四个相匹配的IP概念创意。 整个IP打造的过程就是一场自我迭代与进化的过程。我们通过不断完善细节，赋予虚拟IP更多更细腻的质感和造型特征，从1.0 - 2.0，从2D - 3D，从静态 - 动态。斯凯奇IP如同孩子般在滋养中逐渐成长，从懵懵懂懂到最后栩栩如生，活灵活现地来到消费者身边。 天猫作为商家会员用户存量和活跃程度最高的平台之一，平台中1000万名+会员的品牌接近50家，且部分品牌50%成交额都来自会员。 因此天猫成为了我们选择落地斯凯奇会员IP的首个平台战场。 通过一系列的互动营销玩法，让品牌IP率先在天猫引爆。 升级全新的斯凯奇天猫会员中心，搭建会员与IP的互动平台，持续激活TA与品牌互动。利用会员工具为不同等级的用户，提供了一键领取3D身份入口，并匹配其会员级别，提供对应的适配产品。 让会员可自由“穿搭”爆品，打造自己专属的斯凯奇会员形象，大幅提升TA们对品牌产品的感知。 结合当代年轻人爱追星、露营、滑板刷街等高频兴趣点，借势打造品牌代言人同款、滑板女、露营男等等 限定款的斯凯奇虚拟IP会员形象盲盒。 利用积分体系，以Z世代喜爱的互动游戏、积分换购、专属形象DIY等互动，刺激会员进阶升级，盘活用户活跃度。 会员作为新一轮的生意增长引擎，不仅需要盘活沉睡用户，同样需要引入更多的“新鲜血液”！ 依靠天猫品牌会员日，站外全平台曝光，明星流量加持，站内承接流量，强化活动商品及互动内容。斯凯奇熊猫IP再次席卷全网引发热议， 也使得品牌IP与TA产生深入互动，将TA引入会员池内，转化为新血会员。 斯凯奇核心会员人群热衷于表达自己的喜好，并且是一个具有强社交属性的群体。 为了让熊猫IP与会员用户有更多的接触和互动， 品牌从快闪店、跨界联合、会员活动，进行上线下融合的营销策划 ，全面活化用户资产，让存量用户再次成为品牌增长的高效流量。 熊猫IP进驻线下门店，成为线下门店会员“招募大使” 熊猫IP走进10大高校，线上跨平台宣发种草引发争相打卡 联合得物APP，打造#斯凯奇气泡熊猫鞋#线下会员嘉年华 以熊猫IP撮合线下商场门店，展开多主题线下会员活动 联动全域全链路，打造线上到线下流量引入及存留。 原象i2mago&斯凯奇会员营销案带动全域会员 招募84万 、创造 会员GMV贡献7.5亿 、收获全域曝光破亿的高光战绩，并在618大促中促使活跃会员 较同行提升83.15% ，会员客单大幅提升。 该案获得2023年金投赏「商业创意奖」 电商服务组全链路整合营销赛道铜奖 在当下营销环境变化巨大，流量红利消失，品牌纷纷转向存量用户要增长的同时，唯有充分洞察人群特征，不断精细化运营管理。使流量成为品牌留量，赋予客户人群更多情感价值，方为致胜秘诀。",
      "main_image": "https://oss.adquan.com/upload/20231122/1700648063446186.jpg",
      "images": [
        "https://file.adquan.com/uploads_img/1700647561n3f9k.gif",
        "https://file.adquan.com/uploads_img/1700647628mwgyo.png",
        "https://file.adquan.com/uploads_img/1700647652pn57d.gif",
        "https://file.adquan.com/uploads_img/1700647675xceku.jpg",
        "https://file.adquan.com/uploads_img/1700647698ywdec.png",
        "https://file.adquan.com/uploads_img/1700647748qlech.gif",
        "https://file.adquan.com/uploads_img/1700647798vxa5s.png",
        "https://file.adquan.com/uploads_img/1700647823eujlk.png",
        "https://file.adquan.com/uploads_img/1700647834c3bfe.png",
        "https://file.adquan.com/uploads_img/17006478556g5y9.png",
        "https://file.adquan.com/uploads_img/1700647888brnfc.png",
        "https://file.adquan.com/uploads_img/1700647910lzmbg.png",
        "https://file.adquan.com/uploads_img/1700647936x7flc.png",
        "https://file.adquan.com/uploads_img/17006479592sil4.png",
        "https://file.adquan.com/uploads_img/1700647960gx6dr.png",
        "https://file.adquan.com/uploads_img/17006480234n5pf.jpg"
      ],
      "author": "原象 i2mago",
      "publish_time": "2023-11-22",
      "brand_industry": "快消品",
      "activity_type": "整合营销",
      "location": "中国大陆",
      "tags": [
        "爆款",
        "内容"
      ]
    },
    {
      "case_id": 347825,
      "score": 4,
      "score_decimal": "7.5",
      "favourite": 8,
      "company_name": "海尔电器等2家公司",
      "thumb": "https://oss.adquan.com/upload/20241113716ff6d21c6e9ba7.jpg",
      "source_url": "https://m.adquan.com/creative/detail/347825",
      "title": "海尔电视海外营销：#CheeringForTheBigMoments",
      "description": "尽管全球电视市场整体销量呈现疲软态势，但2024年高端电视市场却逆势而上，预计将迎来稳健的个位数增长。特别值得一提的是，75英寸及以上的大屏和超大屏电视细分市场，据Sigmaintell预估将实现38.9%的显著增长。这一趋势表明，大屏电视已成为电视制造商争夺的焦点领域。 自今年6月起，赞意增长网络荣幸成为海尔电视海外营销的首席合作伙伴，肩负起为客户制定全球统一产品营销策略和内容的重任。我们面临的首要任务是应对大屏电视市场的营销挑战，同时把握全球观众瞩目的6至8月体育盛事这一黄金时机。 为了协助海尔电视以大屏产品为媒介，加强与海外消费者的情感链接，并提升品牌认知和认可，同时在面对不同营销能力和观众需求的海外市场时，实现“Glocal”（Global+Local）的营销策略，我们协助海尔电视海外营销的客户，在总部层面进行了策略性的工作： 在体育赛事的舞台上，无论是足球的破门瞬间、板球的得分高潮，还是游泳的触壁一刻、跑步的终点冲刺，最令人心潮澎湃的莫过于那些创造历史的“大时刻”。The Big Moments，正是这些瞬间的代名词。而海尔的75英寸及以上大屏电视——The Big Screen TV，正是将这些激动人心的Big Moments情绪推向极致的理想选择。 我们协助海尔电视海外营销推出了#CheeringForTheBigMoments，大屏电视营销口号及相应的营销内容与活动，不仅传递了海尔大屏电视的品牌精神，还激发了全球观众对于体育激情的共鸣，让每一个家庭都能通过海尔大屏电视，感受到仿佛身临其境的震撼体验。 （赞意基于海尔电视海外营销素材进行剪辑、文案撰写等，在体育季开始前迅速输出campaign启动物料） 、 （海尔区域市场基于campaign planning中的创意角度，持续输出本地相关内容） 体育赛事之外，大屏电视的营销主题同样展现出强大的延展力。毕竟，生活中值得庆祝的“大时刻”远不止于体育场上。节假日，作为家庭团聚、朋友欢聚的重要时刻，同样承载着无数温馨和喜悦，它们也是不容错过的Big Moments。 （海尔区域市场基于campaign planning 中的延展角度，持续输出本地相关内容） 消费者在酒吧、餐厅观赛是体育季最常见场景之一，这些地方也是最需要大屏电视的场景。因此，我们在campaign策划中，提出了一个创新的想法——与海外市场当地知名的运动餐吧合作，为它们的电视进行大屏升级。通过这种方式，我们能够将海尔的大屏电视直接带入这些观赛热点，让球迷们在享受美食和饮品的同时，也能享受到更加清晰、生动的比赛画面，同时，我们更能构建一个品牌与当地社区的长期关系，能让当地社区热爱体育的消费者们在整个体育季中都尽享大屏带来的震撼体验！当然，在对当地市场重要的比赛日，海尔也将优先合作体育餐吧举办相关品牌活动，邀请海尔员工、海尔 fan club 粉丝等一起线下观赛。 在越南市场，我们辅助总部团队与当地团队的紧密合作，成功将这一想法落地。我们不仅关注活动物料、流程的设计，还确保各项规范与当地文化和市场需求相契合。 （海尔电视AQUA品牌越南线下消费者营销活动） 除了全球性的重点营销活动，赞意增长网络还为海尔电视的海外营销团队提供全方位的支持，凭借敏锐的市场触觉和创新思维，为海尔电视的海外营销提供了强有力的策略与创意服务。 赞意增长网络海外营销业务服务范围涵盖： · 海外产品品牌营销策略 · 海外营销内容创意制作 · 海外媒体KOL传播策略与沟通 · 海外社交媒体运营管理 · 海外线上舆情监测、洞察与分析 我们热忱期待服务更多寻求国际市场突破的客户，以快速响应的服务和富有洞察力的创意策略，为中国企业的全球化征程提供坚实的支持与护航！",
      "main_image": "https://oss.adquan.com/upload/20241113716ff6d21c6e9ba7.jpg",
      "images": [
        "https://file.adquan.com/uploads_img/17314928799m254.png",
        "https://file.adquan.com/uploads_img/1731492914gcore.png",
        "https://file.adquan.com/uploads_img/173149293869jnm.png",
        "https://file.adquan.com/uploads_img/1731492965yix04.png",
        "https://file.adquan.com/uploads_img/17314930206zrlt.png"
      ],
      "author": "赞意",
      "publish_time": "2024-11-13",
      "brand_industry": "家居、家电",
      "activity_type": "影视",
      "location": "中国大陆",
      "tags": [
        "海尔",
        "海外营销"
      ]
    },
    {
      "case_id": 320142,
      "score": 5,
      "score_decimal": "9.0",
      "favourite": 29,
      "thumb": "https://oss.adquan.com/upload/20221109/16679905581cd343e3bb1e0c78.png",
      "source_url": "https://m.adquan.com/creative/detail/320142",
      "title": "这是今年最“大牌”的圣诞广告！",
      "description": "这是今年最豪华阵容的一支圣诞短片了吧！ 《冰川时代》导演Michael Thurmeier以及广告导演Yves Geleyn执导，格莱美创作歌手Colbie Caillat演唱。美国商超巨头Kroger的这部圣诞电影《The Magical Cookbook》（神奇的食谱），不同于其他品牌的圣诞欢庆，制作了一支伤感动画，演绎怀旧情绪。 食物总是有种非凡的魔力，能诱捕我们的感官，无论多久远，只要品尝到，就会打开记忆的闸门，引发回味。短片以“魔法食谱”为背景，祖父偶然发现了他已故妻子的食谱，并尝试着做了一些菜。当他每次品尝后，都会回顾起和妻子在一起时的美好记忆。圣诞，当他准备品尝刚出炉的烤鸡时，孙女拦住他，指着食谱上的“enjoy with family“（与家人一起享受）。 电影结束，日记本上浮现“Today‘s holidays are tomorrow’s memories”（今天的假期是明天的回忆），也是Kroger想要表达的假日理念： 与家人的节日聚餐，创造美好的回忆。 “我们中的许多人都非常兴奋地谈论我们自己的家庭食谱——从我们保存破烂的手写食谱卡到传给我们的‘古老’食谱书。”Kroger品牌营销高级总监 Emily Hartmann 在一份声明中说，“我们都有独特的故事要讲述，节日食物的强大，能让我们和所爱的人一起享受生活中最快乐的时刻，并和新一代一起创造更多回忆。”",
      "main_image": "https://oss.adquan.com/upload/20221109/16679905581cd343e3bb1e0c78.png",
      "images": [],
      "author": "Emily",
      "publish_time": "2022-11-10",
      "brand_industry": "商超、贸易",
      "activity_type": "影视",
      "location": "其他地区",
      "tags": [
        "圣诞",
        "圣诞"
      ]
    },
    {
      "case_id": 335905,
      "score": 4,
      "score_decimal": "8.4",
      "favourite": 17,
      "company_name": "SG 胜加",
      "company_logo": "https://oss.adquan.com/logos/1560156822903650.jpg",
      "thumb": "https://oss.adquan.com/upload/20230908/1694168055709018.png",
      "source_url": "https://m.adquan.com/creative/detail/335905",
      "title": "【胜加答案】｜一个寻找并收获确定的故事",
      "description": "每个提给胜加的问题，都有「胜加答案」。 该栏目将立足胜加出品的案例，由主创团队复盘项目、回应问题、总结经验，带你回味一个优质作品落地成型的全过程。 如果通读完幕后故事，心头仍有几分好奇，欢迎到评论区写下你的问题。我们会细细品读每一条留言，邀请胜加的团队负责人亲自回复。对于行业性深度话题，后续也将形成有价值可复用的方法论，回馈行业。 看，这是我们的答案。 ---- 上周，由胜加洞见团队为专业户外品牌可隆打造的 《有故事 才是自然的事》 案例上线后，我们收到了一些有趣的回复和讨论： 分享人 Q1： 之前可隆在国内市场的广告较多侧重产品层面，这次则站在更高维度提出了一种有关户外生活方式的价值主张，背后的契机是什么？接到brief时，团队又是如何理解客户的商业需求？ 可隆此前的传播已经从产品端把 “Your best way to nature” 讲得很透，在50周年之际、同时也是户外热潮的大背景，我们希望用 更品牌端的价值观 去陪伴消费者，让他们以自己的方式进入到自然——因为在自然里，消费者需要的不止是一件防风防水的衣服，更是品牌能给人带来的、无论什么自然环境下都能应对的底气。 可隆希望能与更多人一起深入自然，但难就难在 目标客群并不单一 ：我们想要共鸣那群深入山野、沉浸式户外的玩家，也想要吸引那些浅浅露营一次甚至还没踏出门的普通消费者。很显然，对于这两者，要讲的话并不能完全统一。 Q2： 你们对户外生活方式的认知是怎样的，深度参与了本次项目后，会产生一些变化吗？ 团队里有同学自己本身就很喜欢大自然，也玩点户外，周末基本上都在山里或者是河边度过。对我们来说，户外成瘾，是因为它是一种更经得起深思熟虑的生活方式，万事万物的魅力会被放大，在自然中习得知识的过程其乐无穷…… 有的人童年就是在自然里生长起来的，工作求学以后离户外和自然的生活方式已经很远了，但也希望“童年的纸飞机重新飞回我手里”，所以遇到这个项目我们都很兴奋，特别是客户团队也希望能 向大家传递自然的真实魅力，而不是营造消费热潮。 当然，我们的个体体验也还只是一些切面。随着项目的开展，我们和十几位露营玩家聊了聊，大家参与的深浅不同，但各有各的乐趣。给我们最直接的感受是 一种近乎乌托邦的包容： 自然属于每一个人，你可以“在不破坏自然和他人体验的前提下尽情做自己”。 Q3： 前期策略团队进行了哪些市场和人群研究？和我们分享一些有趣的/印象深刻的发现吧。 因为这次核心目标市场是以上海为中心的南方，所以我们跑去上海和一些当地玩家聊了聊，他们有的腼腆、有的开朗，有的已经玩得很深入、有的初尝露营的乐趣。我们问的问题不算好回答，每次问到“户外/露营哪里吸引你”往往都会经历几秒的沉默，吸引点太多了、好像又很难转化成语言，这种时候他们大多会说出同一句话——“你去了就知道了”。 于是我们期待从那些“去了才会知道”的事里，找到洞察。 在受访者的叙事里，美景、登顶、日出自然是美好的事，但也另有一件事让全员眼睛发光、津津乐道——那就是各种始料未及的bug。bug能有什么魅力？ 比如A给我们讲，人生不是野生，不可能一去什么都会，大家都是在实践当中慢慢学的。她在麦理浩径露营时，晚上遇到野猪拱脚，还偷吃。惊吓之余才意识到自己来到了什么都可能发生的自然，也没必要生气，只是学着把包挂在树上。有经验了，历经一次又一次的成长，变得越来越娴熟。 Q4： 「有故事才是自然的事」这句话怎么产生的？ 这个社会对我们的容错率很低，大家一遇到问题和意外就容易“心态崩了”。其实自然里不确定的事更多，各种天气、环境不会按我们的意愿来，但自然里的这些“事故”，换个角度看就是故事了，所以视角很重要，心态也很重要。 有事才有故事，这一鼓励大家拥抱bug的洞察被我们内部简称为 “bug but buff” 。既可以助力品牌建立有锐度的认知，也便于传播时激发大家分享自己的“故事”，我们都还挺喜欢的。 Q5： 从策略洞察到品牌主张的确定，是一件水到渠成的事情吗？ 看似水到渠成，其实项目途中挖了不少渠，逐一尝试只求最好。 Q6： 三位艺人、三个“不确定”的户外故事，为什么会这样设计？ 我们从目标人群身上洞察到了三种焦虑，分别是互联网大厂人常见的 职场焦虑 、422家庭人群会有的 家庭焦虑 、年轻群体中普遍存在的 人设焦虑 。基于这三个焦虑，我们分别选择了陈坤、贾静雯、管泽元，让他们结合各自的真实故事与感受，通过在自然里经历各种不确定，最后以收获的感悟给出一种答案。 Q7： 把品牌要表达的观点进行创意转化、把故事讲给更广泛的消费者，创意对此做了哪些思考？ 我们想表达的观点就是 对自然祛魅，不过度去美化它。 所以在创意手法上选择了去广告化、有纪实感的“半采访式”纪录片形式。 Q8： 据说拍摄执行时间非常紧张、团队也集体被大自然“虐”了，想听听背后的精彩故事&如何保质保量完成任务的心路历程~ 可能正是应了“有故事才是自然的事”，我们立了的flag终究要我们自己去完成。 在大山里一边拍摄一边躲雨，好在演技在线、金句频出的陈坤老师给了大家信心； 项目能够保质保量如期上线，更离不开客户和后期团队的共同努力，正是他们让我们觉得前期被大自然“虐”的那些经历都值了！ Q9： 看到有媒体评价说，可隆本次品牌传播所传达的思考，是“对市场流行观点的升级与颠覆”，你们觉得呢？ 这次项目其实也是对疫情后的露营热和户外现象的总结式观察。 有几件事情让我们受到了触动，一方面是不少博主都在高呼生活无解自然撒野，吸引了很多人重新认识自然、参与户外活动，这无疑是有一定积极意义的；而另一方面，则是不少浅尝露营的消费者大呼“上当”。 户外市场亟需打破幻想、走出热潮，引导人们 更谨慎而深入地认识自然、思考人在自然中的存在方式。 陷入沼泽了怎么办？零食被野猪拱了怎么办？前方有岔路怎么办？自然给了我们一个美妙的双关——没有事情完全受到我们的掌控，万事总会出岔子，但当我们走上了岔路，要怎样应对眼前发生的事，则会决定我们的幸福感。 当许多人都在贩卖“治愈”和“拥抱”，暂时的逃离没法给任何人一个交代。正像我们访谈时一位户外玩家所说，“回到日常还是会焦虑，大自然解决不了任何问题”。说到底，解决问题、或者至少改变视角看问题的，只会是我们自己。 如果我们能在自然里（在谨慎和安全的前提下）允许 bug 发生、或依靠自己解决问题， 把岔路也走成一条新路，那我们也终将以一种真正的“松弛感”获得日常生活的幸福。 而懂得这一点的可隆，将以专业的户外背景与对消费者需求的体恤为你提供各种支持，成为你开启山野故事的忠实见证者。 ○ 最后，请大家介绍一下自己以及你们所在的团队吧~ 一个由年轻人和更年轻的人组成的、又低调又新锐的团队，组里充斥着吃货、剧本杀大佬、KTV毒瘤、摇滚乐手和猫猫党。然而每当谈起工作时，扎实的基本功、丰富的经验和过硬的专业能力，又令人在违和之中感受到异常踏实。 平衡策略与创意，既负责放飞，也负责落地。 核心特点：年轻、专业、反传统。",
      "main_image": "https://oss.adquan.com/upload/20230908/1694168055709018.png",
      "images": [
        "https://file.adquan.com/uploads_img/1694165225jh56n.jpg",
        "https://file.adquan.com/uploads_img/1694166260mahuz.GIF",
        "https://file.adquan.com/uploads_img/1694166545mh294.GIF",
        "https://file.adquan.com/uploads_img/1694166554txol8.GIF",
        "https://file.adquan.com/uploads_img/1694166563lao64.GIF",
        "https://file.adquan.com/uploads_img/1694167605uzs57.jpg"
      ],
      "author": "SG 胜加",
      "publish_time": "2023-09-11",
      "brand_industry": "互联网",
      "activity_type": "影视",
      "location": "中国大陆",
      "tags": [
        "广告",
        "户外"
      ]
    },
    {
      "case_id": 44320,
      "score": 4,
      "score_decimal": "8.4",
      "favourite": 15,
      "company_name": "Anomaly 非常创意 纽约 美国",
      "company_logo": "https://oss.adquan.com/logos/1525678947457627.jpg",
      "thumb": "https://oss.adquan.com/upload/20180509/1525854828cb04307f9a17a0b9.jpg",
      "source_url": "https://m.adquan.com/creative/detail/44320",
      "title": "受了超级碗的启发，百威要把黑科技用在世界杯了？",
      "description": "从圣路易斯带一瓶啤酒到莫斯科，想要保证理想质量的同时还要能够透心凉，对人类来说绝对是一项艰难的任务。但很显然，这项任务对无人机而言也是一场挑战。不过百威近期推出的TVC则以这样热血的方式预演了如何燃炸世界杯。 百威此次的营销活动围绕“FIFA世界杯的官方啤酒”展开。广告侧重于无人机，因近来该技术在体育场内运用越来越广，尤其要归功于超级碗，运用300台出自英特尔之手的无人机编队呈现灯光秀。而此次TVC中，百威连接人工智能与体育竞技，在2018世界杯上向尼日利亚、英国、中国、俄罗斯等各国球迷派送啤酒，打响“LIGHT UP THE FIFA WORLD CUP”的口号。 然而，其中一架无人机在工作上似乎不像他的同行那么熟练。被命名为“ Bud 1876”是因为这是百威啤酒第一次进行酿造的年份。画面中，这架无人机历经险阻努力挽回颓势，在Apollo 440发行于1999年的Stop the Rock歌声中找到了最终目标。 据悉，该广告是来自百威母公司百威英博的一次非常大的营销推广活动的一部分，该网站称此次活动为迄今为止规模最大。该支世界杯广告将在50多个国家和社交媒体渠道上播放。同时百威啤酒还将在全球范围内出货800多万百威啤酒红光杯。杯子点亮引发的声嘲将如同人们的狂欢。 “我们的竞选活动是我们公司历史上规模最大的一次，它展示了我们如何将来自世界各地的粉丝与啤酒及其对足球的共同热情聚集在一起，”百威英博集团首席营销官Miguel Patricio在一份声明中表示。“我们的活动捕捉了百威啤牌品牌的欢庆、热情和溢价特质，球迷们将继续通过我们为2018年世界杯开展的持续活动来看到这一点。”",
      "main_image": "https://oss.adquan.com/upload/20180509/1525854828cb04307f9a17a0b9.jpg",
      "images": [],
      "video_url": "http://v.qq.com/iframe/player.html?vid=p0647nqfux4&tiny=0&auto=0",
      "author": "house",
      "publish_time": "2018-05-09",
      "brand_industry": "快消品",
      "activity_type": "影视",
      "location": "中国大陆",
      "tags": [
        "百威",
        "2018世界杯"
      ]
    },
    {
      "case_id": 286480,
      "score": 4,
      "score_decimal": "8.6",
      "favourite": 8,
      "thumb": "https://oss.adquan.com/upload/20190730/1564463571889904ac022c0d6c.png",
      "source_url": "https://m.adquan.com/creative/detail/286480",
      "title": "官宣代言后，一加手机上线小唐尼首支广告",
      "description": "官宣合作后，近日一加手机又发布了由钢铁侠扮演者员小罗伯特·唐尼出演的一加7系列全新广告。 You have to have clarity, focus, vision. Never accept less than the best. 你必须目标明确，保持专注于远见，永不言弃，追求极致 不少粉丝都知道小唐尼非常喜欢咏春拳，并且练过多年，在同一加的合作广告中，也展示了一段。在行云流水的动作中，充分显示着其个人魅力。同时，将产品性能融入，展现了一加7 Pro的超高屏占比与升降式前置摄像头。 据一加创始人刘作虎透露，短片的脚本由小唐尼亲自创作，在复联上映之后一个星期（小唐尼最忙的时候），他自己在家里亲自写脚本，亲自做导演，来拍这支宣传片。 相关阅读： 厉害了！一加手机宣布小罗伯特·唐尼为品牌推广大使",
      "main_image": "https://oss.adquan.com/upload/20190730/1564463571889904ac022c0d6c.png",
      "images": [
        "https://file.adquan.com/uploads_img/bv92j1564464968.png"
      ],
      "video_url": "https://v.qq.com/txp/iframe/player.html?vid=i08719hg3qh&tiny=0&auto=0",
      "author": "Garbo",
      "publish_time": "2019-07-31",
      "brand_industry": "数码、通讯",
      "activity_type": "影视",
      "location": "中国大陆",
      "tags": [
        "一加手机",
        "小罗伯特·唐尼"
      ]
    },
    {
      "case_id": 316894,
      "score": 4,
      "score_decimal": "8.8",
      "favourite": 38,
      "company_name": "美团外卖",
      "company_logo": "https://oss.adquan.com/logo/20161221184810_42911_320.png",
      "thumb": "https://oss.adquan.com/upload/20220711/16575107016453895911cefad2.png",
      "source_url": "https://m.adquan.com/creative/detail/316894",
      "title": "美团外卖艺术拼贴广告，画风有点神奇……",
      "description": "美团又出新广告了?! 这次的画风很神奇，从各种各样的 [ Fěn ]、琳琅满目的 [ shuǐ ] ，到突破想象的 [ jī ]，在魔性洗脑般的节奏中，美团外卖向用户强势输出“美团外卖啥都有卖”的特点。 利用谐音，广告在细数众多物品的同时，能够形成押韵上头的节拍。此外，画面结合使用图像、印刷材料和实物等众多元素，创造出富有视觉冲击力的拼贴艺术，迎合了当代年轻人的审美偏好，有利于吸引他们的注意力。 但从内容本身来看，广告的可看性较弱。不过，这应该主要与品牌需求相关，为了给消费者留下深刻的印象，重复、洗脑的形式是最常见的一种，尤其是在注意力稀缺的年代。 对此，你的感受是什么？",
      "main_image": "https://oss.adquan.com/upload/20220711/16575107016453895911cefad2.png",
      "images": [],
      "author": "River",
      "publish_time": "2022-07-11",
      "brand_industry": "电商、零售",
      "activity_type": "影视",
      "location": "中国大陆",
      "tags": [
        "美团外卖",
        "拼贴艺术"
      ]
    },
    {
      "case_id": 349409,
      "score": 4,
      "score_decimal": "8.0",
      "favourite": 5,
      "company_name": "Pre.1极昼广告",
      "company_logo": "https://oss.adquan.com/logos/1686559260899160.jpg",
      "thumb": "https://oss.adquan.com/upload/202501170dcd68cb6e1bd7ae.jpg",
      "source_url": "https://m.adquan.com/creative/detail/349409",
      "title": "联想 X 大冰｜给每个回家的人，送上最实用的“2025开场白”",
      "description": "春节营销语境下，讲述回家故事、运用中国元素打造情感催泪弹，似乎成了众品牌的“传统节目”，如何才能跳脱传统，给出不一样的营销打法？ 在联想集团“ 人本智能 ”的核心主张下，答案应运而生：我们不做广告，而是回到现实，走进每一个普通人的心中。春运是中国每年最忙碌的时刻，也象征着家与归属。从这一刻起，大家的心开始走向家人，开始期待未来，我们希望抓住这个特别的时间节点，为人们提供实用而有温度的支持。 大冰与联想 AI PC 一起登台 2025 一场大型人间“连麦现场”，正在上演 经历了2024的我们，心中总留有一些不确定，身处正在飞速变化的大时代，如何把脚下的每一天过得更踏实、更安稳，也许才是大家最关心的话题。联想所倡导的科技发展理念“人本智能”强调以人的需求为中心，通过AI技术为人带来切实的便利。所以在1月14日—— 春运第一天，这个对中国人来说意义非凡的日子里，联想找到了2024年“暖上央视”的主播大冰，一起给陆续返回家乡的人们实在又温暖的嘱咐和鼓励。 *图片来源于网络素材 在烟火人间，大冰是站在每一个普通人身边的倾听者。无数场连麦中，他帮网友梳理遇到的问题，并给予暖心的建议和帮助。轻生少年在大冰的直播间因为一碗热干面燃起重生的希望；60岁的麦子奶奶因为大冰的支持，终于亲身感受到西双版纳的春天……这种真诚的互动方式，让他成为了2024年的现象级人物。正如大冰在书中写到的，“于无常处知有情，于有情处知众生。”这句话传递出深刻的人本关怀——无论是在人生的波动中，还是在人情的温暖中，我们都能感知到生命的真谛。正是这种温暖与共情，成为了大冰与联想集团合作的核心。 真诚，是永远的必杀技 这一次，大冰借助联想AI PC，把“直播间”搬到了真实的市井巷弄，和大家一起踏上回家过年的旅程。以薄荷绿乐队《直立行走》这首歌作为背景，温暖的曲调和充满能量的歌词，串联起了此时、此景、此情，正如歌中所唱的，“世界本没有路，一起开疆拓土”，每个人都用自己的行动，绘出了烟火人间中最动人的风景，这个过程中，大冰用真诚串联起属于你我的《2025开场白》。 影片从大冰的直播间引入，“马上过年了，该准备些什么呢？”当大家提出这个问题时，联想AI PC强大算力为他描绘出的了年前的众生相，大冰的直播间也成为了连接当下与希望的奇妙桥梁。 接着，大冰通过AI PC强大的算力，迅速描绘出过节前一幕幕生动的日常，在这些看似平常的瞬间，藏着每个人对新一年的期待与希望。故事随着大冰的脚步展开，一路上大冰看到了回家路上人们真实动人的瞬间，也送出了自己的嘱咐与鼓励。这其中涵盖了从过年回家前的准备，到过年回家后的方方面面。 楼梯上，帮着女孩提行李的保安，也提醒她把家里的闸关好。 过年回家，切记安全第一。 年轻夫妇带着心爱的狗子和成堆的年货，开启了过年回家的旅程。 期待了一整年，能与家人彼此陪伴的日子终于近在眼前。 茶馆里生意火热，老板忙着为顾客和员工分发过年红包。 谁说红包只属于小朋友，大朋友更需要好彩头！ 居民楼下，孩子们用剪纸搭起球门，一个个化身足球小将，一记远射，球进了！ 中国人踢足球也能踢来希望。 坚守在一线的工作人员，回不了家的时候。 与家人的远程连线，就成了心里最大的惦念。 大街小巷里，人们都在为过年准备着。 新的一年，每个人都有着自己奔赴的方向。 结尾，大冰结束了与AI对话后继续出发， 他带着对未来的无限憧憬，踏上了奔赴2025的旅程。 2025年，我们都在用自己的方式，写下属于自己的开场白。 而《2025开场白》，正是以一种温暖而真诚的方式，将力量传递给每个人： 不管过去怎样， 2025 ，带上希望登台，就是 2025 最实用的开场白。 大冰的经验，正是来自于每个人身边的智慧和故事。在他的眼中，每个人的生活，都是一段值得珍惜的旅程。影片通过温暖且贴近生活的细节，为大家提供了真正的帮助，而这些微小的举动正是我们对“人本智能”理念的完美诠释。 最后，送上来自大冰温暖又实用的 2025 开场白，总有一款适合你。 实在的贴士，给准备过年回家的你 “过年回家安全第一，闸都拉好了吗？冰箱的闸要留好哦。” “咱中国人讲究喜上加喜，带对象一起回家，给全家一个惊喜。但如果你今年独自跋涉，衷心祝你明年不再孤单。” “过年准备好胃口，好胃口，带来好福气。” 实用的嘱咐，给到了家的你 “致敬坚守一线的朋友们，祝你的手机不断电，和家人视频永远Wi-Fi在线。” “回家和妈妈聊聊天，陪爸爸看看电视，有质量的陪伴是最好的礼物。” “小朋友需要红包，大朋友也需要。有时候，大朋友更需要好彩头！” 2024 的付出，值得鼓励鼓励 “这一年，你过得好不好？撑了多久？扛住了多少？” “也许今年一般，但你咋知道明年不是一般的好？” “天底下不存在永远的失望，包括中国人踢足球。” “你看，人人都有转运时，事事都有转机处。” 2025 的期待，总会一一兑现 “做一点小小的调整吧，换一个吉祥的开始。” “生活像是对联，有了上联自然有下联。” “不论过去的一年，是苦是甜，是好是坏，只要还在歌唱，生活就有希望。” “新的一年，祝你过得好，如果不算好，要相信会好起来，不过是时间。” 和 2024 的自己说声辛苦了！ 新的一年，让我们带着这份希望与力量， 一起奔赴那个充满无限可能的未来吧！",
      "main_image": "https://oss.adquan.com/upload/202501170dcd68cb6e1bd7ae.jpg",
      "images": [
        "https://file.adquan.com/uploads_img/17370942409cdob.jpeg",
        "https://file.adquan.com/uploads_img/1737094387vt91y.gif",
        "https://file.adquan.com/uploads_img/17370944484jh9w.gif",
        "https://file.adquan.com/uploads_img/1737094529ygkrl.gif",
        "https://file.adquan.com/uploads_img/173709456978i0j.gif",
        "https://file.adquan.com/uploads_img/1737094615xoibq.gif",
        "https://file.adquan.com/uploads_img/17370946809f3kp.gif",
        "https://file.adquan.com/uploads_img/17370947463zja9.gif",
        "https://file.adquan.com/uploads_img/1737094786qragy.gif",
        "https://file.adquan.com/uploads_img/17370948401k6pc.gif",
        "https://file.adquan.com/uploads_img/1737094962u7x3y.jpg",
        "https://file.adquan.com/uploads_img/1737095012le9nq.jpg",
        "https://file.adquan.com/uploads_img/1737095017469jv.jpg",
        "https://file.adquan.com/uploads_img/17370950178tadg.jpg"
      ],
      "author": "Pre.1极昼广告",
      "publish_time": "2025-01-17",
      "brand_industry": "数码、通讯",
      "activity_type": "影视",
      "location": "中国大陆",
      "tags": [
        "春节",
        "温暖"
      ]
    },
    {
      "case_id": 341712,
      "score": 4,
      "score_decimal": "7.8",
      "favourite": 11,
      "company_name": "McDonald’s 麦当劳",
      "company_logo": "https://oss.adquan.com/logos/1727344407b40ad44aada194cf.jpg",
      "thumb": "https://oss.adquan.com/upload/20240327/1711525708ba15903e50cdece6.png",
      "source_url": "https://m.adquan.com/creative/detail/341712",
      "title": "麦当劳出相机了？又是一波抢购潮",
      "description": "就在今天，麦当劳官方发布了麦当劳即将推出限定款相机的消息，瞬间引起了广泛评论。 此次相机分为白色和橙色两款，相机上印有麦当劳招牌产品巨无霸和薯条图案。 值得注意的是，该款相机为限量款，共计限量8000份，且每份带有专属的金粉编号，相机售价168元+200麦当劳积分，周日下午2点开始抢购，预计将会在社交媒体上掀起抢购浪潮。 此前麦当劳还与与摄影 app「NOMO CAM」联合推出「麦当劳主题相机」系列，并推出了 22 款合作滤镜。 用户使用 NOMO CAM 拍摄麦当劳的「M」logo，就能解锁神秘款相机效果。 NOMO CAM 以模拟真实胶片相机的操作体验为特点，用户选择不同的相机滤镜，其快门、闪光灯、切换按钮的位置与样式都会有所不同。",
      "main_image": "https://oss.adquan.com/upload/20240327/1711525708ba15903e50cdece6.png",
      "images": [
        "https://file.adquan.com/uploads_img/17115251210zwpq.png",
        "https://file.adquan.com/uploads_img/1711525406n4w3t.png",
        "https://file.adquan.com/uploads_img/1711525619lto58.png"
      ],
      "author": "源泉",
      "publish_time": "2024-03-27",
      "brand_industry": "快消品",
      "activity_type": "影视",
      "location": "中国大陆",
      "tags": [
        "麦当劳",
        "富士"
      ]
    },
    {
      "case_id": 313922,
      "score": 4,
      "score_decimal": "7.7",
      "favourite": 14,
      "company_name": "ZARA 飒拉",
      "company_logo": "https://oss.adquan.com/logos/1528108522192626.jpg",
      "thumb": "https://oss.adquan.com/upload/20220325/1648195844e34d38c6bcab7882.png",
      "source_url": "https://m.adquan.com/creative/detail/313922",
      "title": "Zara 2022春夏系列，上演摩登与史诗大片",
      "description": "Zara联手奥斯卡提名得主,《犬之力》男二号Kodi Smit-McPhee演绎2022年度最新Studio男装系列大片《Mirage》（幻影），在约旦沙漠腹地上演了一场“诡异”的探险旅程。 Zara 通过此次Studio系列探索西方和波西米亚影响的交汇点，短片传递了强烈的流动性和温文尔雅的波西米亚主义。《Mirage》讲述了男主出现在一望无际的沙漠腹地，眼前出现的城堡像是海市蜃楼，走进有些诡异的城堡中，眼前的事物将他带进一个魔幻无序而多变的世界。 2022年男装开春系列，设计以运动装为主的更广阔的服装领域，以木炭色为基础，用棕色，深红色，灰色与芥黄色着重点缀。在剪裁合身和宽松流畅的廓形之间穿梭，营造出凝聚力的外观。而其女装系列则以美丽和浪漫为主题核心：针织提花、蕾丝、荷叶边、英格兰刺绣、雪纺和薄纱融合，纯白的背景下，油画般的美人跃然纸上，塑造了跨越时代的摩登风格。",
      "main_image": "https://oss.adquan.com/upload/20220325/1648195844e34d38c6bcab7882.png",
      "images": [],
      "author": "Emily",
      "publish_time": "2022-03-25",
      "brand_industry": "时尚、美妆",
      "activity_type": "影视",
      "location": "中国大陆",
      "tags": [
        "Zara",
        "时装秀"
      ]
    },
    {
      "case_id": 315834,
      "score": 4,
      "score_decimal": "7.1",
      "favourite": 18,
      "company_name": "平安银行",
      "company_logo": "https://oss.adquan.com/logos/1617930241253434.jpg",
      "thumb": "https://oss.adquan.com/upload/20220531/16539682555a4686d8d513254a.png",
      "source_url": "https://m.adquan.com/creative/detail/315834",
      "title": "平安银行这支广告，快“笑”不停了",
      "description": "笑声的感染力往往是最强的，它有着治愈人心的魅力。当你看到一支从头至尾都在微笑的短片时，你的心情会是怎样的？ 5月30日，平安银行信用卡发布短片《微笑加油 一路平安》，集合各种不同的微笑传递温暖，以感谢超过2500万平安车主们的微笑赞助。 没有夸张、幽默的剧情，它采用了很简单的立意。“无论生活如何，记得微笑面对”，通过满屏的微笑，用情绪感染去传递积极向上的生活态度。但有的时候，一千个人眼中有一千个哈姆雷特，有人会随之哈哈大笑，也有人会觉得面对不停的微笑，会有些尴尬。对此，你怎么看？",
      "main_image": "https://oss.adquan.com/upload/20220531/16539682555a4686d8d513254a.png",
      "images": [],
      "author": "River",
      "publish_time": "2022-05-31",
      "brand_industry": "金融、保险",
      "activity_type": "影视",
      "location": "中国大陆",
      "tags": [
        "平安银行信用卡"
      ]
    },
    {
      "case_id": 43993,
      "score": 4,
      "score_decimal": "8.2",
      "favourite": 19,
      "thumb": "https://oss.adquan.com/upload/20180403/1522742000e95ce34528a374ff.jpg",
      "source_url": "https://m.adquan.com/creative/detail/43993",
      "title": "为了不让孩子输在起跑线上，优衣库和小猪佩奇合作了！",
      "description": "一时间朋友圈变了模样，不管是80后，90后，还是00后，争相用它作为头像、表情包，甚至用它的生活格言来当做自己的人生指南。没错，就是它，我们的偶像——小猪佩奇。 小猪佩奇，无疑是眼下最网红的卡通形象。 《小猪佩奇》（Peppa Pig）是一部学前电视动画片，2015年被引进中国。故事的主角佩奇是一只正在上幼儿园的小猪，二维动画线条简单，色彩明快，情节也并不复杂，讲述的无非是佩奇一家人的生活，还有在幼儿园和小朋友们玩耍的那些事。 江湖上甚至流传出一句令人闻风丧胆的豪言壮语：小猪佩奇纹上身，掌声送给社会人！ 那么问题来了：当今社会亮出尊贵身份的logo是什么？ 当然是小猪佩奇咯。 3月29日，优衣库官方微博置顶推送中说明，优衣库将和小猪佩奇合作推出最新一季的幼儿款UT和婴儿睡衣。 小猪佩奇合作款将会是优衣库史上最“潮”的婴幼儿装，让孩子们从小赢在起跑线上。 优衣库官博账号甚至与粉丝在留言区进行互动“小猪佩奇穿上身……”。粉丝们纷纷响应，在评论区留言“从小培养涩费人”、“今天我是社会人”、“掌声送给社会人”。 优衣库就是一个如此深谙消费者喜好的“社会”品牌，品牌联名合作从未间断过。下面，我们来一起回顾优衣库与其他品牌经典合作系列。 “+J”by Jil Sander 简约主义女王 Jil Sander 离开自己同名品牌后与优衣库展开合作，以“成衣”式大量、快速的经营方式与她的简约设计融合，贯彻 Jil Sander 辨识度极高的单色设计、扎实的触感和简约立体的线条，如今看来仍无减其时尚味道。 “T-Down”by Theory 在 2003 年，Rosen 向优衣库母公司迅销集团售出 Thoery 大部分的股份，并将资金投资在 Alice + Olivia、Rag & Bone 等新晋品牌上，打造出如 LVMH 般的时尚王国。而 Theory 现作为迅销集团一部分，在 2012 年 Theory 曾与优衣库推出过一系列名为“T-Down”羽绒服系列，设计简约到位，不过在人气方面不可与 +J 同日而喻。 “uu”by UNDERCOVER 早在2011 年 6 月，UNIQLO 与高桥盾主理的 UNDERCOVER 签定合作协议，推出联名系列，消息一出，震撼整个日本时装界。在 2012 年春夏正式以“uu”之名登场，随即展开抢购的热潮。 UT by NIGO 在 2014 年——UT 创立十周年，优衣库特别邀请潮流教父 NIGO 担任首位 UT 系列创作总监，以“THE NEW MODEL T”作为企划主题，将 Tee Print 以 NIGO 过往主理 A BATHING APE 时的经验作重新构想，贯彻 NIGO 擅长的美式怀旧风格，反复斟酌各类印花图案，精挑细选反映时下 Pop Culture 的元素，重新设计超过 1000 枚 Print Tee，展示出 NIGO 深厚的设计功力。 UT by Pharrell Williams 优衣库在NIGO UT成功后，邀请Pharrell Willianms加盟UT创组阵容，推出“I am other”系列，整个系列充满Pharrell Willianms个人风格，Tee款和帽款皆印有“Think Other”与“THE SAME IS LAME”等Pharrell的独特口号，男装部分体现了设计师对于时尚细节的追求，系列火速售尽。 “ Urban Sweats”by Alexandre Plokhov 在 2014 秋冬季度，优衣库特别邀请了 Helmut Lang 的男装俄裔总设计师 Alexandre Plokhov 来设计限量的“Urban Sweats”系列。全系列以棉布作设计主体，设计上并非 Alexandre Plokhov 签名式的暗黑哥德风格，而是依循素有简约大师之称的 HELMUT LANG 之设计进路，签名式简洁俐落的线条加上富立体感的版型，以暗黑及浅灰棉布打造，只需数百元便能入手当红 Hi-fashion 设计师的作品。 “Life Wear”by Carine Roitfeld Carine Roitfeld 是现在最火红的 Fashion Insider 之一，在 2015 年与 UNIQLO 的联名系列，将“Life Wear”概念以更时尚的风格演绎，把自身对于时尚的洞彻力注入当中，从她个人的时尚打扮出发，由 UNIQLO 设计总监瀧泽直己亲自监修，打造出能令女性感到自信的衣服。 “Lemaire”by Christophe Lemaire Lemaire x UNIQLO是由 Hermès 创意总监 Christophe Lemaire 的同名品牌 Lemaire 所主导，以简约设计风格作为基调，将 Lemaire 简约设计风格，配合上 UNIQLO LifeWear 的日常服概念，每件服饰都是衣橱中不可或缺的元素，以精心挑选的素材制作。 UNIQLO X 草间弥生 UT与草间弥生的合作想必热爱优衣库与日本设计师的粉丝都不会陌生。这个喜爱波点的“密集恐惧症杀手”设计师草间弥生，是日本前卫艺术家的代表。 UNIQLO X 星球大战 优衣库致敬星球大战，在40周年纪念时推出合作款。其中的“我是你爸爸”UT更是火爆全世界，连某宝高仿都要卖断货。星战迷们仿佛穿上了这些UT就可以手持光剑让原力觉醒参与星球大战。 UNIQLO X Line Friends 和Line Friends合作款有多款卡通形象供选择，其中有CONY兔、BROWN熊、MOON馒头人、SALLY小黄鸭、部长…T恤多为情侣款。 UNIQLO X Futura Futura是一位15岁就开始街头创作的艺术家，他开创了抽象主义街头涂鸦的先河。在Futura的作品中，主要有原子图案、The Pointman（外星人）、泼墨图像和手绘字体这四个关键元素，极具科幻和未来感。同时Futura作为涂鸦艺术界活着的传奇，用点、线、面这基本的概念打破了街头涂鸦便是涂几个“设计过的字母”这种既定概念，这也是为什么在诸多涂鸦大师中，唯独Futura被视为教父的原因，以我们最简单的视角来看，Futura的这些作品要比涂几个字母有艺术感多了。 UNIQLO X Andre 作为涂鸦界的后起之秀，Andre 非常爱用粉红、柠黄、天蓝等鲜艳明快的色彩。上世纪 90 年代末，他在巴黎举办了“Love Graffiti Project”，大受喜好浪漫的法国人欢迎。 UNIQLO X KAWS KAWS以往作品的精髓，向潮流经典致敬。KAWS标志性的心形和云朵图案，也被用来扩展了他所创作的家喻户晓的原创形象“COMPANION”。与KAWS以往风格不同的是，本系列将包含全身覆盖图案的UT款式。每一件单品都在细节处匠心独具，例如KAWS标志性的“XX”图案在左袖和胸部的巧妙运用。 UNIQLO x Marimekko 创立于 1951 年的 Marimekko，可以说是芬兰的国民品牌了。连美国前任总统肯尼迪的夫人，都是它的粉丝。它主营纺织品和服装，也会和其他品牌跨界合作，推出林林总总的生活用品。色彩斑斓的印花图案，是它的招牌。对于本次的合作，Marimekko 十分看重，还派出了当家设计师 Maija Louekari 亲自操刀。UNIQLO 和 Marimekko 的联名系列，会主打 LifeWear 精神。 优衣库在品牌合作这条路上不停地给消费者制造惊喜，同时兼顾不同年龄、消费水平、喜好的群体。2018年优衣库依然会推出更多的UT品牌合作系列，哪一个品牌合作你最期待呢？ 当然了，最可爱的佩奇款你是穿不了了，想都不要想。",
      "main_image": "https://oss.adquan.com/upload/20180403/1522742000e95ce34528a374ff.jpg",
      "images": [
        "http://file.adquan.com/image_upload/server/upload/52c5cb30eb49696ff3b87b86c27bfee6.gif",
        "http://file.adquan.com/upload/20180403/152274084579668c627b28868f.jpg",
        "http://file.adquan.com/image_upload/server/upload/2624922a9ff7cf37ff6ebdf387de2e46.gif",
        "http://file.adquan.com/upload/20180403/152273994033278b8b8d3208e4.jpg",
        "http://file.adquan.com/upload/20180403/152274193664bcc197d2782c7d.jpg",
        "http://file.adquan.com/upload/20180403/152274061328b1beb78d7f00b4.jpg",
        "http://file.adquan.com/upload/20180403/15227490101f8ad23eee56a4fe.jpg",
        "http://file.adquan.com/upload/20180403/1522747913c2f52bef462fd6e9.jpg",
        "http://file.adquan.com/upload/20180403/1522748798bcd8681d7ba8bc1a.jpg",
        "http://file.adquan.com/upload/20180403/15227426053df7f0063b9e255f.jpg",
        "http://file.adquan.com/upload/20180403/1522748237f22867dd7a596ee1.jpg",
        "http://file.adquan.com/upload/20180403/15227491094b168bd5dccda7de.jpg",
        "http://file.adquan.com/upload/20180403/1522749347d64af9cc12f2f96d.jpg",
        "http://file.adquan.com/upload/20180403/15227497337705c783a8ed0214.jpg",
        "http://file.adquan.com/upload/20180403/1522750129f57e5fdfd6b9002f.jpg",
        "http://file.adquan.com/upload/20180403/1522750445cd23fbdc4b7ea449.jpg",
        "http://file.adquan.com/upload/20180403/1522750658c666e3ed9e986f30.jpg",
        "http://file.adquan.com/upload/20180403/1522751337be23e837ed48670f.jpg",
        "http://file.adquan.com/upload/20180403/152275150400e60082ab226a6b.jpg",
        "http://file.adquan.com/upload/20180403/1522751885c9fdefe24e8c6391.jpg",
        "http://file.adquan.com/upload/20180403/15227526647fcd2cfac46bee16.jpg",
        "http://file.adquan.com/upload/20180403/1522752087616e54c2ea8f0404.jpg",
        "http://file.adquan.com/image_upload/server/upload/9d1d90d19136bd2d83d1dace69e4a828.gif"
      ],
      "author": "魏星",
      "publish_time": "2018-04-04",
      "brand_industry": "时尚、美妆",
      "activity_type": "平面",
      "location": "中国大陆",
      "tags": [
        "优衣库",
        "小猪佩奇"
      ]
    },
    {
      "case_id": 43815,
      "score": 5,
      "score_decimal": "9.3",
      "favourite": 29,
      "thumb": "https://oss.adquan.com/upload/20180322/15216914136887c3680e3c03bb.jpg",
      "source_url": "https://m.adquan.com/creative/detail/43815",
      "title": "为了纪念70周年，“硬汉”路虎写了一封情书",
      "description": "今年路虎已经70岁啦！人活70古来稀，对于人类，这是一段漫长的旅程，而对于一个经典品牌而言，仅仅是一个开始。为了纪念70岁的生日，Kite Rock Pictures 为路虎制作了一则主题为“The Road”的广告片。 片中的主角是一对相互扶持的老夫妇，影片温柔细腻的捕捉着每一缕阳光，每一条苍老的皱纹，妻子拿起相机为丈夫照相，胶卷中 丈夫年轻的样子，经历的磨难走马观花的出现，而路虎则一路陪伴。携手走过的路是夫妻间最深沉的告白，也是品牌的一封情书，以此象征无论过往，无论今后，无论阳光正好，无论风雨侵袭，路虎将始终勇往直前，一路陪伴探索未知事物，征服新天地。与方方正正，“硬汉”气息十足的路虎相配，这则广告片显得柔和优雅，也正是这种反差，凸显了坚硬的壁垒所给予的温柔陪伴。 与威利斯Jeep和奔驰G-Wagen等越野车不同，Land Rover造越野车的初衷并不是以军队订单为目的。而是Rover（罗孚公司）为了开发新车种，完善旗下产品序列，决定研发一款轻型农用越野车。 在1948年举行的阿姆斯特丹车展上，Land Rover Series I正式发布，路虎品牌正式诞生。一经推出便大受欢迎，同时受到英国军方的关注。换代车型Series II系列成功延续了第一代的光芒，成为英国皇室用车。此后的路虎一路高歌，时不时在电影里客串一把。 路虎卫士《古墓丽影》版 路虎卫士《007幽灵党》版 路虎《红海行动》版",
      "main_image": "https://oss.adquan.com/upload/20180322/15216914136887c3680e3c03bb.jpg",
      "images": [
        "http://file.adquan.com/upload/20180322/15216892331218441ed50a5bd7.png",
        "http://file.adquan.com/upload/20180322/15216892665b64b6f48d95c75d.png",
        "http://file.adquan.com/upload/20180322/15216892890f1d1d17ad283ada.png",
        "http://file.adquan.com/upload/20180322/15216866890818e21ed209ec1d.jpg",
        "http://file.adquan.com/upload/20180322/152168675627ea98be605fbbe9.jpg",
        "http://file.adquan.com/upload/20180322/1521686831a25be9afeb3d2549.jpg"
      ],
      "video_url": "http://v.qq.com/iframe/player.html?vid=s0610jss89l&tiny=0&auto=0",
      "author": "Garbo",
      "publish_time": "2018-03-22",
      "brand_industry": "汽车",
      "activity_type": "影视",
      "location": "美国",
      "tags": [
        "路虎",
        "美国"
      ]
    },
    {
      "case_id": 293087,
      "score": 4,
      "score_decimal": "8.4",
      "favourite": 9,
      "thumb": "https://oss.adquan.com/upload/20200323/158495482082d0d8ab3bb2a800.png",
      "source_url": "https://m.adquan.com/creative/detail/293087",
      "title": "这些国外防疫宣传，让人哭笑不得",
      "description": "近期国外疫情严重，为了引起人们的重视，各种防疫宣传也是层出不穷。 澳大利亚The Feed SBS推出一支新冠防疫短片，提醒人们重视疫情。短片以诙谐幽默的形式，讲述疫情期间一对情侣见面的场景，但画风不仅不虐狗，还处处透着沙雕。见面要先洗手，无意间的清嗓就让人紧张，最后的深情告白，却成了爱情终结语。反转的剧情，让既想笑又想哭。 意大利老奶奶的忠告，威严带着俏皮，霸气又不失可爱，还一边劝说，一边亲身示范，没有苦口婆心的讲大道理，而是用贴近年轻人的语言风格让大家做好个人防疫，让人倍感亲切。 法国社保局的防疫短片，将各种防疫注意事项融入舞蹈，通过不断的动作重复加深人们自我防范的意识，既生动形象的宣传了防疫知识，又不失浪漫的生活情调。",
      "main_image": "https://oss.adquan.com/upload/20200323/158495482082d0d8ab3bb2a800.png",
      "images": [],
      "video_url": "https://v.qq.com/txp/iframe/player.html?vid=r0934pea3w6&tiny=0&auto=0",
      "author": "邢焕",
      "publish_time": "2020-03-24",
      "brand_industry": "互联网",
      "activity_type": "微电影",
      "location": "中国大陆",
      "tags": [
        "防疫",
        "抗疫"
      ]
    }
  ]
}