{
  "batch_num": 49,
  "batch_size": 10,
  "created_at": "2026-01-18T23:35:12.447242",
  "cases": [
    {
      "case_id": 43177,
      "score": 5,
      "score_decimal": "9.5",
      "favourite": 6,
      "company_name": "火橙战略咨询",
      "company_logo": "https://oss.adquan.com/logos/1679629090194507.jpg",
      "thumb": "https://oss.adquan.com/upload/20180112/1515738265a7387b823c83dd44.jpg",
      "source_url": "https://m.adquan.com/creative/detail/43177",
      "title": "如何走出一条逍遥之路？",
      "description": "出发，有目的，却未必要有目的地 奔跑，寻找，自然里无畏，驭风涉水 不羡坦途，直面崎岖 美，在路上，在心上 疲惫生活，做一个梦想复燃的英雄 我的路，自逍遥 车非车，它有自己的灵魂， 它在不同的环境，有变化有情绪， 它沐尘，它涉水，它攀巅， 它主动实现，它要展示自己的魅力，它自己性能爆发。 不用刻意，只是精挑细选， 找到“自然的场”，把车放在那，任其逍遥， 陆风逍遥的美， 就诞生了。 陆风逍遥TVC 导演版 2018年初，陆风集团为年轻消费者定制的陆风逍遥，采用了新潮的跨界SUV风格，时尚运动，令人耳目一新。火橙携手广东因赛集团为陆风逍遥跨界SUV的上市推出了这支全新广告TVC。",
      "main_image": "https://oss.adquan.com/upload/20180112/1515738265a7387b823c83dd44.jpg",
      "images": [
        "https://oss.adquan.com/image_upload/server/upload/20180112/cceb166b29b89ebbfac3b1779d58cce1.gif",
        "https://oss.adquan.com/image_upload/server/upload/20180112/d05b1406f2f3f959c09dcd81ea161a9c.gif",
        "https://oss.adquan.com/image_upload/server/upload/20180112/b107e6cc7f94dddb246a8c7436e8cb17.gif",
        "https://oss.adquan.com/image_upload/server/upload/20180112/d678f3612b4208843181b06aaacf62ac.gif",
        "https://oss.adquan.com/image_upload/server/upload/20180112/4dd41410550aa708ff37cd52380557e6.gif"
      ],
      "video_url": "http://v.qq.com/iframe/player.html?vid=s0530tmawts&tiny=0&auto=0",
      "author": "roxy",
      "publish_time": "2018-01-12",
      "brand_industry": "汽车",
      "activity_type": "影视",
      "tags": [
        "陆风逍遥"
      ]
    },
    {
      "case_id": 355819,
      "score": 4,
      "score_decimal": "8.7",
      "favourite": 4,
      "company_name": "Qunar.com 去哪儿网等2家公司",
      "company_logo": "https://oss.adquan.com/logo/20161208193334_19309_320.png",
      "thumb": "https://oss.adquan.com/upload/2025092657332a95f9ccfb8b.jpg",
      "source_url": "https://m.adquan.com/creative/detail/355819",
      "title": "去哪儿旅行×何广智：玫瑰！去哪儿旅行都没贵！",
      "description": "就在我们团队正激烈讨论周末去哪儿的时候，我们接到了去哪儿旅行的十一需求。 十一去哪儿还没定，去哪儿的十一先来了！ 这次的brief是一个半命题作文：在去哪儿的十一大促期间，将旅行与「脱口秀」热点做结合，从「情绪+低价」的角度打造十一低价营销策略。 也算是专业对口了！团队里的小伙伴刚好对脱口秀都比较感兴趣，两档节目都有在追，但这次的项目还是有一个巨大的难点： 旅行和脱口秀究竟有什么关联呢？！ 我们开始思考旅行对人的意义是什么。它可以是一个爱好，可以是一种职业，也可以是一场逃离，我们好像很难找到一个能让大家都有共情的洞察。 直到加完班，点好外卖，点开最新一期的脱口秀节目，当我们不带任何思考的笑出声来时，才猛然发现，或许旅行的意义在某些方面上和脱口秀是一样的——都能给我们带来 一种纯粹的快乐 。 打工人需要在周末打开视频App，看会儿脱口秀让自己的“精神”笑一笑； 也需要在节假日打开去哪儿旅行App，换个城市让自己的“身体”笑一笑。 想到脱口秀，既能让人开心，又能让大家联想到省钱的人选也自然浮现在脑海里——何广智，而且大家对旅行的期许、去哪儿旅行的“比价”优势都和广智的“穷门”不谋而合，穷门不是抠门，旅行便宜重要， 但是体验更重要。 一样好的东西，去哪儿旅行就是更省更便宜。 因此我们决定通过何广智的“穷门”人设，向用户传达去哪儿旅行可以让用户少花点钱，多点快乐的理念； 去哪儿旅行能在十一让用户用更便宜的价格，享受同质量甚至更高质量的旅行，让旅行更有质价比。 这个想法与客户一拍即合！ 我们的主题也应运而生，希望大家可以上去哪儿旅行App—— 比个低价，度个好假 有人在听段子，有人在照镜子，在TVC中我们试着将打工人遇到的情绪和问题与旅行建立链接，进行“广智”式的段子包装，唤起消费者内心对旅行的渴望。 你看这个大海，他就不问你什么专业，你可以专业划水，专业摸鱼，专业躺平； 这个大山虽然你也得抬头看它，但是它不用你向上管理，靠努力是真能爬上去； 还有到了草原才知道，不仅可以放牛、放马，还可以放自己一马； 旅行就是成年人的课间十分钟，似乎格子间里的所有的坏情绪，在山川湖海中都悄然和解了。在段子中，用不说教的方式自然完成了十一期间对消费者出行的号召。 做长视频广告固然很冒险，分段式似乎是更好解题方式。但看完了，不等于看进去了，我们和客户都还是 相信真诚的内容一定会有回响 ，这里真的很感谢客户的信任和满满的情绪价值！ 这条广智味儿满满的TVC也不负众望， 获得了不少广智粉丝的认可！ 不枉创意同学看遍广智所有线上脱口秀又熬了几个大夜才磨出来的本子，真的是每一场都能背下来了。 我们摘了几句VO，又做了一组广智味儿十足海报： 广智友情提醒：放自己一马吧，该去哪儿旅旅行啦！ 我们都和脱口秀大王搭上线了， 少了脱口秀怎么行？ 让广智成为打工人的代表，用脱口秀的形式作为打工人的嘴替！ 在脱口秀中融入了职场的段子，并双关旅行中的爽点，以此来 传递旅行带给用户带来的正向价值与去哪儿的低价感知 ，在一片爆笑声中激发用户对旅行的冲动和向往感。 十一还没到，我的精神先上路了！ 虽然精神已经上路了，但是十一去哪儿才能度个好假呢？！ 别担心！去哪儿旅行也给大家提供一点小思路，请看大屏幕～ 去哪儿旅行App联动了青岛、阿克苏、广东、福州、成都、五指山和芜湖7个热门旅游城市，并与各种打工人的7种职业做融合， 产出了7条略带魔性反转的文旅病毒视频。 同时，去哪儿旅行App还在成都、青岛和福州三座城市分别承包了一块大屏， 融合了当地特色元素进行文案创作 ，希望来旅行的各位都能告别班味儿，好好享受旅行！ 甭管十一去哪儿旅行，去哪儿旅行App都会陪大家一起度个好假！ 再次感谢去哪儿客户的信任，以及制作团队的专业！项目结束了，十一也快到了，该去哪儿四处看看啦！ 我们已经帮大家多平台横向比过价了，去哪儿是真的便宜！ 希望大家 十一都能上去哪儿比个低价，度个好假！！！ 带刺的玫瑰，助你走遍世界都“没贵”！",
      "main_image": "https://oss.adquan.com/upload/2025092657332a95f9ccfb8b.jpg",
      "images": [
        "https://file.adquan.com/uploads_img/1758880874f9dj3.GIF",
        "https://file.adquan.com/uploads_img/1758880897a7ob9.gif",
        "https://file.adquan.com/uploads_img/1758880910lgowv.gif",
        "https://file.adquan.com/uploads_img/17588809208eixk.gif",
        "https://file.adquan.com/uploads_img/1758880942rjkeb.png",
        "https://file.adquan.com/uploads_img/1758880959jsmp4.jpg",
        "https://file.adquan.com/uploads_img/17588809592teyx.jpg",
        "https://file.adquan.com/uploads_img/1758880979wkvu2.GIF",
        "https://file.adquan.com/uploads_img/1758881089r64bg.png",
        "https://file.adquan.com/uploads_img/1758881100no90x.png",
        "https://file.adquan.com/uploads_img/1758881115iu2r5.GIF",
        "https://file.adquan.com/uploads_img/175888112553kqd.jpg"
      ],
      "author": "THINKPARK思库传播",
      "publish_time": "2025-09-28",
      "brand_industry": "旅游、交通",
      "activity_type": "整合营销",
      "location": "中国大陆",
      "tags": [
        "去哪儿",
        "何广智"
      ]
    },
    {
      "case_id": 350402,
      "score": 5,
      "score_decimal": "9.3",
      "favourite": 2,
      "company_name": "Jissbon 杰士邦",
      "company_logo": "https://oss.adquan.com/logo/20140114121534_17869_320.png",
      "thumb": "https://oss.adquan.com/upload/1741142569b52e0cafb9177a9c.jpg",
      "source_url": "https://m.adquan.com/creative/detail/350402",
      "title": "杰士邦三八妇女节广告请来了Olga姐姐",
      "description": "当性话题热度提升，女性能拥有更多主动的选择吗？ 杰士邦和 一条 对话了 Olga姐姐、 吴征大飘飘的游乐场 、蔡嘉茵她们或谈论自己的爱与欲望，或带领女性探索身心，或进行亲密戏指导实践，诠释「主动」带来的力量。我们/WOMEN主动，更多可能。",
      "main_image": "https://oss.adquan.com/upload/1741142569b52e0cafb9177a9c.jpg",
      "images": [],
      "author": "源泉",
      "publish_time": "2025-03-05",
      "brand_industry": "快消品",
      "activity_type": "影视",
      "location": "中国大陆",
      "tags": [
        "Olga",
        "杰士邦"
      ]
    },
    {
      "case_id": 340430,
      "score": 5,
      "score_decimal": "9.0",
      "favourite": 11,
      "company_name": "McDonald’s 麦当劳等2家公司",
      "company_logo": "https://oss.adquan.com/logos/1727344407b40ad44aada194cf.jpg",
      "thumb": "https://oss.adquan.com/upload/20240220/1708399481b35a39aa579e3951.png",
      "source_url": "https://m.adquan.com/creative/detail/340430",
      "title": "麦当劳拍歌剧，所有人都被“定”住了",
      "description": "法国麦当劳发布全新广告，由 TBWAParis 制作。 对麦当劳的渴望是难以控制的，而想吃却吃不到的麦当劳是令人沮丧的。法国麦当劳用这支洞察力和娱乐性相结合的广告片，宣传 McDo+送货上门服务。",
      "main_image": "https://oss.adquan.com/upload/20240220/1708399481b35a39aa579e3951.png",
      "images": [],
      "author": "永刚",
      "publish_time": "2024-02-20",
      "brand_industry": "快消品",
      "activity_type": "影视",
      "location": "中国大陆",
      "tags": [
        "麦当劳",
        "TBWA\\Paris"
      ]
    },
    {
      "case_id": 345401,
      "score": 3,
      "score_decimal": "6.0",
      "favourite": 3,
      "company_name": "Apple 苹果等2家公司",
      "company_logo": "https://oss.adquan.com/logos/1545102800611000.jpg",
      "thumb": "https://oss.adquan.com/upload/20240726/1721968565657211.jpg",
      "source_url": "https://m.adquan.com/creative/detail/345401",
      "title": "Mac 学生 “Mac与泡面”",
      "description": "苹果首次针对中国本土大学生展开 Mac 广告活动，推出了一部纪录片式的社交影片，由三位 Z 世代学生创作者主演，展现 Mac 是如何成为他们探索道路上最得力的助手。通过他们的真实故事，我们希望点燃 Z 世代的雄心壮志，并激励他们用 Mac 不断探索，从而创造属于自己的未来。 何同学，作为 Bilibili 平台（深耕中国 Z 世代的长视频平台）最知名的创作者之一，将在泡面的陪伴下和其他两位学生创作者踏上探索之旅，尝试音乐制作和追风。作为中国学生校园生活的经典元素，泡面充满象征意义，为无数个学习和探索的夜晚提供了快速能量补给。就像 Mac 为学生的探索提供动力一样，泡面也为他们的大学之旅提供能量。 影片由 iPhone 15 Pro 拍摄，展现了年轻创作者如何用 Mac 在传统道路之外尽情探索： 对气候科学充满热情的摄影专业学生苏镝坷同学，善于将理工知识与内容创作相结合，向公众宣传气象常识。由于 Mac 的持久电池续航力，作为狂热的追风者，苏镝坷同学可以在户外探索数小时都不需要给 Mac 充电。 就读于文化管理专业，同时充满音乐理想的邓艺菲同学，能够在学业和音乐创作之间取得平衡。在 Apple 芯片的超强性能和 GarageBand 库乐队的帮助下，邓艺菲同学得以在 Mac 上随时随地创作音乐。 何同学使用 Mac 将富有想象力的科技概念转化为引人瞩目的发明，让他持续为在Bilibili 上的 1100 多万粉丝带来奇思妙想的内容。 从课内学业到课外探索，Mac 凭借 Apple 芯片的超强性能、持久的电池续航力以及与iPhone 的连续互通功能，为学生和内容创作者提供动力，确保他们都能发挥出最大的潜力，奔赴下一场探索。展示的 app 包括 Pages 文稿、 Numbers 表格、WPS、DaVinci Resolve、Final Cut Pro、Adobe Photoshop、GarageBand 库乐队和 QGIS。 该广告活动将在数字媒体和社交媒体平台发布。 影片中的Mac 产品： 何同学: MacBook Air 苏镝坷: MacBook Pro 邓艺菲: MacBook Air Credits: 代理商: TBWAMedia Arts Lab Shanghai 制作公司: Lunar Films 后期: The Mill (Shanghai) 导演: James Cai 音乐: 邓艺菲SuperA",
      "main_image": "https://oss.adquan.com/upload/20240726/1721968565657211.jpg",
      "images": [
        "https://file.adquan.com/uploads_img/1721967921g2s95.jpg"
      ],
      "author": "TBWA\\China 腾迈中国",
      "publish_time": "2024-07-26",
      "brand_industry": "数码、通讯",
      "activity_type": "影视",
      "location": "中国大陆",
      "tags": [
        "TBWA",
        "Apple"
      ]
    },
    {
      "case_id": 336676,
      "score": 4,
      "score_decimal": "8.0",
      "favourite": 9,
      "company_name": "美团等3家公司",
      "company_logo": "https://oss.adquan.com/logos/1677757897511982.jpg",
      "thumb": "https://oss.adquan.com/upload/20231012/1697094331933337.jpg",
      "source_url": "https://m.adquan.com/creative/detail/336676",
      "title": "美团团购 X 时趣：这个夏天的综艺在治愈，赞助的品牌在发疯",
      "description": "众所周知，资源硬广和social营销之间的依存共生性，就像鱼和自行车。 接到客户brief时，我们意识到这是一个在yes or no中选择or 的工作——既不是综艺节目宣发，也不是品牌宣发，而是为 美团×《现在就出发》综艺赞助 这件事做宣发。 而节目综艺中的品牌露出，基本以口播、中插、平面物料等硬广为主的形式呈现。而我们此次需要做的，是搭载 娱乐综艺 ，将 品牌硬广 以 social形式 进行宣发和话题策划，这三个词，诸位您也看见了，谁也不挨谁。 但决定接手这个项目倒不是因为团队里有一个范丞丞粉丝、一个沈腾粉丝、和一个贾冰粉丝（新晋），而是我们认真地觉得这件事不仅能搞，而且一定能搞好。不为别的，单纯觉得social营销的先提条件不该被限制得太苛刻。有爆点、笑点、雷点、热点、敏感点和话题点加持傍身的social营销做了不少，把硬广素材做成有梗热点的挑战是元旦翻日历，头一回。 比稿期间的顺利赢标，就不在此多赘述了，当然得是我们（叉腰）。执行阶段的第一个任务，就是把节目中插广告送上野生热搜。 美团项目第三方团队传播物料 顺便放送几个没来得及（不敢）出街的表情包： 感谢东北老铁送来的笑点，也感谢这个节目带来的治愈。文末最后，允许我们打一句广告： 美团团购，让你省个够 。 项目总监：徐洪迅 项目执行：曾文欣 传播策划：孟佳慧 创意文案：胡逸文 策略支持：吴晨光 撰文：孟佳慧",
      "main_image": "https://oss.adquan.com/upload/20231012/1697094331933337.jpg",
      "images": [
        "https://file.adquan.com/uploads_img/16970945172nelz.png",
        "https://file.adquan.com/uploads_img/1697094597hlin5.png",
        "https://file.adquan.com/uploads_img/16970954181zwgf.png",
        "https://file.adquan.com/uploads_img/1697095450ykgm1.png",
        "https://file.adquan.com/uploads_img/1697095479bo48p.png",
        "https://file.adquan.com/uploads_img/1697095535hoymj.png",
        "https://file.adquan.com/uploads_img/1697095542pa3jv.png",
        "https://file.adquan.com/uploads_img/1697095578x6394.jpg",
        "https://file.adquan.com/uploads_img/16970955925kwxt.png",
        "https://file.adquan.com/uploads_img/16970956279opr8.jpg",
        "https://file.adquan.com/uploads_img/1697095641po674.jpg",
        "https://file.adquan.com/uploads_img/1697095688ly134.jpg",
        "https://file.adquan.com/uploads_img/1697095705d3ire.jpg",
        "https://file.adquan.com/uploads_img/1697095723ts7e1.jpg",
        "https://file.adquan.com/uploads_img/1697095737or2w3.jpg",
        "https://file.adquan.com/uploads_img/1697095822klzxo.jpg"
      ],
      "author": "时趣",
      "publish_time": "2023-10-12",
      "brand_industry": "互联网",
      "activity_type": "社会化营销",
      "location": "中国大陆",
      "tags": [
        "时趣",
        "美团团购"
      ]
    },
    {
      "case_id": 333874,
      "score": 4,
      "score_decimal": "7.6",
      "favourite": 7,
      "thumb": "https://oss.adquan.com/upload/20230704/1688460234b04d1c57b60f7b87.png",
      "source_url": "https://m.adquan.com/creative/detail/333874",
      "title": "汗！网飞广告，玩的就是真实",
      "description": "北京现在气温已经飙升到40度+了，炎炎夏日，汗腺发达的人可以说是经常饱受流汗的痛苦。 但除了炎热的夏日，人在紧张的时候也会狂飙汗液。就比如一些紧张的时刻。 最近网飞就在街头放出了克里斯·海姆斯沃斯主演的《惊天营救2》的街头广告海报，乍看之下平平无奇的广告背后其实暗藏玄机。 没错，如此紧张的场景下，克里斯·海姆斯沃斯竟然真的在流汗！ 这个广告牌利用定时循环水系统和背后的水泵在为广告牌供水，同时广告牌上有很多密集的小洞，营造出主角在危险瞬间流汗紧张的氛围。",
      "main_image": "https://oss.adquan.com/upload/20230704/1688460234b04d1c57b60f7b87.png",
      "images": [
        "https://file.adquan.com/uploads_img/1688458652cp287.png"
      ],
      "author": "源泉",
      "publish_time": "2023-07-04",
      "brand_industry": "互联网",
      "activity_type": "装置/陈列",
      "location": "美国",
      "tags": [
        "网飞",
        "Netflix"
      ]
    },
    {
      "case_id": 349331,
      "score": 4,
      "score_decimal": "8.0",
      "favourite": 4,
      "company_name": "小红书等2家公司",
      "company_logo": "https://oss.adquan.com/com_info/20220301/16461251218e1db33ab7248a0f.jpg",
      "thumb": "https://oss.adquan.com/upload/2025011547aba11213c56b00.jpg",
      "source_url": "https://m.adquan.com/creative/detail/349331",
      "title": "小红书雪人节2.0：冬天到了，去雪地白捡快乐",
      "description": "雪给世界留了片「白」 也给我们的快乐留了个空___ 白给的快乐在雪上❄️ 白给的快乐更在 #小红书雪人节 伴着「大雪」，雪人节2.0正式启动 两大场地白给快乐 指北集结 在阿勒泰，开启对“人类滑雪起源地”的刺激探索之旅。体验“赏雪猎人”的生活，在起源地寻找古老民族滑雪的生活痕迹。边滑雪，边感受最“刺激的快乐”。 在哈尔滨，雪小花的快乐信号为雪人们带来一场魔法般的福利派送。在哈尔滨快乐玩雪，与冰雪使者一起进入雪世界！边玩雪，边感受最“轻松的快乐”。 刺激的快乐阿勒泰 指北目的地 雪猎们！领取一份猎人手册，加入为期三天的阿勒泰雪上刺激之旅。 前往三大雪域，开启不一样的玩法之旅。在滑雪区，白天夜里畅快玩雪，一秒get冬季北国白色的快乐；在冒险区，体验各种雪上玩法，让肾上腺素充分被激发；在探索区，让双手动起来，感受最原始的雪地玩法。 这次破冰来真的破冰，做最原始的快乐雪人，与大雪人、安陵容一起抽象开板。 在冒险区，挖挖挖、滑滑滑、堆堆堆……解锁雪上的各种快乐玩法。 在探索区，亲手打造手工木制品，一起植出一棵「白给快乐树」。 完成滑雪、玩雪、探雪各项活动，即可解冻雪人节2.0的「形象大使」雪小花。获得表情包徽章与认可奖牌，串成一串挂在身上，即刻成为雪中最显眼的显眼包。 玩累了，就来雪山顶上，跟随DJ的节奏燃爆这个夜晚。 当然还有人气超高的经典老番，在雪地里，一起点燃最浪漫的烟火。雪委会们特备大、中、小各种类型的烟花，为雪猎们提升远、中、近各个视角的全面浪漫体验。 不可错过的品牌好友也来到了阿勒泰。让颜值被百分百保障，打造雪景缆车与日落打卡框，和华为一起，记录最美雪景，定格起飞一刻。 还有暖冬好友雪山集合铺与飞鹤冰雪聪明顿顿车，用汤圆、火锅、热奶为阿勒泰的各位雪猎们提供必需的热量！ 轻松的快乐哈尔滨 雪人们冰城集结！领取哈尔滨全程玩雪地图，搭上冰天雪国列车，探索散落全城的快乐玩法。 在冰天雪国列车的出发地圣·索菲亚大教堂，跟着雪小花一起获得白给的快乐福利！参与冰雪聪明运动会，解锁亚冬会热门项目新玩法；打卡冰雪快乐集合铺，体验一段有关冰雪香氛制作和冰雪好运占卜的冬日奇缘；解锁雪世界快乐巡游，获得更多白给的快乐。 大雪人小雪人化身亚冬会的后备役，即刻热身，火速加入冰雪聪明运动会。 冰雪快乐集合铺限时开放，白给的快乐解冻中…… 冰雪使者诚邀各位雪人们进入雪世界，一起快乐巡游。 继续北上的品牌好友们，这一次来到了哈尔滨。飞鹤冰雪聪明顿顿车，时刻为哈尔滨的大小雪人们提供冰雪聪明趣玩雪的必需热量！ 雪小花与品牌和玩雪主理人手拉手，在哈药六厂开启冰天雪地大集。诚邀大小雪人，一站式开启雪世界好吃的、好玩的、好逛的，这个冬天将快乐值拉满！ *文内图源小红书，如有侵权请联系后台删除 雪委会（思库ver.）说 从零下20度的阿勒泰到零下27度寒风透过羽绒服吹进骨头里的哈尔滨，项目组的同学们不仅承担着心理上的巨大压力，身体上也被北国的寒冬洗礼了一场。如同接力赛般冻伤、感冒、发烧……每天都有新的人倒下，相比希望带给用户们的“简单纯粹白给快乐”，他们的快乐则混合着活性炭与布洛芬的味道。 历经3个月最终圆满落幕，项目组每一次都是在极限中完成着一个接一个的任务。再次让雪人节以快乐的姿态出现在大家的视线中，所经受的所有“苦难”，在项目完美收官那刻，都伴随北国的雪成为了浪漫的一份子。",
      "main_image": "https://oss.adquan.com/upload/2025011547aba11213c56b00.jpg",
      "images": [
        "https://file.adquan.com/uploads_img/1736910057wvker.png",
        "https://file.adquan.com/uploads_img/17369100571wlub.png",
        "https://file.adquan.com/uploads_img/1736910111cf48l.png",
        "https://file.adquan.com/uploads_img/1736910111mshrw.png",
        "https://file.adquan.com/uploads_img/173691026347d62.png",
        "https://file.adquan.com/uploads_img/1736910279oib4m.png",
        "https://file.adquan.com/uploads_img/1736910296t9mk0.png",
        "https://file.adquan.com/uploads_img/1736910296fav5o.png",
        "https://file.adquan.com/uploads_img/1736910296ekocq.png",
        "https://file.adquan.com/uploads_img/1736910297ma0kp.png",
        "https://file.adquan.com/uploads_img/1736910297c0nzg.png",
        "https://file.adquan.com/uploads_img/1736910298qefrx.png",
        "https://file.adquan.com/uploads_img/1736910298yhnkz.png",
        "https://file.adquan.com/uploads_img/1736910298lgf65.png",
        "https://file.adquan.com/uploads_img/1736910299giycq.png",
        "https://file.adquan.com/uploads_img/1736910299gsh4e.png",
        "https://file.adquan.com/uploads_img/1736910301bo9nc.png",
        "https://file.adquan.com/uploads_img/1736910301gzsbn.png",
        "https://file.adquan.com/uploads_img/1736910301nb2p1.png",
        "https://file.adquan.com/uploads_img/1736910302qh54l.png",
        "https://file.adquan.com/uploads_img/1736910303pkntv.png",
        "https://file.adquan.com/uploads_img/1736910304l7cwi.png",
        "https://file.adquan.com/uploads_img/1736910304ir6wc.png"
      ],
      "author": "THINKPARK思库传播",
      "publish_time": "2025-01-15",
      "brand_industry": "生活服务",
      "activity_type": "装置/陈列",
      "location": "中国大陆",
      "tags": [
        "ip",
        "雪人节"
      ]
    },
    {
      "case_id": 334413,
      "score": 4,
      "score_decimal": "8.8",
      "favourite": 5,
      "company_name": "McDonald’s 麦当劳",
      "company_logo": "https://oss.adquan.com/logos/1727344407b40ad44aada194cf.jpg",
      "thumb": "https://oss.adquan.com/upload/20230725/169027168523139c1397048100.png",
      "source_url": "https://m.adquan.com/creative/detail/334413",
      "title": "日本麦当劳电波系广告，再看亿次",
      "description": "日本广告向来以脑洞元素闻名，这次的麦当劳广告虽然没有二次元角色，但却在创意和设计间满满的二次元风味，尤其是视频最后的麦当劳经典balabalaba，更人忍不住让人多听几次。",
      "main_image": "https://oss.adquan.com/upload/20230725/169027168523139c1397048100.png",
      "images": [],
      "author": "源泉",
      "publish_time": "2023-07-25",
      "brand_industry": "快消品",
      "activity_type": "影视",
      "location": "中国大陆",
      "tags": [
        "麦当劳",
        "日本"
      ]
    },
    {
      "case_id": 318146,
      "score": 5,
      "score_decimal": "9.5",
      "favourite": 16,
      "thumb": "https://oss.adquan.com/upload/20220822/1661149897e06449c3e34946ba.png",
      "source_url": "https://m.adquan.com/creative/detail/318146",
      "title": "没有大制作，冰岛银行这广告为什么这么“费钱”？",
      "description": "用计算器不同按钮声组成一首乐曲，大家可能都听过。那用微信/支付宝的支付音效形成的曲子？听起来应该会很悦耳，毕竟是钱到账的声音。 冰岛银行为了推广移动支付服务（非接触式支付），邀请翻唱乐队Bjartar Sövður对美国90年代的一首流行曲《U Can't Touch This》进行重新演绎，其中，他们的“乐器”是手机，声音则是支付时的音效。整体的节奏听起来会是怎样的？ 不难看出，无论是选用的歌曲还是演奏形式，它都非常重点地突出了“非接触式支付”的特点。尤其是对于这首歌了解的人，听的时候可能会更快联想到，无需接触现金、卡片就能完成支付的特点。",
      "main_image": "https://oss.adquan.com/upload/20220822/1661149897e06449c3e34946ba.png",
      "images": [],
      "author": "River",
      "publish_time": "2022-08-22",
      "brand_industry": "金融、保险",
      "activity_type": "影视",
      "location": "欧洲",
      "tags": [
        "非接触式支付",
        "冰岛银行"
      ]
    }
  ]
}